Workbook

Sheet About
A1: Active state name: | B1: Washington | C1: 46184
A2: Active state code: | B2: =INDEX(Geography!B:B, MATCH(B1, Geography!C:C, 0)) -> WA
A3: Active state FIPS: | B3: =INDEX(Geography!A:A, MATCH(B2, Geography!B:B, 0)) -> 53
A4: Active NEMS division #: | B4: =INDEX(Geography!D:D, MATCH(B2, Geography!B:B, 0)) -> 9
A5: Active NEMS division label: | B5: =INDEX(Geography!E:E, MATCH(B2, Geography!B:B, 0)) -> 9 Pacific | C5: (matches the labels used in NEMS_residential col B / NEMS_commercial col B)
A6: Active state HH: | B6: =INDEX(State_demographics!D:D, MATCH(B2, State_demographics!A:A, 0)) -> 3168080
A7: Active state commercial floor (sqft): | B7: =INDEX(State_demographics!E:E, MATCH(B2, State_demographics!A:A, 0)) -> 1.772637e+09
A8: Active state urban share (%): | B8: =INDEX(State_demographics!F:F, MATCH(B2, State_demographics!A:A, 0)) -> 83.371846
A9: Active state rural share (%): | B9: =INDEX(State_demographics!G:G, MATCH(B2, State_demographics!A:A, 0)) -> 16.628154
A10: Division HH (denominator): | B10: =SUMIF(State_demographics!$C$2:$C$49, $B$4, State_demographics!$D$2:$D$49) -> 18709988 | C10: (SUMIF over the 48 state rows of State_demographics, summed by active NEMS division #)
A11: Division floor (denominator, sqft): | B11: =SUMIF(State_demographics!$C$2:$C$49, $B$4, State_demographics!$E$2:$E$49) -> 1.2044315e+10
A12: State HH share within division: | B12: =B6/B10 -> 0.1693256
A13: State floor share within division: | B13: =B7/B11 -> 0.14717624
A15: Workbook
A16: State-level capex on building components (heating, cooling+vent, lighting, appliances) 2024-2050.
A17: Drop-in input for the EPS state model at InputData/bldgs/BASoBC/.
A19: Method (Option A): division NEMS capex x state share within division.
A20: Residential: state_HH_share x national-NEMS division capex. Urban/rural split per state (2020 Census).
A21: Commercial: state_floor_share x national-NEMS division capex.
A23: Envelope and "other component" output = 0 (NEMS source does not report these).
A25: Methodology: docs/methodology/BASoBC.md
A26: Generator: outputs/buildings/_build_BASoBC_workbook.py
A29: state_BASoBC — State BAU Amount Spent on Building Components
A31: Built: 2026-06-08 15:28
A32: Scope: 48 contiguous U.S. states, 2024-2050.
... A47: Generator: outputs/buildings/_build_BASoBC_workbook.py

Sheet Methodology
A1: Methodology summary
A3: Inputs
A4: * NEMS division x component x year capex (residential + commercial) — embedded from the EPS national BASoBC source file (AEO 2015 vintage). 9 census divisions.
A5: * State household counts: ACS 2024 1-year (sources/processed/acs/acs2024_state_housing.csv).
A6: * State commercial floorspace: QCEW-derived 2024 (sources/processed/qcew/state_commercial_floorspace_2024.csv).
A7: * State urban/rural shares: 2020 Census decennial (sources/raw/census/State_Urban_Rural_Pop_2020_2010.xlsx).
A8: * State -> Census division: config/geography/state_to_census_division.csv (using aeo_division_num, the 9-region scheme matching NEMS).
A9: Aggregation: NEMS source -> (division, component, year)
A10: * Source data is row-per-(division, building_type, end_use, fuel, equipment_type). For each (division, EPS_component, year), SUMIFS over all rows where Sum of TOTINVEST applies (residential) or the subtotal rows are present (commercial).
A11: * Component mapping: NEMS end_use -> EPS component per the source mapping tab (e.g. Cooking -> appliances; Cooling -> cooling and ventilation).
A12: * Helper "division_filled" column on NEMS source tabs fills the pivot-style division header downward so SUMIFS can filter by division.
A13: Downscale: division -> state
... A30: * Active state selector: About!B2 (2-letter code). About!B1 displays the derived full state name.

Sheet Sources
A1: Sources for state_BASoBC.xlsx
A3: All citations require staff verification against the primary source before external use, per organizational guidance.
A5: Organization | B5: Dataset | C5: URL | D5: Vintage / Note
A6: U.S. Energy Information Administration | B6: NEMS "Amount Spent on Components" — division x building x end_use x fuel x equipment_type x year | C6: https://www.eia.gov/outlooks/aeo/ | D6: AEO 2015 vintage; available on request from EIA. Embedded via the EPS national BASoBC file (eps-us/InputData/bldgs/BASoBC/).
A7: U.S. Energy Information Administration | B7: Assumptions to the Annual Energy Outlook 2026: Residential Demand Module — Table 4 (per-division rebate percentages) | C7: https://www.eia.gov/outlooks/aeo/assumptions/pdf/RDM_Assumptions.pdf | D7: April 2026. Used to populate the AEO_RDM_rebates reference tab. Confirms NEMS subtracts division-level utility incentives + federal tax credits from sticker cost before reporting TOTINVEST.
A8: U.S. Census Bureau | B8: American Community Survey 1-Year Estimates, DP04 (Selected Housing Characteristics) | C8: https://data.census.gov/table?d=ACS+1-Year+Estimates+Selected+Population+Profiles&tid=ACSDP1Y2024.DP04 | D8: 2024 release. Used: occupied_housing_units per state.
A9: U.S. Bureau of Labor Statistics | B9: Quarterly Census of Employment and Wages (QCEW) state x NAICS sector x ownership | C9: https://www.bls.gov/cew/downloadable-data-files.htm | D9: 2024 annual averages, agglvl 54. Used to derive state commercial floorspace allocation (sources/processed/qcew/state_commercial_floorspace_2024.csv).
A10: U.S. Census Bureau | B10: 2020 Decennial Census, State Urban and Rural Population | C10: https://www.census.gov/programs-surveys/decennial-census/about/urban-rural.html | D10: 2020 release. Used: per-state urban/rural pop %.
A11: U.S. Bureau of Labor Statistics | B11: Consumer Price Index (CPI-U all items) | C11: https://www.bls.gov/cpi/data.htm | D11: CPI 2017 -> 2012 deflator = 0.9367 (per EPS national BASoBC source About tab).

Sheet Geography
A1: state_fips | B1: state_abbr | C1: state_name | D1: nems_division_num | E1: nems_division_label
A2: 01 | B2: AL | C2: Alabama | D2: 6 | E2: 6 East South Central
A3: 04 | B3: AZ | C3: Arizona | D3: 8 | E3: 8 Mountain
A4: 05 | B4: AR | C4: Arkansas | D4: 7 | E4: 7 West South Central
A5: 06 | B5: CA | C5: California | D5: 9 | E5: 9 Pacific
A6: 08 | B6: CO | C6: Colorado | D6: 8 | E6: 8 Mountain
A7: 09 | B7: CT | C7: Connecticut | D7: 1 | E7: 1 New England
A8: 10 | B8: DE | C8: Delaware | D8: 5 | E8: 5 South Atlantic
A9: 12 | B9: FL | C9: Florida | D9: 5 | E9: 5 South Atlantic
A10: 13 | B10: GA | C10: Georgia | D10: 5 | E10: 5 South Atlantic
A11: 16 | B11: ID | C11: Idaho | D11: 8 | E11: 8 Mountain
A12: 17 | B12: IL | C12: Illinois | D12: 3 | E12: 3 East North Central
A13: 18 | B13: IN | C13: Indiana | D13: 3 | E13: 3 East North Central
... A49: 56 | B49: WY | C49: Wyoming | D49: 8 | E49: 8 Mountain

Sheet State_demographics
A1: state_abbr | B1: state_name | C1: nems_division_num | D1: state_HH | E1: state_commercial_floor_sqft | F1: state_urban_share_pct | G1: state_rural_share_pct
A2: AL | B2: Alabama | C2: 6 | D2: 2059528 | E2: 1.2667742e+09 | F2: 57.73724 | G2: 42.26276
A3: AZ | B3: Arizona | C3: 8 | D3: 2982475 | E3: 2.0326988e+09 | F3: 89.28516 | G3: 10.71484
A4: AR | B4: Arkansas | C4: 7 | D4: 1246754 | E4: 7.4451156e+08 | F4: 55.476131 | G4: 44.523869
A5: CA | B5: California | C5: 9 | D5: 13797638 | E5: 9290924823 | F5: 94.236633 | G5: 5.7633673
A6: CO | B6: Colorado | C6: 8 | D6: 2479892 | E6: 1.8821231e+09 | F6: 86.026707 | G6: 13.973293
A7: CT | B7: Connecticut | C7: 1 | D7: 1455235 | E7: 8.5116782e+08 | F7: 86.250729 | G7: 13.749271
A8: DE | B8: Delaware | C8: 5 | D8: 412304 | E8: 2.6248924e+08 | F8: 82.612117 | G8: 17.387883
A9: FL | B9: Florida | C9: 5 | D9: 9141675 | E9: 6.1924183e+09 | F9: 91.534195 | G9: 8.4658054
A10: GA | B10: Georgia | C10: 5 | D10: 4220732 | E10: 2.8914578e+09 | F10: 74.066973 | G10: 25.933027
A11: ID | B11: Idaho | C11: 8 | D11: 751181 | E11: 5.2050958e+08 | F11: 69.242175 | G11: 30.757825
A12: IL | B12: Illinois | C12: 3 | D12: 5105448 | E12: 5.0949735e+09 | F12: 86.927477 | G12: 13.072523
A13: IN | B13: Indiana | C13: 3 | D13: 2775637 | E13: 2.4486121e+09 | F13: 71.176274 | G13: 28.823726
... A49: WY | B49: Wyoming | C49: 8 | D49: 256289 | E49: 1.6866885e+08 | F49: 62.017748 | G49: 37.982252
A51: Division totals (SUMIF helpers for downscale denominator):
A52: nems_division_num | B52: nems_division_label | C52: division_HH | D52: division_floor_sqft
A53: 1 | B53: 1 New England | C53: =SUMIF(C2:C49, A53, D2:D49) -> 6204829 | D53: =SUMIF(C2:C49, A53, E2:E49) -> 3760333030
A54: 2 | B54: 2 Middle Atlantic | C54: =SUMIF(C2:C49, A54, D2:D49) -> 16733742 | D54: =SUMIF(C2:C49, A54, E2:E49) -> 1.2225747e+10
A55: 3 | B55: 3 East North Central | C55: =SUMIF(C2:C49, A55, D2:D49) -> 19476886 | D55: =SUMIF(C2:C49, A55, E2:E49) -> 1.748009e+10
A56: 4 | B56: 4 West North Central | C56: =SUMIF(C2:C49, A56, D2:D49) -> 9030501 | D56: =SUMIF(C2:C49, A56, E2:E49) -> 8.4870475e+09
A57: 5 | B57: 5 South Atlantic | C57: =SUMIF(C2:C49, A57, D2:D49) -> 27085501 | D57: =SUMIF(C2:C49, A57, E2:E49) -> 1.7934672e+10
A58: 6 | B58: 6 East South Central | C58: =SUMIF(C2:C49, A58, D2:D49) -> 8030439 | D58: =SUMIF(C2:C49, A58, E2:E49) -> 5.4278296e+09
A59: 7 | B59: 7 West South Central | C59: =SUMIF(C2:C49, A59, D2:D49) -> 16149236 | D59: =SUMIF(C2:C49, A59, E2:E49) -> 1.157908e+10
A60: 8 | B60: 8 Mountain | C60: =SUMIF(C2:C49, A60, D2:D49) -> 10219141 | D60: =SUMIF(C2:C49, A60, E2:E49) -> 7.5880825e+09
A61: 9 | B61: 9 Pacific | C61: =SUMIF(C2:C49, A61, D2:D49) -> 18709988 | D61: =SUMIF(C2:C49, A61, E2:E49) -> 1.2044315e+10

Sheet Keys
A1: category | B1: key | C1: value | D1: description
A2: unit | B2: cpi_2017_to_2012 | C2: 0.9366596 | D2: CPI deflator 2017 USD -> 2012 USD (NEMS data is in 2017$ per source)
A3: unit | B3: billions_to_dollars | C3: 1000000000 | D3: Commercial NEMS data is in billions of 2017$; multiply by 1e9 to get $
A4: label | B4: sum_of_totinvest | C4: Sum of TOTINVEST | D4: NEMS Residential data label for total capital expenditure
A5: component | B5: heating | C5: heating
A6: component | B6: cooling_and_ventilation | C6: cooling and ventilation
A7: component | B7: lighting | C7: lighting
A8: component | B8: appliances | C8: appliances
A9: component | B9: envelope | C9: envelope | D9: NEMS does not report; output = 0
A10: component | B10: other_component | C10: other component | D10: NEMS does not report; output = 0
A11: division | B11: div_1 | C11: 1 New England
A12: division | B12: div_2 | C12: 2 Middle Atlantic
A13: division | B13: div_3 | C13: 3 East North Central
A14: division | B14: div_4 | C14: 4 West North Central
A15: division | B15: div_5 | C15: 5 South Atlantic
A16: division | B16: div_6 | C16: 6 East South Central
A17: division | B17: div_7 | C17: 7 West South Central
A18: division | B18: div_8 | C18: 8 Mountain
A19: division | B19: div_9 | C19: 9 Pacific

Sheet NEMS_residential
B1: Displays Investment and Subsidy on the Shell and Investment Tables -- note total expenditures on equipment or shell = consumer investment ("Investment") + subsidy; subsidy includes both federal and non-federal subsidies
B2: i.e., total investment = totinvest + totsubsidy ; investments are in RTEKDOLLARYR dollars (currently 2017$)
B3: Displays Investment and Subsidy on the Shell and Investment Tables -- note total expenditures on equipment or shell = consumer investment ("Investment") + subsidy.
B4: i.e., total investment = totinvest + totsubsidy
H5: YEAR
A6: mapping | B6: CDIV | C6: BLDG | D6: ENDUSE | E6: FUEL | F6: EQPTYPE | G6: Data | H6: 2016 | I6: 2017 | J6: 2018 | K6: 2019 | L6: 2020 | M6: 2021 | N6: 2022 | O6: 2023 | P6: 2024 | Q6: 2025 | R6: 2026 | S6: 2027 | T6: 2028 | U6: 2029 | V6: 2030 | W6: 2031 | X6: 2032 | Y6: 2033 | Z6: 2034 | AA6: 2035 | AB6: 2036 | AC6: 2037 | AD6: 2038 | AE6: 2039 | AF6: 2040 | AG6: 2041 | AH6: 2042 | AI6: 2043 | AJ6: 2044 | AK6: 2045 | AL6: 2046 | AM6: 2047 | AN6: 2048 | AO6: 2049 | AP6: 2050 | DH6: division_filled
A7: =IFERROR(INDEX(NEMS_mapping!C$3:C$12,MATCH(NEMS_residential!D7,NEMS_mapping!B$3:B$12,0)),A6) -> appliances | B7: 1 New England | C7: Single Family | D7: Cooking | E7: Electricity | F7: ELEC_STV2 | G7: Sum of TOTSUBSIDY | H7: 0 | I7: 0 | J7: 0 | K7: 0 | L7: 0 | M7: 0 | N7: 0 | O7: 0 | P7: 0 | Q7: 0 | R7: 0 | S7: 0 | T7: 0 | U7: 0 | V7: 0 | W7: 0 | X7: 0 | Y7: 0 | Z7: 0 | AA7: 0 | AB7: 0 | AC7: 0 | AD7: 0 | AE7: 0 | AF7: 0 | AG7: 0 | AH7: 0 | AI7: 0 | AJ7: 0 | AK7: 0 | AL7: 0 | AM7: 0 | AN7: 0 | AO7: 0 | AP7: 0 | DH7: =B7 -> 1 New England
A8: =IFERROR(INDEX(NEMS_mapping!C$3:C$12,MATCH(NEMS_residential!D8,NEMS_mapping!B$3:B$12,0)),A7) -> appliances | G8: Sum of TOTPURCHASE | H8: 91893 | I8: 90934 | J8: 91587 | K8: 92942 | L8: 97784 | M8: 102590 | N8: 113733 | O8: 117654 | P8: 124238 | Q8: 130918 | R8: 138592 | S8: 148098 | T8: 158204 | U8: 181957 | V8: 206949 | W8: 236279 | X8: 267562 | Y8: 251651 | Z8: 222109 | AA8: 191161 | AB8: 154786 | AC8: 115987 | AD8: 124280 | AE8: 132612 | AF8: 141355 | AG8: 150325 | AH8: 159248 | AI8: 168058 | AJ8: 176273 | AK8: 183259 | AL8: 188425 | AM8: 191359 | AN8: 191724 | AO8: 189631 | AP8: 185357 | DH8: =IF(B8<>"", B8, DH7) -> 1 New England
A9: =IFERROR(INDEX(NEMS_mapping!C$3:C$12,MATCH(NEMS_residential!D9,NEMS_mapping!B$3:B$12,0)),A8) -> appliances | G9: Sum of TOTINVEST | H9: 59731125 | I9: 59107502 | J9: 59532301 | K9: 60412722 | L9: 63560000 | M9: 66684231 | N9: 73926573 | O9: 76475947 | P9: 80755795 | Q9: 85097366 | R9: 90085590 | S9: 96264187 | T9: 102833036 | U9: 118272624 | V9: 134517617 | W9: 153582460 | X9: 173916075 | Y9: 163573552 | Z9: 144370956 | AA9: 124255634 | AB9: 100611961 | AC9: 75391992 | AD9: 80782508 | AE9: 86198394 | AF9: 91881717 | AG9: 97712399 | AH9: 103512223 | AI9: 109238841 | AJ9: 114578131 | AK9: 119119150 | AL9: 122477262 | AM9: 124383763 | AN9: 124620885 | AO9: 123260623 | AP9: 120482333 | DH9: =IF(B9<>"", B9, DH8) -> 1 New England
A10: =IFERROR(INDEX(NEMS_mapping!C$3:C$12,MATCH(NEMS_residential!D10,NEMS_mapping!B$3:B$12,0)),A9) -> appliances | E10: Natural Gas | F10: NG_STV2 | G10: Sum of TOTSUBSIDY | H10: 0 | I10: 0 | J10: 0 | K10: 0 | L10: 0 | M10: 0 | N10: 0 | O10: 0 | P10: 0 | Q10: 0 | R10: 0 | S10: 0 | T10: 0 | U10: 0 | V10: 0 | W10: 0 | X10: 0 | Y10: 0 | Z10: 0 | AA10: 0 | AB10: 0 | AC10: 0 | AD10: 0 | AE10: 0 | AF10: 0 | AG10: 0 | AH10: 0 | AI10: 0 | AJ10: 0 | AK10: 0 | AL10: 0 | AM10: 0 | AN10: 0 | AO10: 0 | AP10: 0 | DH10: =IF(B10<>"", B10, DH9) -> 1 New England
A11: =IFERROR(INDEX(NEMS_mapping!C$3:C$12,MATCH(NEMS_residential!D11,NEMS_mapping!B$3:B$12,0)),A10) -> appliances | G11: Sum of TOTPURCHASE | H11: 41927 | I11: 43493 | J11: 44035 | K11: 45830 | L11: 49250 | M11: 49513 | N11: 52863 | O11: 54643 | P11: 58405 | Q11: 62523 | R11: 68837 | S11: 77378 | T11: 85858 | U11: 95202 | V11: 104223 | W11: 112027 | X11: 118193 | Y11: 110766 | Z11: 102572 | AA11: 94111 | AB11: 85569 | AC11: 77398 | AD11: 83044 | AE11: 89476 | AF11: 96568 | AG11: 103702 | AH11: 110112 | AI11: 115198 | AJ11: 118210 | AK11: 118686 | AL11: 116808 | AM11: 113245 | AN11: 109218 | AO11: 105966 | AP11: 104598 | DH11: =IF(B11<>"", B11, DH10) -> 1 New England
A12: =IFERROR(INDEX(NEMS_mapping!C$3:C$12,MATCH(NEMS_residential!D12,NEMS_mapping!B$3:B$12,0)),A11) -> appliances | G12: Sum of TOTINVEST | H12: 10901285 | I12: 11308325 | J12: 11449390 | K12: 11916143 | L12: 12805152 | M12: 12873525 | N12: 13744703 | O12: 14207401 | P12: 15185694 | Q12: 16256363 | R12: 17897886 | S12: 20118478 | T12: 22323547 | U12: 24752693 | V12: 27098467 | W12: 29127382 | X12: 30730461 | Y12: 28799586 | Z12: 26668820 | AA12: 24469025 | AB12: 22248051 | AC12: 20123700 | AD12: 21591758 | AE12: 23264121 | AF12: 25107997 | AG12: 26962873 | AH12: 28629334 | AI12: 29951659 | AJ12: 30734912 | AK12: 30858769 | AL12: 30370164 | AM12: 29444135 | AN12: 28396812 | AO12: 27551423 | AP12: 27195724 | DH12: =IF(B12<>"", B12, DH11) -> 1 New England
A13: =IFERROR(INDEX(NEMS_mapping!C$3:C$12,MATCH(NEMS_residential!D13,NEMS_mapping!B$3:B$12,0)),A12) -> appliances | F13: NG_STV4 | G13: Sum of TOTSUBSIDY | H13: 0 | I13: 0 | J13: 0 | K13: 0 | L13: 0 | M13: 0 | N13: 0 | O13: 0 | P13: 0 | Q13: 0 | R13: 0 | S13: 0 | T13: 0 | U13: 0 | V13: 0 | W13: 0 | X13: 0 | Y13: 0 | Z13: 0 | AA13: 0 | AB13: 0 | AC13: 0 | AD13: 0 | AE13: 0 | AF13: 0 | AG13: 0 | AH13: 0 | AI13: 0 | AJ13: 0 | AK13: 0 | AL13: 0 | AM13: 0 | AN13: 0 | AO13: 0 | AP13: 0 | DH13: =IF(B13<>"", B13, DH12) -> 1 New England
A14: =IFERROR(INDEX(NEMS_mapping!C$3:C$12,MATCH(NEMS_residential!D14,NEMS_mapping!B$3:B$12,0)),A13) -> appliances | G14: Sum of TOTPURCHASE | H14: 18701 | I14: 19506 | J14: 20537 | K14: 20944 | L14: 22347 | M14: 23043 | N14: 26434 | O14: 26764 | P14: 27366 | Q14: 28744 | R14: 31311 | S14: 34892 | T14: 38486 | U14: 42669 | V14: 46695 | W14: 50183 | X14: 52951 | Y14: 49635 | Z14: 45975 | AA14: 42193 | AB14: 38396 | AC14: 34771 | AD14: 37375 | AE14: 40307 | AF14: 43563 | AG14: 46845 | AH14: 49775 | AI14: 52081 | AJ14: 53412 | AK14: 53687 | AL14: 52836 | AM14: 51220 | AN14: 49387 | AO14: 47935 | AP14: 47355 | DH14: =IF(B14<>"", B14, DH13) -> 1 New England
A15: =IFERROR(INDEX(NEMS_mapping!C$3:C$12,MATCH(NEMS_residential!D15,NEMS_mapping!B$3:B$12,0)),A14) -> appliances | G15: Sum of TOTINVEST | H15: 5618793 | I15: 5860743 | J15: 6170627 | K15: 6292672 | L15: 6714259 | M15: 6923474 | N15: 7942203 | O15: 8041302 | P15: 8222370 | Q15: 8636333 | R15: 9407497 | S15: 10483280 | T15: 11563181 | U15: 12820179 | V15: 14029715 | W15: 15077244 | X15: 15909118 | Y15: 14912954 | Z15: 13813038 | AA15: 12677159 | AB15: 11536178 | AC15: 10447272 | AD15: 11229305 | AE15: 12110323 | AF15: 13088317 | AG15: 14074643 | AH15: 14954824 | AI15: 15647771 | AJ15: 16047776 | AK15: 16130380 | AL15: 15874713 | AM15: 15388996 | AN15: 14838458 | AO15: 14402148 | AP15: 14228091 | DH15: =IF(B15<>"", B15, DH14) -> 1 New England
A16: =IFERROR(INDEX(NEMS_mapping!C$3:C$12,MATCH(NEMS_residential!D16,NEMS_mapping!B$3:B$12,0)),A15) -> appliances | E16: LPG | F16: LPG_STV2 | G16: Sum of TOTSUBSIDY | H16: 0 | I16: 0 | J16: 0 | K16: 0 | L16: 0 | M16: 0 | N16: 0 | O16: 0 | P16: 0 | Q16: 0 | R16: 0 | S16: 0 | T16: 0 | U16: 0 | V16: 0 | W16: 0 | X16: 0 | Y16: 0 | Z16: 0 | AA16: 0 | AB16: 0 | AC16: 0 | AD16: 0 | AE16: 0 | AF16: 0 | AG16: 0 | AH16: 0 | AI16: 0 | AJ16: 0 | AK16: 0 | AL16: 0 | AM16: 0 | AN16: 0 | AO16: 0 | AP16: 0 | DH16: =IF(B16<>"", B16, DH15) -> 1 New England
A17: =IFERROR(INDEX(NEMS_mapping!C$3:C$12,MATCH(NEMS_residential!D17,NEMS_mapping!B$3:B$12,0)),A16) -> appliances | G17: Sum of TOTPURCHASE | H17: 28302 | I17: 30026 | J17: 30093 | K17: 31828 | L17: 33152 | M17: 37258 | N17: 28140 | O17: 28281 | P17: 29490 | Q17: 31602 | R17: 35239 | S17: 40144 | T17: 44890 | U17: 49711 | V17: 54146 | W17: 57477 | X17: 59439 | Y17: 54312 | Z17: 48873 | AA17: 43192 | AB17: 37601 | AC17: 32489 | AD17: 34321 | AE17: 36832 | AF17: 39686 | AG17: 42525 | AH17: 44967 | AI17: 46690 | AJ17: 47361 | AK17: 46786 | AL17: 45081 | AM17: 42600 | AN17: 39927 | AO17: 37723 | AP17: 36464 | DH17: =IF(B17<>"", B17, DH16) -> 1 New England
A18: =IFERROR(INDEX(NEMS_mapping!C$3:C$12,MATCH(NEMS_residential!D18,NEMS_mapping!B$3:B$12,0)),A17) -> appliances | G18: Sum of TOTINVEST | H18: 7358681 | I18: 7806992 | J18: 7824457 | K18: 8275675 | L18: 8619855 | M18: 9687317 | N18: 7316577 | O18: 7353387 | P18: 7667647 | Q18: 8216909 | R18: 9162344 | S18: 10437755 | T18: 11671472 | U18: 12925262 | V18: 14078077 | W18: 14944370 | X18: 15454474 | Y18: 14121354 | Z18: 12707211 | AA18: 11230382 | AB18: 9776550 | AC18: 8447533 | AD18: 8923713 | AE18: 9576558 | AF18: 10318408 | AG18: 11056728 | AH18: 11691710 | AI18: 12139588 | AJ18: 12314039 | AK18: 12164676 | AL18: 11721264 | AM18: 11076264 | AN18: 10381377 | AO18: 9808098 | AP18: 9480982 | DH18: =IF(B18<>"", B18, DH17) -> 1 New England
A19: =IFERROR(INDEX(NEMS_mapping!C$3:C$12,MATCH(NEMS_residential!D19,NEMS_mapping!B$3:B$12,0)),A18) -> appliances | F19: LPG_STV4 | G19: Sum of TOTSUBSIDY | H19: 0 | I19: 0 | J19: 0 | K19: 0 | L19: 0 | M19: 0 | N19: 0 | O19: 0 | P19: 0 | Q19: 0 | R19: 0 | S19: 0 | T19: 0 | U19: 0 | V19: 0 | W19: 0 | X19: 0 | Y19: 0 | Z19: 0 | AA19: 0 | AB19: 0 | AC19: 0 | AD19: 0 | AE19: 0 | AF19: 0 | AG19: 0 | AH19: 0 | AI19: 0 | AJ19: 0 | AK19: 0 | AL19: 0 | AM19: 0 | AN19: 0 | AO19: 0 | AP19: 0 | DH19: =IF(B19<>"", B19, DH18) -> 1 New England
A20: =IFERROR(INDEX(NEMS_mapping!C$3:C$12,MATCH(NEMS_residential!D20,NEMS_mapping!B$3:B$12,0)),A19) -> appliances | G20: Sum of TOTPURCHASE | H20: 14149 | I20: 14850 | J20: 16222 | K20: 16444 | L20: 16337 | M20: 19971 | N20: 17423 | O20: 18348 | P20: 19241 | Q20: 20145 | R20: 21918 | S20: 24467 | T20: 27036 | U20: 29805 | V20: 32531 | W20: 34766 | X20: 36341 | Y20: 33657 | Z20: 30690 | AA20: 27410 | AB20: 24048 | AC20: 20922 | AD20: 22296 | AE20: 24030 | AF20: 26069 | AG20: 28122 | AH20: 29878 | AI20: 31097 | AJ20: 31561 | AK20: 31217 | AL20: 30093 | AM20: 28458 | AN20: 26717 | AO20: 25253 | AP20: 24402 | DH20: =IF(B20<>"", B20, DH19) -> 1 New England
A21: =IFERROR(INDEX(NEMS_mapping!C$3:C$12,MATCH(NEMS_residential!D21,NEMS_mapping!B$3:B$12,0)),A20) -> appliances | G21: Sum of TOTINVEST | H21: 4251280 | I21: 4461926 | J21: 4873869 | K21: 4941012 | L21: 4908546 | M21: 6000344 | N21: 5235130 | O21: 5512862 | P21: 5781149 | Q21: 6052528 | R21: 6585328 | S21: 7351111 | T21: 8123137 | U21: 8954984 | V21: 9773958 | W21: 10445619 | X21: 10918891 | Y21: 10112308 | Z21: 9221178 | AA21: 8235443 | AB21: 7225317 | AC21: 6286190 | AD21: 6699164 | AE21: 7219838 | AF21: 7832740 | AG21: 8449459 | AH21: 8976992 | AI21: 9343208 | AJ21: 9482836 | AK21: 9379318 | AL21: 9041503 | AM21: 8550323 | AN21: 8027237 | AO21: 7587651 | AP21: 7331810 | DH21: =IF(B21<>"", B21, DH20) -> 1 New England
A22: =IFERROR(INDEX(NEMS_mapping!C$3:C$12,MATCH(NEMS_residential!D22,NEMS_mapping!B$3:B$12,0)),A21) -> cooling and ventilation | D22: Cooling | E22: Electricity | F22: CENT_AIR1 | G22: Sum of TOTSUBSIDY | H22: 0 | I22: 0 | J22: 0 | K22: 0 | L22: 0 | M22: 0 | N22: 0 | O22: 0 | P22: 0 | Q22: 0 | R22: 0 | S22: 0 | T22: 0 | U22: 0 | V22: 0 | W22: 0 | X22: 0 | Y22: 0 | Z22: 0 | AA22: 0 | AB22: 0 | AC22: 0 | AD22: 0 | AE22: 0 | AF22: 0 | AG22: 0 | AH22: 0 | AI22: 0 | AJ22: 0 | AK22: 0 | AL22: 0 | AM22: 0 | AN22: 0 | AO22: 0 | AP22: 0 | DH22: =IF(B22<>"", B22, DH21) -> 1 New England
A23: =IFERROR(INDEX(NEMS_mapping!C$3:C$12,MATCH(NEMS_residential!D23,NEMS_mapping!B$3:B$12,0)),A22) -> cooling and ventilation | G23: Sum of TOTPURCHASE | H23: 33760 | I23: 37383 | J23: 35156 | K23: 37446 | L23: 38727 | M23: 41772 | N23: 18949 | O23: 0 | P23: 0 | Q23: 0 | R23: 0 | S23: 0 | T23: 0 | U23: 0 | V23: 0 | W23: 0 | X23: 0 | Y23: 0 | Z23: 0 | AA23: 0 | AB23: 0 | AC23: 0 | AD23: 0 | AE23: 0 | AF23: 0 | AG23: 0 | AH23: 0 | AI23: 0 | AJ23: 0 | AK23: 0 | AL23: 0 | AM23: 0 | AN23: 0 | AO23: 0 | AP23: 0 | DH23: =IF(B23<>"", B23, DH22) -> 1 New England
A24: =IFERROR(INDEX(NEMS_mapping!C$3:C$12,MATCH(NEMS_residential!D24,NEMS_mapping!B$3:B$12,0)),A23) -> cooling and ventilation | G24: Sum of TOTINVEST | H24: 74273564 | I24: 82245592 | J24: 77346278 | K24: 82383488 | L24: 85200310 | M24: 91901896 | N24: 41689372 | O24: 0 | P24: 0 | Q24: 0 | R24: 0 | S24: 0 | T24: 0 | U24: 0 | V24: 0 | W24: 0 | X24: 0 | Y24: 0 | Z24: 0 | AA24: 0 | AB24: 0 | AC24: 0 | AD24: 0 | AE24: 0 | AF24: 0 | AG24: 0 | AH24: 0 | AI24: 0 | AJ24: 0 | AK24: 0 | AL24: 0 | AM24: 0 | AN24: 0 | AO24: 0 | AP24: 0 | DH24: =IF(B24<>"", B24, DH23) -> 1 New England
A25: =IFERROR(INDEX(NEMS_mapping!C$3:C$12,MATCH(NEMS_residential!D25,NEMS_mapping!B$3:B$12,0)),A24) -> cooling and ventilation | F25: CENT_AIR2 | G25: Sum of TOTSUBSIDY | H25: 0 | I25: 0 | J25: 0 | K25: 0 | L25: 0 | M25: 0 | N25: 0 | O25: 0 | P25: 0 | Q25: 0 | R25: 0 | S25: 0 | T25: 0 | U25: 0 | V25: 0 | W25: 0 | X25: 0 | Y25: 0 | Z25: 0 | AA25: 0 | AB25: 0 | AC25: 0 | AD25: 0 | AE25: 0 | AF25: 0 | AG25: 0 | AH25: 0 | AI25: 0 | AJ25: 0 | AK25: 0 | AL25: 0 | AM25: 0 | AN25: 0 | AO25: 0 | AP25: 0 | DH25: =IF(B25<>"", B25, DH24) -> 1 New England
A26: =IFERROR(INDEX(NEMS_mapping!C$3:C$12,MATCH(NEMS_residential!D26,NEMS_mapping!B$3:B$12,0)),A25) -> cooling and ventilation | G26: Sum of TOTPURCHASE | H26: 22003 | I26: 23229 | J26: 23447 | K26: 24386 | L26: 24692 | M26: 25480 | N26: 5700 | O26: 10516 | P26: 11103 | Q26: 11110 | R26: 10678 | S26: 10425 | T26: 10098 | U26: 9704 | V26: 9270 | W26: 8846 | X26: 8495 | Y26: 63575 | Z26: 64294 | AA26: 66087 | AB26: 66972 | AC26: 67539 | AD26: 70960 | AE26: 74063 | AF26: 76732 | AG26: 78861 | AH26: 80581 | AI26: 81889 | AJ26: 83220 | AK26: 84033 | AL26: 84564 | AM26: 85266 | AN26: 85698 | AO26: 86635 | AP26: 87534 | DH26: =IF(B26<>"", B26, DH25) -> 1 New England
A27: =IFERROR(INDEX(NEMS_mapping!C$3:C$12,MATCH(NEMS_residential!D27,NEMS_mapping!B$3:B$12,0)),A26) -> cooling and ventilation | G27: Sum of TOTINVEST | H27: 49508464 | I27: 52266464 | J27: 52756280 | K27: 54870092 | L27: 55558396 | M27: 57331168 | N27: 12826356 | O27: 24714711 | P27: 26095446 | Q27: 26110806 | R27: 25096064 | S27: 24500959 | T27: 23734432 | U27: 22806647 | V27: 21786009 | W27: 20791232 | X27: 19966792 | Y27: 149402930 | Z27: 151094066 | AA27: 155305968 | AB27: 157387042 | AC27: 158718134 | AD27: 166758980 | AE27: 174048834 | AF27: 180323550 | AG27: 185325724 | AH27: 189367356 | AI27: 192442210 | AJ27: 195569696 | AK27: 197479024 | AL27: 198726482 | AM27: 200377924 | AN27: 201391490 | AO27: 203595810 | AP27: 205706180 | DH27: =IF(B27<>"", B27, DH26) -> 1 New England
A28: =IFERROR(INDEX(NEMS_mapping!C$3:C$12,MATCH(NEMS_residential!D28,NEMS_mapping!B$3:B$12,0)),A27) -> cooling and ventilation | F28: CENT_AIR3 | G28: Sum of TOTSUBSIDY | H28: 0 | I28: 0 | J28: 0 | K28: 0 | L28: 0 | M28: 0 | N28: 0 | O28: 99500784 | P28: 97463464 | Q28: 96222488 | R28: 95053144 | S28: 94450512 | T28: 94296888 | U28: 95523840 | V28: 96982424 | W28: 98888480 | X28: 101717968 | Y28: 0 | Z28: 0 | AA28: 0 | AB28: 0 | AC28: 0 | AD28: 0 | AE28: 0 | AF28: 0 | AG28: 0 | AH28: 0 | AI28: 0 | AJ28: 0 | AK28: 0 | AL28: 0 | AM28: 0 | AN28: 0 | AO28: 0 | AP28: 0 | DH28: =IF(B28<>"", B28, DH27) -> 1 New England
A29: =IFERROR(INDEX(NEMS_mapping!C$3:C$12,MATCH(NEMS_residential!D29,NEMS_mapping!B$3:B$12,0)),A28) -> cooling and ventilation | G29: Sum of TOTPURCHASE | H29: 14957 | I29: 14987 | J29: 16666 | K29: 16521 | L29: 17242 | M29: 17725 | N29: 5920 | O29: 55463 | P29: 54301 | Q29: 53964 | R29: 53487 | S29: 53246 | T29: 53406 | U29: 54237 | V29: 55093 | W29: 56177 | X29: 57745 | Y29: 26836 | Z29: 28194 | AA29: 29357 | AB29: 30705 | AC29: 31579 | AD29: 33925 | AE29: 35993 | AF29: 37911 | AG29: 39572 | AH29: 40841 | AI29: 41947 | AJ29: 42723 | AK29: 43487 | AL29: 44193 | AM29: 44742 | AN29: 45385 | AO29: 45845 | AP29: 46431 | DH29: =IF(B29<>"", B29, DH28) -> 1 New England
A30: =IFERROR(INDEX(NEMS_mapping!C$3:C$12,MATCH(NEMS_residential!D30,NEMS_mapping!B$3:B$12,0)),A29) -> cooling and ventilation | G30: Sum of TOTINVEST | H30: 39639391 | I30: 39716706 | J30: 44166657 | K30: 43784215 | L30: 45694953 | M30: 46972913 | N30: 15690186 | O30: 156776548 | P30: 153495648 | Q30: 152540499 | R30: 151193302 | S30: 150511106 | T30: 150964026 | U30: 153315258 | V30: 155732396 | W30: 158796388 | X30: 163229978 | Y30: 75858217 | Z30: 79697586 | AA30: 82985799 | AB30: 86795467 | AC30: 89266299 | AD30: 95896771 | AE30: 101743217 | AF30: 107165063 | AG30: 111859434 | AH30: 115446247 | AI30: 118571137 | AJ30: 120766854 | AK30: 122925036 | AL30: 124921916 | AM30: 126472659 | AN30: 128290463 | AO30: 129589490 | AP30: 131245455 | DH30: =IF(B30<>"", B30, DH29) -> 1 New England
A31: =IFERROR(INDEX(NEMS_mapping!C$3:C$12,MATCH(NEMS_residential!D31,NEMS_mapping!B$3:B$12,0)),A30) -> cooling and ventilation | F31: CENT_AIR4 | G31: Sum of TOTSUBSIDY | H31: 6181201 | I31: 5637911 | J31: 7001921 | K31: 6444983 | L31: 7180935 | M31: 7048536 | N31: 152886017 | O31: 79409831 | P31: 78860931 | Q31: 77949493 | R31: 77085333 | S31: 76691551 | T31: 76685796 | U31: 77820923 | V31: 79107480 | W31: 80805426 | X31: 83301022 | Y31: 3411219 | Z31: 3612210 | AA31: 3756688 | AB31: 3952178 | AC31: 4070831 | AD31: 4398179 | AE31: 4685214 | AF31: 4950969 | AG31: 5184054 | AH31: 5362957 | AI31: 5520221 | AJ31: 5619067 | AK31: 5727850 | AL31: 5835929 | AM31: 5913992 | AN31: 6018974 | AO31: 6081296 | AP31: 6167990 | DH31: =IF(B31<>"", B31, DH30) -> 1 New England
A32: =IFERROR(INDEX(NEMS_mapping!C$3:C$12,MATCH(NEMS_residential!D32,NEMS_mapping!B$3:B$12,0)),A31) -> cooling and ventilation | G32: Sum of TOTPURCHASE | H32: 12900 | I32: 11806 | J32: 14655 | K32: 13518 | L32: 15005 | M32: 14783 | N32: 70955 | O32: 37564 | P32: 37267 | Q32: 36894 | R32: 36513 | S32: 36382 | T32: 36427 | U32: 36994 | V32: 37607 | W32: 38415 | X32: 39598 | Y32: 18707 | Z32: 19809 | AA32: 20602 | AB32: 21675 | AC32: 22328 | AD32: 24120 | AE32: 25692 | AF32: 27148 | AG32: 28426 | AH32: 29405 | AI32: 30268 | AJ32: 30809 | AK32: 31405 | AL32: 31997 | AM32: 32424 | AN32: 32997 | AO32: 33336 | AP32: 33810 | DH32: =IF(B32<>"", B32, DH31) -> 1 New England
A33: =IFERROR(INDEX(NEMS_mapping!C$3:C$12,MATCH(NEMS_residential!D33,NEMS_mapping!B$3:B$12,0)),A32) -> cooling and ventilation | G33: Sum of TOTINVEST | H33: 41285131 | I33: 37782671 | J33: 46899273 | K33: 43258316 | L33: 48019042 | M33: 47309047 | N33: 227057751 | O33: 120208331 | P33: 119260000 | Q33: 118063328 | R33: 116845514 | S33: 116425975 | T33: 116566940 | U33: 118382208 | V33: 120343831 | W33: 122934127 | X33: 126716478 | Y33: 59865746 | Z33: 63391370 | AA33: 65929672 | AB33: 69363808 | AC33: 71451514 | AD33: 77188613 | AE33: 82217869 | AF33: 86879311 | AG33: 90968089 | AH33: 94101342 | AI33: 96858445 | AJ33: 98591049 | AK33: 100498527 | AL33: 102392390 | AM33: 103758398 | AN33: 105594127 | AO33: 106680434 | AP33: 108193854 | DH33: =IF(B33<>"", B33, DH32) -> 1 New England
A34: =IFERROR(INDEX(NEMS_mapping!C$3:C$12,MATCH(NEMS_residential!D34,NEMS_mapping!B$3:B$12,0)),A33) -> cooling and ventilation | F34: ELEC_HP1 | G34: Sum of TOTSUBSIDY | H34: 0 | I34: 0 | J34: 0 | K34: 0 | L34: 0 | M34: 0 | N34: 0 | O34: 0 | P34: 0 | Q34: 0 | R34: 0 | S34: 0 | T34: 0 | U34: 0 | V34: 0 | W34: 0 | X34: 0 | Y34: 0 | Z34: 0 | AA34: 0 | AB34: 0 | AC34: 0 | AD34: 0 | AE34: 0 | AF34: 0 | AG34: 0 | AH34: 0 | AI34: 0 | AJ34: 0 | AK34: 0 | AL34: 0 | AM34: 0 | AN34: 0 | AO34: 0 | AP34: 0 | DH34: =IF(B34<>"", B34, DH33) -> 1 New England
A35: =IFERROR(INDEX(NEMS_mapping!C$3:C$12,MATCH(NEMS_residential!D35,NEMS_mapping!B$3:B$12,0)),A34) -> cooling and ventilation | G35: Sum of TOTPURCHASE | H35: 1245 | I35: 1832 | J35: 2091 | K35: 2141 | L35: 2112 | M35: 2019 | N35: 123 | O35: 0 | P35: 0 | Q35: 0 | R35: 0 | S35: 0 | T35: 0 | U35: 0 | V35: 0 | W35: 0 | X35: 0 | Y35: 0 | Z35: 0 | AA35: 0 | AB35: 0 | AC35: 0 | AD35: 0 | AE35: 0 | AF35: 0 | AG35: 0 | AH35: 0 | AI35: 0 | AJ35: 0 | AK35: 0 | AL35: 0 | AM35: 0 | AN35: 0 | AO35: 0 | AP35: 0 | DH35: =IF(B35<>"", B35, DH34) -> 1 New England
A36: =IFERROR(INDEX(NEMS_mapping!C$3:C$12,MATCH(NEMS_residential!D36,NEMS_mapping!B$3:B$12,0)),A35) -> cooling and ventilation | G36: Sum of TOTINVEST | H36: 0 | I36: 0 | J36: 0 | K36: 0 | L36: 0 | M36: 0 | N36: 0 | O36: 0 | P36: 0 | Q36: 0 | R36: 0 | S36: 0 | T36: 0 | U36: 0 | V36: 0 | W36: 0 | X36: 0 | Y36: 0 | Z36: 0 | AA36: 0 | AB36: 0 | AC36: 0 | AD36: 0 | AE36: 0 | AF36: 0 | AG36: 0 | AH36: 0 | AI36: 0 | AJ36: 0 | AK36: 0 | AL36: 0 | AM36: 0 | AN36: 0 | AO36: 0 | AP36: 0 | DH36: =IF(B36<>"", B36, DH35) -> 1 New England
A37: =IFERROR(INDEX(NEMS_mapping!C$3:C$12,MATCH(NEMS_residential!D37,NEMS_mapping!B$3:B$12,0)),A36) -> cooling and ventilation | F37: ELEC_HP2 | G37: Sum of TOTSUBSIDY | H37: 215943 | I37: 217890 | J37: 227293 | K37: 231872 | L37: 222651 | M37: 223912 | N37: 22227 | O37: 2034452 | P37: 2010121 | Q37: 2050998 | R37: 2110849 | S37: 2127412 | T37: 2147006 | U37: 2173957 | V37: 2209561 | W37: 2277324 | X37: 2346062 | Y37: 0 | Z37: 0 | AA37: 0 | AB37: 0 | AC37: 0 | AD37: 0 | AE37: 0 | AF37: 0 | AG37: 0 | AH37: 0 | AI37: 0 | AJ37: 0 | AK37: 0 | AL37: 0 | AM37: 0 | AN37: 0 | AO37: 0 | AP37: 0 | DH37: =IF(B37<>"", B37, DH36) -> 1 New England
A38: =IFERROR(INDEX(NEMS_mapping!C$3:C$12,MATCH(NEMS_residential!D38,NEMS_mapping!B$3:B$12,0)),A37) -> cooling and ventilation | G38: Sum of TOTPURCHASE | H38: 1439 | I38: 1452 | J38: 1515 | K38: 1545 | L38: 1484 | M38: 1492 | N38: 148 | O38: 2034 | P38: 2010 | Q38: 2050 | R38: 2110 | S38: 2127 | T38: 2147 | U38: 2173 | V38: 2209 | W38: 2277 | X38: 2346 | Y38: 2425 | Z38: 2502 | AA38: 2589 | AB38: 2656 | AC38: 2692 | AD38: 2757 | AE38: 2808 | AF38: 2850 | AG38: 2907 | AH38: 3015 | AI38: 3118 | AJ38: 3192 | AK38: 3268 | AL38: 3341 | AM38: 3433 | AN38: 3516 | AO38: 3573 | AP38: 3630 | DH38: =IF(B38<>"", B38, DH37) -> 1 New England
A39: =IFERROR(INDEX(NEMS_mapping!C$3:C$12,MATCH(NEMS_residential!D39,NEMS_mapping!B$3:B$12,0)),A38) -> cooling and ventilation | G39: Sum of TOTINVEST | H39: 0 | I39: 0 | J39: 0 | K39: 0 | L39: 0 | M39: 0 | N39: 0 | O39: 0 | P39: 0 | Q39: 0 | R39: 0 | S39: 0 | T39: 0 | U39: 0 | V39: 0 | W39: 0 | X39: 0 | Y39: 0 | Z39: 0 | AA39: 0 | AB39: 0 | AC39: 0 | AD39: 0 | AE39: 0 | AF39: 0 | AG39: 0 | AH39: 0 | AI39: 0 | AJ39: 0 | AK39: 0 | AL39: 0 | AM39: 0 | AN39: 0 | AO39: 0 | AP39: 0 | DH39: =IF(B39<>"", B39, DH38) -> 1 New England
A40: =IFERROR(INDEX(NEMS_mapping!C$3:C$12,MATCH(NEMS_residential!D40,NEMS_mapping!B$3:B$12,0)),A39) -> cooling and ventilation | F40: ELEC_HP3 | G40: Sum of TOTSUBSIDY | H40: 8447128 | I40: 9997430 | J40: 10349171 | K40: 10483677 | L40: 10173277 | M40: 10289977 | N40: 25689201 | O40: 22562688 | P40: 22456733 | Q40: 22827060 | R40: 23426805 | S40: 23562900 | T40: 23743223 | U40: 24006586 | V40: 24345259 | W40: 25063555 | X40: 25794458 | Y40: 11005203 | Z40: 11359694 | AA40: 11725120 | AB40: 12028626 | AC40: 12150178 | AD40: 12329666 | AE40: 12528579 | AF40: 12678476 | AG40: 12885129 | AH40: 13358224 | AI40: 13788478 | AJ40: 14211869 | AK40: 14562952 | AL40: 14872304 | AM40: 15301935 | AN40: 15657733 | AO40: 16015149 | AP40: 16266304 | DH40: =IF(B40<>"", B40, DH39) -> 1 New England
A41: =IFERROR(INDEX(NEMS_mapping!C$3:C$12,MATCH(NEMS_residential!D41,NEMS_mapping!B$3:B$12,0)),A40) -> cooling and ventilation | G41: Sum of TOTPURCHASE | H41: 10668 | I41: 12609 | J41: 13109 | K41: 13295 | L41: 12886 | M41: 13017 | N41: 15569 | O41: 13241 | P41: 13178 | Q41: 13396 | R41: 13748 | S41: 13827 | T41: 13933 | U41: 14088 | V41: 14287 | W41: 14708 | X41: 15137 | Y41: 15632 | Z41: 16135 | AA41: 16655 | AB41: 17086 | AC41: 17258 | AD41: 17513 | AE41: 17796 | AF41: 18009 | AG41: 18302 | AH41: 18974 | AI41: 19585 | AJ41: 20187 | AK41: 20686 | AL41: 21125 | AM41: 21735 | AN41: 22241 | AO41: 22748 | AP41: 23105 | DH41: =IF(B41<>"", B41, DH40) -> 1 New England
A42: =IFERROR(INDEX(NEMS_mapping!C$3:C$12,MATCH(NEMS_residential!D42,NEMS_mapping!B$3:B$12,0)),A41) -> cooling and ventilation | G42: Sum of TOTINVEST | H42: 0 | I42: 0 | J42: 0 | K42: 0 | L42: 0 | M42: 0 | N42: 0 | O42: 0 | P42: 0 | Q42: 0 | R42: 0 | S42: 0 | T42: 0 | U42: 0 | V42: 0 | W42: 0 | X42: 0 | Y42: 0 | Z42: 0 | AA42: 0 | AB42: 0 | AC42: 0 | AD42: 0 | AE42: 0 | AF42: 0 | AG42: 0 | AH42: 0 | AI42: 0 | AJ42: 0 | AK42: 0 | AL42: 0 | AM42: 0 | AN42: 0 | AO42: 0 | AP42: 0 | DH42: =IF(B42<>"", B42, DH41) -> 1 New England
A43: =IFERROR(INDEX(NEMS_mapping!C$3:C$12,MATCH(NEMS_residential!D43,NEMS_mapping!B$3:B$12,0)),A42) -> cooling and ventilation | F43: ELEC_HP4 | G43: Sum of TOTSUBSIDY | H43: 6825897 | I43: 3716141 | J43: 3915255 | K43: 4016424 | L43: 3780677 | M43: 3796032 | N43: 7968573 | O43: 9143794 | P43: 8609405 | Q43: 8693088 | R43: 8876871 | S43: 8896497 | T43: 8940048 | U43: 9016067 | V43: 9107094 | W43: 9356943 | X43: 9612771 | Y43: 4532461 | Z43: 4681966 | AA43: 4809536 | AB43: 4933830 | AC43: 4982145 | AD43: 5083923 | AE43: 5164159 | AF43: 5227886 | AG43: 5318243 | AH43: 5504188 | AI43: 5679376 | AJ43: 5809298 | AK43: 5938132 | AL43: 6059502 | AM43: 6218066 | AN43: 6359344 | AO43: 6453301 | AP43: 6548803 | DH43: =IF(B43<>"", B43, DH42) -> 1 New England
A44: =IFERROR(INDEX(NEMS_mapping!C$3:C$12,MATCH(NEMS_residential!D44,NEMS_mapping!B$3:B$12,0)),A43) -> cooling and ventilation | G44: Sum of TOTPURCHASE | H44: 7177 | I44: 3907 | J44: 4116 | K44: 4223 | L44: 3975 | M44: 3991 | N44: 4323 | O44: 4961 | P44: 4671 | Q44: 4716 | R44: 4816 | S44: 4827 | T44: 4850 | U44: 4892 | V44: 4941 | W44: 5077 | X44: 5215 | Y44: 5376 | Z44: 5553 | AA44: 5705 | AB44: 5852 | AC44: 5910 | AD44: 6030 | AE44: 6125 | AF44: 6201 | AG44: 6308 | AH44: 6529 | AI44: 6737 | AJ44: 6891 | AK44: 7044 | AL44: 7188 | AM44: 7376 | AN44: 7543 | AO44: 7655 | AP44: 7768 | DH44: =IF(B44<>"", B44, DH43) -> 1 New England
A45: =IFERROR(INDEX(NEMS_mapping!C$3:C$12,MATCH(NEMS_residential!D45,NEMS_mapping!B$3:B$12,0)),A44) -> cooling and ventilation | G45: Sum of TOTINVEST | H45: 0 | I45: 0 | J45: 0 | K45: 0 | L45: 0 | M45: 0 | N45: 0 | O45: 0 | P45: 0 | Q45: 0 | R45: 0 | S45: 0 | T45: 0 | U45: 0 | V45: 0 | W45: 0 | X45: 0 | Y45: 0 | Z45: 0 | AA45: 0 | AB45: 0 | AC45: 0 | AD45: 0 | AE45: 0 | AF45: 0 | AG45: 0 | AH45: 0 | AI45: 0 | AJ45: 0 | AK45: 0 | AL45: 0 | AM45: 0 | AN45: 0 | AO45: 0 | AP45: 0 | DH45: =IF(B45<>"", B45, DH44) -> 1 New England
A46: =IFERROR(INDEX(NEMS_mapping!C$3:C$12,MATCH(NEMS_residential!D46,NEMS_mapping!B$3:B$12,0)),A45) -> cooling and ventilation | F46: GEO_HP1 | G46: Sum of TOTSUBSIDY | H46: 0 | I46: 0 | J46: 0 | K46: 0 | L46: 0 | M46: 0 | N46: 0 | O46: 0 | P46: 0 | Q46: 0 | R46: 0 | S46: 0 | T46: 0 | U46: 0 | V46: 0 | W46: 0 | X46: 0 | Y46: 0 | Z46: 0 | AA46: 0 | AB46: 0 | AC46: 0 | AD46: 0 | AE46: 0 | AF46: 0 | AG46: 0 | AH46: 0 | AI46: 0 | AJ46: 0 | AK46: 0 | AL46: 0 | AM46: 0 | AN46: 0 | AO46: 0 | AP46: 0 | DH46: =IF(B46<>"", B46, DH45) -> 1 New England
A47: =IFERROR(INDEX(NEMS_mapping!C$3:C$12,MATCH(NEMS_residential!D47,NEMS_mapping!B$3:B$12,0)),A46) -> cooling and ventilation | G47: Sum of TOTPURCHASE | H47: 17 | I47: 11 | J47: 16 | K47: 14 | L47: 21 | M47: 23 | N47: 31 | O47: 19 | P47: 22 | Q47: 22 | R47: 20 | S47: 19 | T47: 17 | U47: 16 | V47: 15 | W47: 14 | X47: 13 | Y47: 39 | Z47: 51 | AA47: 486 | AB47: 490 | AC47: 484 | AD47: 479 | AE47: 475 | AF47: 478 | AG47: 474 | AH47: 468 | AI47: 463 | AJ47: 459 | AK47: 455 | AL47: 453 | AM47: 463 | AN47: 474 | AO47: 483 | AP47: 493 | DH47: =IF(B47<>"", B47, DH46) -> 1 New England
A48: =IFERROR(INDEX(NEMS_mapping!C$3:C$12,MATCH(NEMS_residential!D48,NEMS_mapping!B$3:B$12,0)),A47) -> cooling and ventilation | G48: Sum of TOTINVEST | H48: 0 | I48: 0 | J48: 0 | K48: 0 | L48: 0 | M48: 0 | N48: 0 | O48: 0 | P48: 0 | Q48: 0 | R48: 0 | S48: 0 | T48: 0 | U48: 0 | V48: 0 | W48: 0 | X48: 0 | Y48: 0 | Z48: 0 | AA48: 0 | AB48: 0 | AC48: 0 | AD48: 0 | AE48: 0 | AF48: 0 | AG48: 0 | AH48: 0 | AI48: 0 | AJ48: 0 | AK48: 0 | AL48: 0 | AM48: 0 | AN48: 0 | AO48: 0 | AP48: 0 | DH48: =IF(B48<>"", B48, DH47) -> 1 New England
A49: =IFERROR(INDEX(NEMS_mapping!C$3:C$12,MATCH(NEMS_residential!D49,NEMS_mapping!B$3:B$12,0)),A48) -> cooling and ventilation | F49: GEO_HP2 | G49: Sum of TOTSUBSIDY | H49: 0 | I49: 0 | J49: 0 | K49: 0 | L49: 0 | M49: 0 | N49: 0 | O49: 0 | P49: 0 | Q49: 0 | R49: 0 | S49: 0 | T49: 0 | U49: 0 | V49: 0 | W49: 0 | X49: 0 | Y49: 0 | Z49: 0 | AA49: 0 | AB49: 0 | AC49: 0 | AD49: 0 | AE49: 0 | AF49: 0 | AG49: 0 | AH49: 0 | AI49: 0 | AJ49: 0 | AK49: 0 | AL49: 0 | AM49: 0 | AN49: 0 | AO49: 0 | AP49: 0 | DH49: =IF(B49<>"", B49, DH48) -> 1 New England
A50: =IFERROR(INDEX(NEMS_mapping!C$3:C$12,MATCH(NEMS_residential!D50,NEMS_mapping!B$3:B$12,0)),A49) -> cooling and ventilation | G50: Sum of TOTPURCHASE | H50: 0 | I50: 1 | J50: 1 | K50: 1 | L50: 2 | M50: 2 | N50: 1 | O50: 1 | P50: 1 | Q50: 1 | R50: 1 | S50: 1 | T50: 1 | U50: 1 | V50: 2 | W50: 2 | X50: 2 | Y50: 4 | Z50: 8 | AA50: 233 | AB50: 244 | AC50: 247 | AD50: 251 | AE50: 253 | AF50: 259 | AG50: 260 | AH50: 260 | AI50: 260 | AJ50: 257 | AK50: 257 | AL50: 257 | AM50: 266 | AN50: 275 | AO50: 282 | AP50: 290 | DH50: =IF(B50<>"", B50, DH49) -> 1 New England
A51: =IFERROR(INDEX(NEMS_mapping!C$3:C$12,MATCH(NEMS_residential!D51,NEMS_mapping!B$3:B$12,0)),A50) -> cooling and ventilation | G51: Sum of TOTINVEST | H51: 0 | I51: 0 | J51: 0 | K51: 0 | L51: 0 | M51: 0 | N51: 0 | O51: 0 | P51: 0 | Q51: 0 | R51: 0 | S51: 0 | T51: 0 | U51: 0 | V51: 0 | W51: 0 | X51: 0 | Y51: 0 | Z51: 0 | AA51: 0 | AB51: 0 | AC51: 0 | AD51: 0 | AE51: 0 | AF51: 0 | AG51: 0 | AH51: 0 | AI51: 0 | AJ51: 0 | AK51: 0 | AL51: 0 | AM51: 0 | AN51: 0 | AO51: 0 | AP51: 0 | DH51: =IF(B51<>"", B51, DH50) -> 1 New England
A52: =IFERROR(INDEX(NEMS_mapping!C$3:C$12,MATCH(NEMS_residential!D52,NEMS_mapping!B$3:B$12,0)),A51) -> cooling and ventilation | F52: GEO_HP3 | G52: Sum of TOTSUBSIDY | H52: 2292380 | I52: 8158594 | J52: 9188169 | K52: 9483854 | L52: 7746694 | M52: 7878982 | N52: 9740480 | O52: 10097467 | P52: 9944491 | Q52: 10270491 | R52: 10613876 | S52: 11048367 | T52: 11631292 | U52: 12340046 | V52: 13224936 | W52: 14207661 | X52: 15280094 | Y52: 15285394 | Z52: 14987411 | AA52: 7771941 | AB52: 8140259 | AC52: 8216933 | AD52: 8240548 | AE52: 8307023 | AF52: 8491089 | AG52: 8480312 | AH52: 8474875 | AI52: 8466857 | AJ52: 8477586 | AK52: 8487440 | AL52: 8497309 | AM52: 8807249 | AN52: 9099047 | AO52: 9419751 | AP52: 9686711 | DH52: =IF(B52<>"", B52, DH51) -> 1 New England
A53: =IFERROR(INDEX(NEMS_mapping!C$3:C$12,MATCH(NEMS_residential!D53,NEMS_mapping!B$3:B$12,0)),A52) -> cooling and ventilation | G53: Sum of TOTPURCHASE | H53: 760 | I53: 2111 | J53: 2453 | K53: 2492 | L53: 2221 | M53: 2274 | N53: 2832 | O53: 2871 | P53: 2860 | Q53: 2958 | R53: 3039 | S53: 3144 | T53: 3288 | U53: 3458 | V53: 3666 | W53: 3897 | X53: 4153 | Y53: 4454 | Z53: 4725 | AA53: 4910 | AB53: 5136 | AC53: 5185 | AD53: 5201 | AE53: 5241 | AF53: 5355 | AG53: 5351 | AH53: 5345 | AI53: 5339 | AJ53: 5345 | AK53: 5350 | AL53: 5354 | AM53: 5537 | AN53: 5707 | AO53: 5893 | AP53: 6050 | DH53: =IF(B53<>"", B53, DH52) -> 1 New England
A54: =IFERROR(INDEX(NEMS_mapping!C$3:C$12,MATCH(NEMS_residential!D54,NEMS_mapping!B$3:B$12,0)),A53) -> cooling and ventilation | G54: Sum of TOTINVEST | H54: 0 | I54: 0 | J54: 0 | K54: 0 | L54: 0 | M54: 0 | N54: 0 | O54: 0 | P54: 0 | Q54: 0 | R54: 0 | S54: 0 | T54: 0 | U54: 0 | V54: 0 | W54: 0 | X54: 0 | Y54: 0 | Z54: 0 | AA54: 0 | AB54: 0 | AC54: 0 | AD54: 0 | AE54: 0 | AF54: 0 | AG54: 0 | AH54: 0 | AI54: 0 | AJ54: 0 | AK54: 0 | AL54: 0 | AM54: 0 | AN54: 0 | AO54: 0 | AP54: 0 | DH54: =IF(B54<>"", B54, DH53) -> 1 New England
A55: =IFERROR(INDEX(NEMS_mapping!C$3:C$12,MATCH(NEMS_residential!D55,NEMS_mapping!B$3:B$12,0)),A54) -> cooling and ventilation | F55: GEO_HP4 | G55: Sum of TOTSUBSIDY | H55: 11995145 | I55: 7414502 | J55: 8633060 | K55: 9115391 | L55: 6784571 | M55: 6826245 | N55: 9136083 | O55: 9721525 | P55: 8955733 | Q55: 9148538 | R55: 9383361 | S55: 9707085 | T55: 10172146 | U55: 10747190 | V55: 20709030 | W55: 19015994 | X55: 16982438 | Y55: 13893033 | Z55: 9344927 | AA55: 5381098 | AB55: 4662494 | AC55: 4611368 | AD55: 4231940 | AE55: 4223897 | AF55: 4107320 | AG55: 3970379 | AH55: 4015399 | AI55: 3954676 | AJ55: 4344456 | AK55: 4415299 | AL55: 4362930 | AM55: 4524515 | AN55: 4438381 | AO55: 5208398 | AP55: 5306364 | DH55: =IF(B55<>"", B55, DH54) -> 1 New England
A56: =IFERROR(INDEX(NEMS_mapping!C$3:C$12,MATCH(NEMS_residential!D56,NEMS_mapping!B$3:B$12,0)),A55) -> cooling and ventilation | G56: Sum of TOTPURCHASE | H56: 2792 | I56: 1725 | J56: 2018 | K56: 2126 | L56: 1719 | M56: 1730 | N56: 2160 | O56: 2294 | P56: 2116 | Q56: 2162 | R56: 2216 | S56: 2290 | T56: 2397 | U56: 2530 | V56: 5195 | W56: 4774 | X56: 4273 | Y56: 3805 | Z56: 2809 | AA56: 3312 | AB56: 2857 | AC56: 2814 | AD56: 2575 | AE56: 2563 | AF56: 2489 | AG56: 2404 | AH56: 2427 | AI56: 2389 | AJ56: 2622 | AK56: 2664 | AL56: 2631 | AM56: 2725 | AN56: 2669 | AO56: 3129 | AP56: 3183 | DH56: =IF(B56<>"", B56, DH55) -> 1 New England
A57: =IFERROR(INDEX(NEMS_mapping!C$3:C$12,MATCH(NEMS_residential!D57,NEMS_mapping!B$3:B$12,0)),A56) -> cooling and ventilation | G57: Sum of TOTINVEST | H57: 0 | I57: 0 | J57: 0 | K57: 0 | L57: 0 | M57: 0 | N57: 0 | O57: 0 | P57: 0 | Q57: 0 | R57: 0 | S57: 0 | T57: 0 | U57: 0 | V57: 0 | W57: 0 | X57: 0 | Y57: 0 | Z57: 0 | AA57: 0 | AB57: 0 | AC57: 0 | AD57: 0 | AE57: 0 | AF57: 0 | AG57: 0 | AH57: 0 | AI57: 0 | AJ57: 0 | AK57: 0 | AL57: 0 | AM57: 0 | AN57: 0 | AO57: 0 | AP57: 0 | DH57: =IF(B57<>"", B57, DH56) -> 1 New England
A58: =IFERROR(INDEX(NEMS_mapping!C$3:C$12,MATCH(NEMS_residential!D58,NEMS_mapping!B$3:B$12,0)),A57) -> cooling and ventilation | F58: ROOM_AIR1 | G58: Sum of TOTSUBSIDY | H58: 0 | I58: 0 | J58: 0 | K58: 0 | L58: 0 | M58: 0 | N58: 0 | O58: 0 | P58: 0 | Q58: 0 | R58: 0 | S58: 0 | T58: 0 | U58: 0 | V58: 0 | W58: 0 | X58: 0 | Y58: 0 | Z58: 0 | AA58: 0 | AB58: 0 | AC58: 0 | AD58: 0 | AE58: 0 | AF58: 0 | AG58: 0 | AH58: 0 | AI58: 0 | AJ58: 0 | AK58: 0 | AL58: 0 | AM58: 0 | AN58: 0 | AO58: 0 | AP58: 0 | DH58: =IF(B58<>"", B58, DH57) -> 1 New England
A59: =IFERROR(INDEX(NEMS_mapping!C$3:C$12,MATCH(NEMS_residential!D59,NEMS_mapping!B$3:B$12,0)),A58) -> cooling and ventilation | G59: Sum of TOTPURCHASE | H59: 58135 | I59: 60373 | J59: 64483 | K59: 72541 | L59: 77272 | M59: 84073 | N59: 77934 | O59: 88061 | P59: 98495 | Q59: 99453 | R59: 98604 | S59: 97951 | T59: 98359 | U59: 97379 | V59: 78735 | W59: 74077 | X59: 68978 | Y59: 73255 | Z59: 76201 | AA59: 78996 | AB59: 80105 | AC59: 80498 | AD59: 79974 | AE59: 79015 | AF59: 77026 | AG59: 75936 | AH59: 75310 | AI59: 75151 | AJ59: 75693 | AK59: 76348 | AL59: 76976 | AM59: 77586 | AN59: 77718 | AO59: 77856 | AP59: 77692 | DH59: =IF(B59<>"", B59, DH58) -> 1 New England
A60: =IFERROR(INDEX(NEMS_mapping!C$3:C$12,MATCH(NEMS_residential!D60,NEMS_mapping!B$3:B$12,0)),A59) -> cooling and ventilation | G60: Sum of TOTINVEST | H60: 31102712 | I60: 32299709 | J60: 34499359 | K60: 38810242 | L60: 41340864 | M60: 44979553 | N60: 41695279 | O60: 47113264 | P60: 52695397 | Q60: 53207769 | R60: 52753766 | S60: 52404125 | T60: 52622365 | U60: 52098402 | V60: 42123407 | W60: 39631870 | X60: 36904126 | Y60: 39192232 | Z60: 40768216 | AA60: 42263496 | AB60: 42856713 | AC60: 43066986 | AD60: 42786817 | AE60: 42273567 | AF60: 41209381 | AG60: 40626128 | AH60: 40291177 | AI60: 40206003 | AJ60: 40496478 | AK60: 40846733 | AL60: 41182437 | AM60: 41508800 | AN60: 41580114 | AO60: 41653177 | AP60: 41565858 | DH60: =IF(B60<>"", B60, DH59) -> 1 New England
A61: =IFERROR(INDEX(NEMS_mapping!C$3:C$12,MATCH(NEMS_residential!D61,NEMS_mapping!B$3:B$12,0)),A60) -> cooling and ventilation | F61: ROOM_AIR2 | G61: Sum of TOTSUBSIDY | H61: 0 | I61: 0 | J61: 0 | K61: 0 | L61: 0 | M61: 0 | N61: 0 | O61: 0 | P61: 0 | Q61: 0 | R61: 0 | S61: 0 | T61: 0 | U61: 0 | V61: 0 | W61: 0 | X61: 0 | Y61: 0 | Z61: 0 | AA61: 0 | AB61: 0 | AC61: 0 | AD61: 0 | AE61: 0 | AF61: 0 | AG61: 0 | AH61: 0 | AI61: 0 | AJ61: 0 | AK61: 0 | AL61: 0 | AM61: 0 | AN61: 0 | AO61: 0 | AP61: 0 | DH61: =IF(B61<>"", B61, DH60) -> 1 New England
A62: =IFERROR(INDEX(NEMS_mapping!C$3:C$12,MATCH(NEMS_residential!D62,NEMS_mapping!B$3:B$12,0)),A61) -> cooling and ventilation | G62: Sum of TOTPURCHASE | H62: 57055 | I62: 57423 | J62: 64048 | K62: 70215 | L62: 76328 | M62: 82162 | N62: 76318 | O62: 84356 | P62: 96019 | Q62: 97093 | R62: 96404 | S62: 95919 | T62: 96510 | U62: 95770 | V62: 78919 | W62: 74474 | X62: 69611 | Y62: 74092 | Z62: 77838 | AA62: 80720 | AB62: 82419 | AC62: 83101 | AD62: 82892 | AE62: 82118 | AF62: 82159 | AG62: 81314 | AH62: 80823 | AI62: 80874 | AJ62: 81461 | AK62: 82362 | AL62: 83299 | AM62: 84067 | AN62: 84486 | AO62: 84614 | AP62: 84517 | DH62: =IF(B62<>"", B62, DH61) -> 1 New England
A63: =IFERROR(INDEX(NEMS_mapping!C$3:C$12,MATCH(NEMS_residential!D63,NEMS_mapping!B$3:B$12,0)),A62) -> cooling and ventilation | G63: Sum of TOTINVEST | H63: 31666101 | I63: 31870128 | J63: 35547501 | K63: 38969659 | L63: 42362314 | M63: 45600577 | N63: 42357207 | O63: 46818431 | P63: 53291177 | Q63: 53887525 | R63: 53504909 | S63: 53235572 | T63: 53563946 | U63: 53153334 | V63: 43800568 | W63: 41333556 | X63: 38634756 | Y63: 41121340 | Z63: 43200564 | AA63: 44799912 | AB63: 45743403 | AC63: 46121829 | AD63: 46005367 | AE63: 45576455 | AF63: 45598829 | AG63: 45129581 | AH63: 44857255 | AI63: 44885996 | AJ63: 45211337 | AK63: 45711639 | AL63: 46231411 | AM63: 46657923 | AN63: 46890149 | AO63: 46961250 | AP63: 46907270 | DH63: =IF(B63<>"", B63, DH62) -> 1 New England
A64: =IFERROR(INDEX(NEMS_mapping!C$3:C$12,MATCH(NEMS_residential!D64,NEMS_mapping!B$3:B$12,0)),A63) -> cooling and ventilation | F64: ROOM_AIR3 | G64: Sum of TOTSUBSIDY | H64: 0 | I64: 0 | J64: 0 | K64: 0 | L64: 0 | M64: 0 | N64: 0 | O64: 0 | P64: 0 | Q64: 0 | R64: 0 | S64: 0 | T64: 0 | U64: 0 | V64: 0 | W64: 0 | X64: 0 | Y64: 0 | Z64: 0 | AA64: 0 | AB64: 0 | AC64: 0 | AD64: 0 | AE64: 0 | AF64: 0 | AG64: 0 | AH64: 0 | AI64: 0 | AJ64: 0 | AK64: 0 | AL64: 0 | AM64: 0 | AN64: 0 | AO64: 0 | AP64: 0 | DH64: =IF(B64<>"", B64, DH63) -> 1 New England
A65: =IFERROR(INDEX(NEMS_mapping!C$3:C$12,MATCH(NEMS_residential!D65,NEMS_mapping!B$3:B$12,0)),A64) -> cooling and ventilation | G65: Sum of TOTPURCHASE | H65: 57055 | I65: 57423 | J65: 64048 | K65: 70215 | L65: 76328 | M65: 82162 | N65: 76318 | O65: 84356 | P65: 96019 | Q65: 97093 | R65: 96404 | S65: 95919 | T65: 96510 | U65: 95770 | V65: 77572 | W65: 73165 | X65: 68345 | Y65: 72717 | Z65: 76275 | AA65: 79089 | AB65: 80678 | AC65: 81304 | AD65: 81051 | AE65: 80261 | AF65: 78474 | AG65: 77588 | AH65: 77069 | AI65: 77061 | AJ65: 77609 | AK65: 78414 | AL65: 79239 | AM65: 79935 | AN65: 80263 | AO65: 80378 | AP65: 80259 | DH65: =IF(B65<>"", B65, DH64) -> 1 New England
A66: =IFERROR(INDEX(NEMS_mapping!C$3:C$12,MATCH(NEMS_residential!D66,NEMS_mapping!B$3:B$12,0)),A65) -> cooling and ventilation | G66: Sum of TOTINVEST | H66: 31666101 | I66: 31870128 | J66: 35547501 | K66: 38969659 | L66: 42362314 | M66: 45600577 | N66: 42357207 | O66: 46818431 | P66: 53291177 | Q66: 53887525 | R66: 53504909 | S66: 53235572 | T66: 53563946 | U66: 53153334 | V66: 43052984 | W66: 40607600 | X66: 37932036 | Y66: 40358315 | Z66: 42333259 | AA66: 43894921 | AB66: 44776880 | AC66: 45124264 | AD66: 44983928 | AE66: 44545803 | AF66: 43553676 | AG66: 43061780 | AH66: 42774117 | AI66: 42769251 | AJ66: 43073765 | AK66: 43520338 | AL66: 43978200 | AM66: 44364545 | AN66: 44546424 | AO66: 44610332 | AP66: 44543867 | DH66: =IF(B66<>"", B66, DH65) -> 1 New England
A67: =IFERROR(INDEX(NEMS_mapping!C$3:C$12,MATCH(NEMS_residential!D67,NEMS_mapping!B$3:B$12,0)),A66) -> cooling and ventilation | F67: ROOM_AIR4 | G67: Sum of TOTSUBSIDY | H67: 0 | I67: 0 | J67: 0 | K67: 0 | L67: 0 | M67: 0 | N67: 0 | O67: 0 | P67: 0 | Q67: 0 | R67: 0 | S67: 0 | T67: 0 | U67: 0 | V67: 0 | W67: 0 | X67: 0 | Y67: 0 | Z67: 0 | AA67: 0 | AB67: 0 | AC67: 0 | AD67: 0 | AE67: 0 | AF67: 0 | AG67: 0 | AH67: 0 | AI67: 0 | AJ67: 0 | AK67: 0 | AL67: 0 | AM67: 0 | AN67: 0 | AO67: 0 | AP67: 0 | DH67: =IF(B67<>"", B67, DH66) -> 1 New England
A68: =IFERROR(INDEX(NEMS_mapping!C$3:C$12,MATCH(NEMS_residential!D68,NEMS_mapping!B$3:B$12,0)),A67) -> cooling and ventilation | G68: Sum of TOTPURCHASE | H68: 42041 | I68: 41993 | J68: 47366 | K68: 51644 | L68: 56374 | M68: 60480 | N68: 113794 | O68: 124686 | P68: 142912 | Q68: 144596 | R68: 143652 | S68: 143018 | T68: 144014 | U68: 143042 | V68: 179415 | W68: 169548 | X68: 158754 | Y68: 169149 | Z68: 178860 | AA68: 185295 | AB68: 190476 | AC68: 192516 | AD68: 192663 | AE68: 191214 | AF68: 195024 | AG68: 193578 | AH68: 192594 | AI68: 193035 | AJ68: 194211 | AK68: 196578 | AL68: 199212 | AM68: 201042 | AN68: 202470 | AO68: 202458 | AP68: 202182 | DH68: =IF(B68<>"", B68, DH67) -> 1 New England
A69: =IFERROR(INDEX(NEMS_mapping!C$3:C$12,MATCH(NEMS_residential!D69,NEMS_mapping!B$3:B$12,0)),A68) -> cooling and ventilation | G69: Sum of TOTINVEST | H69: 26066090 | I69: 26036078 | J69: 29367254 | K69: 32019720 | L69: 34952055 | M69: 37497877 | N69: 70553392 | O69: 77306366 | P69: 88607350 | Q69: 89650510 | R69: 89064944 | S69: 88672950 | T69: 89290400 | U69: 88687162 | V69: 111239283 | W69: 105120573 | X69: 98430318 | Y69: 104873784 | Z69: 110896620 | AA69: 114884307 | AB69: 118097013 | AC69: 119362413 | AD69: 119453595 | AE69: 118554555 | AF69: 120916767 | AG69: 120019884 | AH69: 119408856 | AI69: 119684073 | AJ69: 120412659 | AK69: 121878948 | AL69: 123512619 | AM69: 124648119 | AN69: 125533041 | AO69: 125525652 | AP69: 125355000 | DH69: =IF(B69<>"", B69, DH68) -> 1 New England
A70: =IFERROR(INDEX(NEMS_mapping!C$3:C$12,MATCH(NEMS_residential!D70,NEMS_mapping!B$3:B$12,0)),A69) -> cooling and ventilation | E70: Natural Gas | F70: NG_HP2 | G70: Sum of TOTSUBSIDY | H70: 0 | I70: 0 | J70: 0 | K70: 0 | L70: 0 | M70: 0 | N70: 0 | O70: 0 | P70: 0 | Q70: 0 | R70: 0 | S70: 0 | T70: 0 | U70: 0 | V70: 0 | W70: 0 | X70: 0 | Y70: 0 | Z70: 0 | AA70: 0 | AB70: 0 | AC70: 0 | AD70: 0 | AE70: 0 | AF70: 0 | AG70: 0 | AH70: 0 | AI70: 0 | AJ70: 0 | AK70: 0 | AL70: 0 | AM70: 0 | AN70: 0 | AO70: 0 | AP70: 0 | DH70: =IF(B70<>"", B70, DH69) -> 1 New England
A71: =IFERROR(INDEX(NEMS_mapping!C$3:C$12,MATCH(NEMS_residential!D71,NEMS_mapping!B$3:B$12,0)),A70) -> cooling and ventilation | G71: Sum of TOTPURCHASE | H71: 552 | I71: 570 | J71: 588 | K71: 611 | L71: 637 | M71: 669 | N71: 2930 | O71: 2402 | P71: 3869 | Q71: 4538 | R71: 5198 | S71: 5738 | T71: 5471 | U71: 5179 | V71: 257980 | W71: 250284 | X71: 240570 | Y71: 227160 | Z71: 211265 | AA71: 222521 | AB71: 232569 | AC71: 240589 | AD71: 246827 | AE71: 251420 | AF71: 254691 | AG71: 256505 | AH71: 256998 | AI71: 256792 | AJ71: 256360 | AK71: 255684 | AL71: 255094 | AM71: 254940 | AN71: 255155 | AO71: 256009 | AP71: 257160 | DH71: =IF(B71<>"", B71, DH70) -> 1 New England
A72: =IFERROR(INDEX(NEMS_mapping!C$3:C$12,MATCH(NEMS_residential!D72,NEMS_mapping!B$3:B$12,0)),A71) -> cooling and ventilation | G72: Sum of TOTINVEST | H72: 0 | I72: 0 | J72: 0 | K72: 0 | L72: 0 | M72: 0 | N72: 0 | O72: 0 | P72: 0 | Q72: 0 | R72: 0 | S72: 0 | T72: 0 | U72: 0 | V72: 0 | W72: 0 | X72: 0 | Y72: 0 | Z72: 0 | AA72: 0 | AB72: 0 | AC72: 0 | AD72: 0 | AE72: 0 | AF72: 0 | AG72: 0 | AH72: 0 | AI72: 0 | AJ72: 0 | AK72: 0 | AL72: 0 | AM72: 0 | AN72: 0 | AO72: 0 | AP72: 0 | DH72: =IF(B72<>"", B72, DH71) -> 1 New England
A73: =IFERROR(INDEX(NEMS_mapping!C$3:C$12,MATCH(NEMS_residential!D73,NEMS_mapping!B$3:B$12,0)),A72) -> appliances | D73: Clothes Washing | E73: Electricity | F73: CL_WASH_F1 | G73: Sum of TOTSUBSIDY | H73: 0 | I73: 0 | J73: 0 | K73: 0 | L73: 0 | M73: 0 | N73: 0 | O73: 0 | P73: 0 | Q73: 0 | R73: 0 | S73: 0 | T73: 0 | U73: 0 | V73: 0 | W73: 0 | X73: 0 | Y73: 0 | Z73: 0 | AA73: 0 | AB73: 0 | AC73: 0 | AD73: 0 | AE73: 0 | AF73: 0 | AG73: 0 | AH73: 0 | AI73: 0 | AJ73: 0 | AK73: 0 | AL73: 0 | AM73: 0 | AN73: 0 | AO73: 0 | AP73: 0 | DH73: =IF(B73<>"", B73, DH72) -> 1 New England
A74: =IFERROR(INDEX(NEMS_mapping!C$3:C$12,MATCH(NEMS_residential!D74,NEMS_mapping!B$3:B$12,0)),A73) -> appliances | G74: Sum of TOTPURCHASE | H74: 275 | I74: 267 | J74: 230 | K74: 230 | L74: 1345 | M74: 1572 | N74: 1613 | O74: 1481 | P74: 1955 | Q74: 2199 | R74: 2449 | S74: 2690 | T74: 2597 | U74: 2497 | V74: 3451 | W74: 3259 | X74: 3025 | Y74: 2774 | Z74: 2301 | AA74: 2563 | AB74: 2439 | AC74: 2466 | AD74: 2397 | AE74: 2415 | AF74: 2399 | AG74: 2369 | AH74: 2382 | AI74: 2363 | AJ74: 2467 | AK74: 2482 | AL74: 2464 | AM74: 2505 | AN74: 2482 | AO74: 2678 | AP74: 2706 | DH74: =IF(B74<>"", B74, DH73) -> 1 New England
A75: =IFERROR(INDEX(NEMS_mapping!C$3:C$12,MATCH(NEMS_residential!D75,NEMS_mapping!B$3:B$12,0)),A74) -> appliances | G75: Sum of TOTINVEST | H75: 221171 | I75: 213821 | J75: 184712 | K75: 184748 | L75: 1076983 | M75: 1258366 | N75: 1291582 | O75: 1186124 | P75: 1565040 | Q75: 1759859 | R75: 1960048 | S75: 2153316 | T75: 2078528 | U75: 1998521 | V75: 2761759 | W75: 2608671 | X75: 2420571 | Y75: 2220317 | Z75: 1841931 | AA75: 2051546 | AB75: 1951932 | AC75: 1973547 | AD75: 1918718 | AE75: 1933386 | AF75: 1920184 | AG75: 1895986 | AH75: 1906556 | AI75: 1891306 | AJ75: 1974782 | AK75: 1986595 | AL75: 1972311 | AM75: 2004778 | AN75: 1986447 | AO75: 2143503 | AP75: 2165979 | DH75: =IF(B75<>"", B75, DH74) -> 1 New England
A76: =IFERROR(INDEX(NEMS_mapping!C$3:C$12,MATCH(NEMS_residential!D76,NEMS_mapping!B$3:B$12,0)),A75) -> appliances | F76: CL_WASH_F2 | G76: Sum of TOTSUBSIDY | H76: 0 | I76: 0 | J76: 0 | K76: 0 | L76: 0 | M76: 0 | N76: 0 | O76: 0 | P76: 0 | Q76: 0 | R76: 0 | S76: 0 | T76: 0 | U76: 0 | V76: 0 | W76: 0 | X76: 0 | Y76: 0 | Z76: 0 | AA76: 0 | AB76: 0 | AC76: 0 | AD76: 0 | AE76: 0 | AF76: 0 | AG76: 0 | AH76: 0 | AI76: 0 | AJ76: 0 | AK76: 0 | AL76: 0 | AM76: 0 | AN76: 0 | AO76: 0 | AP76: 0 | DH76: =IF(B76<>"", B76, DH75) -> 1 New England
A77: =IFERROR(INDEX(NEMS_mapping!C$3:C$12,MATCH(NEMS_residential!D77,NEMS_mapping!B$3:B$12,0)),A76) -> appliances | G77: Sum of TOTPURCHASE | H77: 4927 | I77: 5019 | J77: 5096 | K77: 5264 | L77: 29771 | M77: 30601 | N77: 31633 | O77: 33505 | P77: 34260 | Q77: 36458 | R77: 39146 | S77: 42738 | T77: 41920 | U77: 41136 | V77: 22394 | W77: 21962 | X77: 21412 | Y77: 20456 | Z77: 19916 | AA77: 20513 | AB77: 22338 | AC77: 23411 | AD77: 24751 | AE77: 25364 | AF77: 25976 | AG77: 26447 | AH77: 26445 | AI77: 26528 | AJ77: 25838 | AK77: 25647 | AL77: 25657 | AM77: 25402 | AN77: 25566 | AO77: 24624 | AP77: 24651 | DH77: =IF(B77<>"", B77, DH76) -> 1 New England
A78: =IFERROR(INDEX(NEMS_mapping!C$3:C$12,MATCH(NEMS_residential!D78,NEMS_mapping!B$3:B$12,0)),A77) -> appliances | G78: Sum of TOTINVEST | H78: 4188463 | I78: 4267185 | J78: 4332931 | K78: 4475359 | L78: 25306017 | M78: 26012348 | N78: 26888892 | O78: 28480005 | P78: 29121874 | Q78: 30990433 | R78: 33275417 | S78: 36327811 | T78: 35633135 | U78: 34965940 | V78: 21275683 | W78: 20865102 | X78: 20342608 | Y78: 19434161 | Z78: 18920798 | AA78: 19489094 | AB78: 21222629 | AC78: 22241024 | AD78: 23515063 | AE78: 24096896 | AF78: 24678315 | AG78: 25125284 | AH78: 25123600 | AI78: 25202760 | AJ78: 24546838 | AK78: 24365614 | AL78: 24375585 | AM78: 24132627 | AN78: 24288171 | AO78: 23393596 | AP78: 23419354 | DH78: =IF(B78<>"", B78, DH77) -> 1 New England
A79: =IFERROR(INDEX(NEMS_mapping!C$3:C$12,MATCH(NEMS_residential!D79,NEMS_mapping!B$3:B$12,0)),A78) -> appliances | F79: CL_WASH_F3 | G79: Sum of TOTSUBSIDY | H79: 0 | I79: 0 | J79: 0 | K79: 0 | L79: 0 | M79: 0 | N79: 0 | O79: 0 | P79: 0 | Q79: 0 | R79: 0 | S79: 0 | T79: 0 | U79: 0 | V79: 0 | W79: 0 | X79: 0 | Y79: 0 | Z79: 0 | AA79: 0 | AB79: 0 | AC79: 0 | AD79: 0 | AE79: 0 | AF79: 0 | AG79: 0 | AH79: 0 | AI79: 0 | AJ79: 0 | AK79: 0 | AL79: 0 | AM79: 0 | AN79: 0 | AO79: 0 | AP79: 0 | DH79: =IF(B79<>"", B79, DH78) -> 1 New England
A80: =IFERROR(INDEX(NEMS_mapping!C$3:C$12,MATCH(NEMS_residential!D80,NEMS_mapping!B$3:B$12,0)),A79) -> appliances | G80: Sum of TOTPURCHASE | H80: 4990 | I80: 4999 | J80: 4810 | K80: 4907 | L80: 28082 | M80: 30137 | N80: 31082 | O80: 31339 | P80: 34893 | Q80: 37791 | R80: 41054 | S80: 44911 | T80: 43826 | U80: 42727 | V80: 58375 | W80: 56423 | X80: 53968 | Y80: 50754 | Z80: 46448 | AA80: 49312 | AB80: 50789 | AC80: 52293 | AD80: 53053 | AE80: 53918 | AF80: 54395 | AG80: 54555 | AH80: 54702 | AI80: 54575 | AJ80: 54998 | AK80: 54952 | AL80: 54769 | AM80: 54929 | AN80: 54861 | AO80: 55881 | AP80: 56200 | DH80: =IF(B80<>"", B80, DH79) -> 1 New England
A81: =IFERROR(INDEX(NEMS_mapping!C$3:C$12,MATCH(NEMS_residential!D81,NEMS_mapping!B$3:B$12,0)),A80) -> appliances | G81: Sum of TOTINVEST | H81: 3992433 | I81: 3999952 | J81: 3849258 | K81: 3926186 | L81: 22466427 | M81: 24110741 | N81: 24866986 | O81: 25071525 | P81: 27914996 | Q81: 30233723 | R81: 32844570 | S81: 35929328 | T81: 35062181 | U81: 34182889 | V81: 46700587 | W81: 45139546 | X81: 43175426 | Y81: 40603971 | Z81: 37159691 | AA81: 39450153 | AB81: 40632174 | AC81: 41835364 | AD81: 42443319 | AE81: 43135781 | AF81: 43516571 | AG81: 43644979 | AH81: 43762422 | AI81: 43660813 | AJ81: 43999251 | AK81: 43962082 | AL81: 43815799 | AM81: 43944024 | AN81: 43889269 | AO81: 44705173 | AP81: 44961272 | DH81: =IF(B81<>"", B81, DH80) -> 1 New England
A82: =IFERROR(INDEX(NEMS_mapping!C$3:C$12,MATCH(NEMS_residential!D82,NEMS_mapping!B$3:B$12,0)),A81) -> appliances | F82: CL_WASH_F4 | G82: Sum of TOTSUBSIDY | H82: 4729302 | I82: 4841911 | J82: 4983926 | K82: 5144128 | L82: 39183 | M82: 38559 | N82: 40158 | O82: 45123 | P82: 42743 | Q82: 45007 | R82: 48077 | S82: 52553 | T82: 51701 | U82: 50943 | V82: 69394 | W82: 68294 | X82: 66875 | Y82: 64104 | Z82: 63348 | AA82: 64847 | AB82: 72246 | AC82: 76752 | AD82: 83630 | AE82: 86257 | AF82: 89305 | AG82: 91908 | AH82: 91760 | AI82: 92424 | AJ82: 87894 | AK82: 86851 | AL82: 87135 | AM82: 85499 | AN82: 86547 | AO82: 80129 | AP82: 79981 | DH82: =IF(B82<>"", B82, DH81) -> 1 New England
A83: =IFERROR(INDEX(NEMS_mapping!C$3:C$12,MATCH(NEMS_residential!D83,NEMS_mapping!B$3:B$12,0)),A82) -> appliances | G83: Sum of TOTPURCHASE | H83: 42924 | I83: 43983 | J83: 45273 | K83: 46713 | L83: 283 | M83: 279 | N83: 290 | O83: 323 | P83: 306 | Q83: 321 | R83: 342 | S83: 373 | T83: 367 | U83: 362 | V83: 491 | W83: 483 | X83: 473 | Y83: 454 | Z83: 449 | AA83: 459 | AB83: 511 | AC83: 543 | AD83: 591 | AE83: 608 | AF83: 630 | AG83: 648 | AH83: 647 | AI83: 652 | AJ83: 619 | AK83: 612 | AL83: 614 | AM83: 603 | AN83: 610 | AO83: 564 | AP83: 563 | DH83: =IF(B83<>"", B83, DH82) -> 1 New England
A84: =IFERROR(INDEX(NEMS_mapping!C$3:C$12,MATCH(NEMS_residential!D84,NEMS_mapping!B$3:B$12,0)),A83) -> appliances | G84: Sum of TOTINVEST | H84: 38632906 | I84: 39585777 | J84: 40745899 | K84: 42042420 | L84: 255657 | M84: 252314 | N84: 261222 | O84: 291657 | P84: 276032 | Q84: 290212 | R84: 309119 | S84: 337011 | T84: 331731 | U84: 326976 | V84: 491881 | W84: 484184 | X84: 474376 | Y84: 455018 | Z84: 450070 | AA84: 460015 | AB84: 511933 | AC84: 543337 | AD84: 591583 | AE84: 609776 | AF84: 631164 | AG84: 649417 | AH84: 648115 | AI84: 652664 | AJ84: 620584 | AK84: 613142 | AL84: 615026 | AM84: 603335 | AN84: 610536 | AO84: 565056 | AP84: 563811 | DH84: =IF(B84<>"", B84, DH83) -> 1 New England
A85: =IFERROR(INDEX(NEMS_mapping!C$3:C$12,MATCH(NEMS_residential!D85,NEMS_mapping!B$3:B$12,0)),A84) -> appliances | F85: CL_WASH_T1 | G85: Sum of TOTSUBSIDY | H85: 0 | I85: 0 | J85: 0 | K85: 0 | L85: 0 | M85: 0 | N85: 0 | O85: 0 | P85: 0 | Q85: 0 | R85: 0 | S85: 0 | T85: 0 | U85: 0 | V85: 0 | W85: 0 | X85: 0 | Y85: 0 | Z85: 0 | AA85: 0 | AB85: 0 | AC85: 0 | AD85: 0 | AE85: 0 | AF85: 0 | AG85: 0 | AH85: 0 | AI85: 0 | AJ85: 0 | AK85: 0 | AL85: 0 | AM85: 0 | AN85: 0 | AO85: 0 | AP85: 0 | DH85: =IF(B85<>"", B85, DH84) -> 1 New England
A86: =IFERROR(INDEX(NEMS_mapping!C$3:C$12,MATCH(NEMS_residential!D86,NEMS_mapping!B$3:B$12,0)),A85) -> appliances | G86: Sum of TOTPURCHASE | H86: 52527 | I86: 51371 | J86: 44615 | K86: 44058 | L86: 2221 | M86: 2870 | N86: 2930 | O86: 2402 | P86: 3869 | Q86: 4538 | R86: 5198 | S86: 5738 | T86: 5471 | U86: 5179 | V86: 5195 | W86: 4774 | X86: 4273 | Y86: 3805 | Z86: 2809 | AA86: 3312 | AB86: 2857 | AC86: 2814 | AD86: 2575 | AE86: 2563 | AF86: 2489 | AG86: 2404 | AH86: 2427 | AI86: 2389 | AJ86: 2622 | AK86: 2664 | AL86: 2631 | AM86: 2725 | AN86: 2669 | AO86: 3129 | AP86: 3183 | DH86: =IF(B86<>"", B86, DH85) -> 1 New England
A87: =IFERROR(INDEX(NEMS_mapping!C$3:C$12,MATCH(NEMS_residential!D87,NEMS_mapping!B$3:B$12,0)),A86) -> appliances | G87: Sum of TOTINVEST | H87: 26263835 | I87: 25685849 | J87: 22308113 | K87: 22029574 | L87: 1110791 | M87: 1435348 | N87: 1465260 | O87: 1201088 | P87: 1934849 | Q87: 2269443 | R87: 2599321 | S87: 2869363 | T87: 2735945 | U87: 2590009 | V87: 2597923 | W87: 2387637 | X87: 2136999 | Y87: 1902989 | Z87: 1405151 | AA87: 1656600 | AB87: 1428855 | AC87: 1407541 | AD87: 1287754 | AE87: 1281897 | AF87: 1245230 | AG87: 1202664 | AH87: 1214286 | AI87: 1194902 | AJ87: 1311901 | AK87: 1332570 | AL87: 1315706 | AM87: 1363108 | AN87: 1335462 | AO87: 1564792 | AP87: 1591957 | DH87: =IF(B87<>"", B87, DH86) -> 1 New England
A88: =IFERROR(INDEX(NEMS_mapping!C$3:C$12,MATCH(NEMS_residential!D88,NEMS_mapping!B$3:B$12,0)),A87) -> appliances | F88: CL_WASH_T2 | G88: Sum of TOTSUBSIDY | H88: 0 | I88: 0 | J88: 0 | K88: 0 | L88: 0 | M88: 0 | N88: 0 | O88: 0 | P88: 0 | Q88: 0 | R88: 0 | S88: 0 | T88: 0 | U88: 0 | V88: 0 | W88: 0 | X88: 0 | Y88: 0 | Z88: 0 | AA88: 0 | AB88: 0 | AC88: 0 | AD88: 0 | AE88: 0 | AF88: 0 | AG88: 0 | AH88: 0 | AI88: 0 | AJ88: 0 | AK88: 0 | AL88: 0 | AM88: 0 | AN88: 0 | AO88: 0 | AP88: 0 | DH88: =IF(B88<>"", B88, DH87) -> 1 New England
A89: =IFERROR(INDEX(NEMS_mapping!C$3:C$12,MATCH(NEMS_residential!D89,NEMS_mapping!B$3:B$12,0)),A88) -> appliances | G89: Sum of TOTPURCHASE | H89: 52527 | I89: 51371 | J89: 44615 | K89: 44058 | L89: 181833 | M89: 191178 | N89: 197389 | O89: 203722 | P89: 217805 | Q89: 233906 | R89: 252675 | S89: 276140 | T89: 270143 | U89: 264195 | V89: 257980 | W89: 250284 | X89: 240570 | Y89: 227160 | Z89: 211265 | AA89: 222521 | AB89: 232569 | AC89: 240589 | AD89: 246827 | AE89: 251420 | AF89: 254691 | AG89: 256505 | AH89: 256998 | AI89: 256792 | AJ89: 256360 | AK89: 255684 | AL89: 255094 | AM89: 254940 | AN89: 255155 | AO89: 256009 | AP89: 257160 | DH89: =IF(B89<>"", B89, DH88) -> 1 New England
A90: =IFERROR(INDEX(NEMS_mapping!C$3:C$12,MATCH(NEMS_residential!D90,NEMS_mapping!B$3:B$12,0)),A89) -> appliances | G90: Sum of TOTINVEST | H90: 26263835 | I90: 25685849 | J90: 22308113 | K90: 22029574 | L90: 109100659 | M90: 114707793 | N90: 118433757 | O90: 122233557 | P90: 130683391 | Q90: 140344172 | R90: 151605993 | S90: 165684326 | T90: 162086320 | U90: 158517684 | V90: 154788756 | W90: 150171014 | X90: 144342988 | Y90: 136296487 | Z90: 126759505 | AA90: 133513295 | AB90: 139541976 | AC90: 144354405 | AD90: 148096256 | AE90: 150852605 | AF90: 152815127 | AG90: 153903443 | AH90: 154199724 | AI90: 154075461 | AJ90: 153816695 | AK90: 153411241 | AL90: 153057107 | AM90: 152964533 | AN90: 153093430 | AO90: 153606085 | AP90: 154296514 | DH90: =IF(B90<>"", B90, DH89) -> 1 New England
A91: =IFERROR(INDEX(NEMS_mapping!C$3:C$12,MATCH(NEMS_residential!D91,NEMS_mapping!B$3:B$12,0)),A90) -> appliances | F91: CL_WASH_T3 | G91: Sum of TOTSUBSIDY | H91: 0 | I91: 0 | J91: 0 | K91: 0 | L91: 0 | M91: 0 | N91: 0 | O91: 0 | P91: 0 | Q91: 0 | R91: 0 | S91: 0 | T91: 0 | U91: 0 | V91: 0 | W91: 0 | X91: 0 | Y91: 0 | Z91: 0 | AA91: 0 | AB91: 0 | AC91: 0 | AD91: 0 | AE91: 0 | AF91: 0 | AG91: 0 | AH91: 0 | AI91: 0 | AJ91: 0 | AK91: 0 | AL91: 0 | AM91: 0 | AN91: 0 | AO91: 0 | AP91: 0 | DH91: =IF(B91<>"", B91, DH90) -> 1 New England
A92: =IFERROR(INDEX(NEMS_mapping!C$3:C$12,MATCH(NEMS_residential!D92,NEMS_mapping!B$3:B$12,0)),A91) -> appliances | G92: Sum of TOTPURCHASE | H92: 12677 | I92: 13482 | J92: 15370 | K92: 16216 | L92: 767 | M92: 796 | N92: 822 | O92: 868 | P92: 907 | Q92: 974 | R92: 1053 | S92: 1150 | T92: 1125 | U92: 1100 | V92: 1074 | W92: 1043 | X92: 1002 | Y92: 946 | Z92: 880 | AA92: 926 | AB92: 980 | AC92: 1027 | AD92: 1084 | AE92: 1111 | AF92: 1137 | AG92: 1157 | AH92: 1157 | AI92: 1160 | AJ92: 1131 | AK92: 1123 | AL92: 1123 | AM92: 1112 | AN92: 1119 | AO92: 1081 | AP92: 1081 | DH92: =IF(B92<>"", B92, DH91) -> 1 New England
A93: =IFERROR(INDEX(NEMS_mapping!C$3:C$12,MATCH(NEMS_residential!D93,NEMS_mapping!B$3:B$12,0)),A92) -> appliances | G93: Sum of TOTINVEST | H93: 10142450 | I93: 10786686 | J93: 12296122 | K93: 12973592 | L93: 614384 | M93: 637670 | N93: 658382 | O93: 694607 | P93: 726479 | Q93: 780185 | R93: 842790 | S93: 921053 | T93: 901051 | U93: 881214 | V93: 860485 | W93: 834813 | X93: 802417 | Y93: 757686 | Z93: 704667 | AA93: 742214 | AB93: 784663 | AC93: 821921 | AD93: 867903 | AE93: 889132 | AF93: 910108 | AG93: 926089 | AH93: 926125 | AI93: 928852 | AJ93: 905773 | AK93: 899283 | AL93: 899541 | AM93: 890954 | AN93: 896469 | AO93: 864891 | AP93: 865946 | DH93: =IF(B93<>"", B93, DH92) -> 1 New England
A94: =IFERROR(INDEX(NEMS_mapping!C$3:C$12,MATCH(NEMS_residential!D94,NEMS_mapping!B$3:B$12,0)),A93) -> appliances | F94: CL_WASH_T4 | G94: Sum of TOTSUBSIDY | H94: 5965476 | I94: 6569360 | J94: 8369038 | K94: 9040568 | L94: 418299 | M94: 396966 | N94: 412791 | O94: 482149 | P94: 423225 | Q94: 438057 | R94: 462103 | S94: 503387 | T94: 497746 | U94: 493499 | V94: 476413 | W94: 472899 | X94: 468404 | Y94: 453295 | Z94: 464781 | AA94: 467022 | AB94: 536402 | AC94: 574409 | AD94: 638188 | AE94: 660674 | AF94: 688958 | AG94: 714183 | AH94: 711938 | AI94: 718938 | AJ94: 672376 | AK94: 662250 | AL94: 665554 | AM94: 648912 | AN94: 659195 | AO94: 594061 | AP94: 591566 | DH94: =IF(B94<>"", B94, DH93) -> 1 New England
A95: =IFERROR(INDEX(NEMS_mapping!C$3:C$12,MATCH(NEMS_residential!D95,NEMS_mapping!B$3:B$12,0)),A94) -> appliances | G95: Sum of TOTPURCHASE | H95: 50479 | I95: 55632 | J95: 70872 | K95: 76536 | L95: 3544 | M95: 3368 | N95: 3494 | O95: 4071 | P95: 3572 | Q95: 3695 | R95: 3894 | S95: 4237 | T95: 4190 | U95: 4155 | V95: 4011 | W95: 3982 | X95: 3945 | Y95: 3819 | Z95: 3918 | AA95: 3934 | AB95: 4515 | AC95: 4833 | AD95: 5368 | AE95: 5555 | AF95: 5793 | AG95: 6004 | AH95: 5984 | AI95: 6043 | AJ95: 5650 | AK95: 5565 | AL95: 5592 | AM95: 5452 | AN95: 5537 | AO95: 4989 | AP95: 4967 | DH95: =IF(B95<>"", B95, DH94) -> 1 New England
A96: =IFERROR(INDEX(NEMS_mapping!C$3:C$12,MATCH(NEMS_residential!D96,NEMS_mapping!B$3:B$12,0)),A95) -> appliances | G96: Sum of TOTINVEST | H96: 49218110 | I96: 54242585 | J96: 69100869 | K96: 74623654 | L96: 3456880 | M96: 3284250 | N96: 3407294 | O96: 3969914 | P96: 3483537 | Q96: 3603481 | R96: 3797016 | S96: 4131953 | T96: 4086535 | U96: 4052219 | V96: 3912005 | W96: 3883576 | X96: 3847709 | Y96: 3724856 | Z96: 3821049 | AA96: 3836454 | AB96: 4403896 | AC96: 4713589 | AD96: 5234941 | AE96: 5417587 | AF96: 5648792 | AG96: 5854965 | AH96: 5835347 | AI96: 5892086 | AJ96: 5510083 | AK96: 5426729 | AL96: 5453253 | AM96: 5316238 | AN96: 5399624 | AO96: 4865169 | AP96: 4843867 | DH96: =IF(B96<>"", B96, DH95) -> 1 New England
A97: =IFERROR(INDEX(NEMS_mapping!C$3:C$12,MATCH(NEMS_residential!D97,NEMS_mapping!B$3:B$12,0)),A96) -> appliances | D97: Clothes Drying | E97: Electricity | F97: ELEC_DRY1 | G97: Sum of TOTSUBSIDY | H97: 0 | I97: 0 | J97: 0 | K97: 0 | L97: 0 | M97: 0 | N97: 0 | O97: 0 | P97: 0 | Q97: 0 | R97: 0 | S97: 0 | T97: 0 | U97: 0 | V97: 0 | W97: 0 | X97: 0 | Y97: 0 | Z97: 0 | AA97: 0 | AB97: 0 | AC97: 0 | AD97: 0 | AE97: 0 | AF97: 0 | AG97: 0 | AH97: 0 | AI97: 0 | AJ97: 0 | AK97: 0 | AL97: 0 | AM97: 0 | AN97: 0 | AO97: 0 | AP97: 0 | DH97: =IF(B97<>"", B97, DH96) -> 1 New England
A98: =IFERROR(INDEX(NEMS_mapping!C$3:C$12,MATCH(NEMS_residential!D98,NEMS_mapping!B$3:B$12,0)),A97) -> appliances | G98: Sum of TOTPURCHASE | H98: 98686 | I98: 101478 | J98: 103255 | K98: 106016 | L98: 111162 | M98: 119096 | N98: 123326 | O98: 126856 | P98: 136472 | Q98: 146621 | R98: 159168 | S98: 173747 | T98: 172029 | U98: 171365 | V98: 170195 | W98: 168678 | X98: 166561 | Y98: 162879 | Z98: 157227 | AA98: 150045 | AB98: 141078 | AC98: 147374 | AD98: 152598 | AE98: 157487 | AF98: 161728 | AG98: 165026 | AH98: 167379 | AI98: 168760 | AJ98: 169892 | AK98: 169837 | AL98: 169054 | AM98: 168269 | AN98: 167133 | AO98: 167204 | AP98: 166904 | DH98: =IF(B98<>"", B98, DH97) -> 1 New England
A99: =IFERROR(INDEX(NEMS_mapping!C$3:C$12,MATCH(NEMS_residential!D99,NEMS_mapping!B$3:B$12,0)),A98) -> appliances | G99: Sum of TOTINVEST | H99: 41448648 | I99: 42621410 | J99: 43367280 | K99: 44527213 | L99: 46688633 | M99: 50020752 | N99: 51797603 | O99: 53279803 | P99: 57318838 | Q99: 61581291 | R99: 66850753 | S99: 72974166 | T99: 72252488 | U99: 71973751 | V99: 71482246 | W99: 70845318 | X99: 69956200 | Y99: 68409332 | Z99: 66035720 | AA99: 63019096 | AB99: 59253505 | AC99: 61897717 | AD99: 64091333 | AE99: 66145073 | AF99: 67926205 | AG99: 69311428 | AH99: 70299700 | AI99: 70879704 | AJ99: 71355287 | AK99: 71332153 | AL99: 71003102 | AM99: 70673460 | AN99: 70195975 | AO99: 70226100 | AP99: 70099887 | DH99: =IF(B99<>"", B99, DH98) -> 1 New England
A100: =IFERROR(INDEX(NEMS_mapping!C$3:C$12,MATCH(NEMS_residential!D100,NEMS_mapping!B$3:B$12,0)),A99) -> appliances | F100: ELEC_DRY2 | G100: Sum of TOTSUBSIDY | H100: 0 | I100: 0 | J100: 0 | K100: 0 | L100: 0 | M100: 0 | N100: 0 | O100: 0 | P100: 0 | Q100: 0 | R100: 0 | S100: 0 | T100: 0 | U100: 0 | V100: 0 | W100: 0 | X100: 0 | Y100: 0 | Z100: 0 | AA100: 0 | AB100: 0 | AC100: 0 | AD100: 0 | AE100: 0 | AF100: 0 | AG100: 0 | AH100: 0 | AI100: 0 | AJ100: 0 | AK100: 0 | AL100: 0 | AM100: 0 | AN100: 0 | AO100: 0 | AP100: 0 | DH100: =IF(B100<>"", B100, DH99) -> 1 New England
...

Sheet NEMS_commercial
B2: Billions of 2017$
B4: Capital Invest: total installed capital cost of major end-use equipment paid by consumer (excludes federal or utility incentives)
B5: Subsidy Invest: federal equipment subsidies (e.g., investment tax credits for solar water heaters and ground-source heat pumps)
B7: Sum of Amount | E7: Year
B8: Division | C8: EndUse | D8: Label | E8: 2013 | F8: 2014 | G8: 2015 | H8: 2016 | I8: 2017 | J8: 2018 | K8: 2019 | L8: 2020 | M8: 2021 | N8: 2022 | O8: 2023 | P8: 2024 | Q8: 2025 | R8: 2026 | S8: 2027 | T8: 2028 | U8: 2029 | V8: 2030 | W8: 2031 | X8: 2032 | Y8: 2033 | Z8: 2034 | AA8: 2035 | AB8: 2036 | AC8: 2037 | AD8: 2038 | AE8: 2039 | AF8: 2040 | AG8: 2041 | AH8: 2042 | AI8: 2043 | AJ8: 2044 | AK8: 2045 | AL8: 2046 | AM8: 2047 | AN8: 2048 | AO8: 2049 | AP8: 2050 | AQ8: division_filled
A9: =IFERROR(INDEX(NEMS_mapping!C$15:C$29,MATCH(C9,NEMS_mapping!B$15:B$29,0)),"") -> 0 | B9: 1 New England | C9: 1 Heating | D9: Capital Invest | E9: 0.344181 | F9: 0.331865 | G9: 0.28265 | H9: 0.274544 | I9: 0.274712 | J9: 0.237545 | K9: 0.240459 | L9: 0.225642 | M9: 0.229639 | N9: 0.23404 | O9: 0.230791 | P9: 0.22569 | Q9: 0.219426 | R9: 0.213868 | S9: 0.209877 | T9: 0.209018 | U9: 0.208821 | V9: 0.207567 | W9: 0.206389 | X9: 0.203335 | Y9: 0.22554 | Z9: 0.220431 | AA9: 0.21528 | AB9: 0.210423 | AC9: 0.205495 | AD9: 0.200619 | AE9: 0.196272 | AF9: 0.192011 | AG9: 0.188216 | AH9: 0.184726 | AI9: 0.181251 | AJ9: 0.177932 | AK9: 0.17494 | AL9: 0.171769 | AM9: 0.168794 | AN9: 0.166058 | AO9: 0.163078 | AP9: 0.160389 | AQ9: =B9 -> 1 New England
A10: =IFERROR(INDEX(NEMS_mapping!C$15:C$29,MATCH(C10,NEMS_mapping!B$15:B$29,0)),"") | D10: Tot Subsidy Inv | E10: 0.040291 | F10: 0.039495 | G10: 0.034441 | H10: 0.033283 | I10: 0.032725 | J10: 0.024715 | K10: 0.02419 | L10: 0.032051 | M10: 0.031314 | N10: 0.031243 | O10: 0.091871 | P10: 0.09045 | Q10: 0.089599 | R10: 0.089298 | S10: 0.089161 | T10: 0.089042 | U10: 0.090349 | V10: 0.090049 | W10: 0.090608 | X10: 0.090822 | Y10: 0.014215 | Z10: 0.013741 | AA10: 0.013309 | AB10: 0.012899 | AC10: 0.01223 | AD10: 0.011552 | AE10: 0.011192 | AF10: 0.010764 | AG10: 0.01043 | AH10: 0.010132 | AI10: 0.009695 | AJ10: 0.009396 | AK10: 0.009139 | AL10: 0.008885 | AM10: 0.008615 | AN10: 0.008389 | AO10: 0.00816 | AP10: 0.007948 | AQ10: =IF(B10<>"", B10, AQ9) -> 1 New England
A11: =IFERROR(INDEX(NEMS_mapping!C$15:C$29,MATCH(C11,NEMS_mapping!B$15:B$29,0)),"") -> heating | C11: 1 Heating Total | E11: 0.384472 | F11: 0.37136 | G11: 0.317091 | H11: 0.307827 | I11: 0.307437 | J11: 0.26226 | K11: 0.264649 | L11: 0.257693 | M11: 0.260953 | N11: 0.265283 | O11: 0.322662 | P11: 0.31614 | Q11: 0.309025 | R11: 0.303166 | S11: 0.299038 | T11: 0.29806 | U11: 0.29917 | V11: 0.297616 | W11: 0.296997 | X11: 0.294157 | Y11: 0.239755 | Z11: 0.234172 | AA11: 0.228589 | AB11: 0.223322 | AC11: 0.217725 | AD11: 0.212171 | AE11: 0.207464 | AF11: 0.202775 | AG11: 0.198646 | AH11: 0.194858 | AI11: 0.190946 | AJ11: 0.187328 | AK11: 0.184079 | AL11: 0.180654 | AM11: 0.177409 | AN11: 0.174447 | AO11: 0.171238 | AP11: 0.168337 | AQ11: =IF(B11<>"", B11, AQ10) -> 1 New England
A12: =IFERROR(INDEX(NEMS_mapping!C$15:C$29,MATCH(C12,NEMS_mapping!B$15:B$29,0)),"") -> 0 | C12: 2 Cooling | D12: Capital Invest | E12: 0.459549 | F12: 0.250312 | G12: 0.270012 | H12: 0.264214 | I12: 0.25006 | J12: 0.257265 | K12: 0.264678 | L12: 0.254914 | M12: 0.254714 | N12: 0.251159 | O12: 0.258645 | P12: 0.25721 | Q12: 0.260611 | R12: 0.256828 | S12: 0.25443 | T12: 0.256565 | U12: 0.259006 | V12: 0.261049 | W12: 0.262179 | X12: 0.261104 | Y12: 0.261881 | Z12: 0.259144 | AA12: 0.256238 | AB12: 0.253421 | AC12: 0.251026 | AD12: 0.248606 | AE12: 0.246351 | AF12: 0.244633 | AG12: 0.243069 | AH12: 0.241987 | AI12: 0.241094 | AJ12: 0.240521 | AK12: 0.240239 | AL12: 0.239928 | AM12: 0.239896 | AN12: 0.239742 | AO12: 0.239743 | AP12: 0.239565 | AQ12: =IF(B12<>"", B12, AQ11) -> 1 New England
A13: =IFERROR(INDEX(NEMS_mapping!C$15:C$29,MATCH(C13,NEMS_mapping!B$15:B$29,0)),"") | D13: Tot Subsidy Inv | E13: 0.009266 | F13: 0.008442 | G13: 0.010826 | H13: 0.010124 | I13: 0.0071 | J13: 0.010742 | K13: 0.007896 | L13: 0.008899 | M13: 0.008329 | N13: 0.008734 | O13: 0.013037 | P13: 0.01713 | Q13: 0.016044 | R13: 0.016028 | S13: 0.016286 | T13: 0.01692 | U13: 0.017724 | V13: 0.019027 | W13: 0.019597 | X13: 0.020102 | Y13: 0.009436 | Z13: 0.009466 | AA13: 0.009361 | AB13: 0.009372 | AC13: 0.00935 | AD13: 0.009369 | AE13: 0.009339 | AF13: 0.009747 | AG13: 0.009742 | AH13: 0.009782 | AI13: 0.009819 | AJ13: 0.009885 | AK13: 0.009957 | AL13: 0.010031 | AM13: 0.010137 | AN13: 0.010215 | AO13: 0.010317 | AP13: 0.010387 | AQ13: =IF(B13<>"", B13, AQ12) -> 1 New England
A14: =IFERROR(INDEX(NEMS_mapping!C$15:C$29,MATCH(C14,NEMS_mapping!B$15:B$29,0)),"") -> cooling and ventilation | C14: 2 Cooling Total | E14: 0.468815 | F14: 0.258754 | G14: 0.280838 | H14: 0.274338 | I14: 0.25716 | J14: 0.268007 | K14: 0.272574 | L14: 0.263813 | M14: 0.263043 | N14: 0.259893 | O14: 0.271682 | P14: 0.27434 | Q14: 0.276655 | R14: 0.272856 | S14: 0.270716 | T14: 0.273485 | U14: 0.27673 | V14: 0.280076 | W14: 0.281776 | X14: 0.281206 | Y14: 0.271317 | Z14: 0.26861 | AA14: 0.265599 | AB14: 0.262793 | AC14: 0.260376 | AD14: 0.257975 | AE14: 0.25569 | AF14: 0.25438 | AG14: 0.252811 | AH14: 0.251769 | AI14: 0.250913 | AJ14: 0.250406 | AK14: 0.250196 | AL14: 0.249959 | AM14: 0.250033 | AN14: 0.249957 | AO14: 0.25006 | AP14: 0.249952 | AQ14: =IF(B14<>"", B14, AQ13) -> 1 New England
A15: =IFERROR(INDEX(NEMS_mapping!C$15:C$29,MATCH(C15,NEMS_mapping!B$15:B$29,0)),"") -> 0 | C15: 3 Water Heating | D15: Capital Invest | E15: 0.01449 | F15: 0.014314 | G15: 0.014585 | H15: 0.014826 | I15: 0.014597 | J15: 0.014882 | K15: 0.015203 | L15: 0.015069 | M15: 0.01514 | N15: 0.015929 | O15: 0.015414 | P15: 0.015225 | Q15: 0.015488 | R15: 0.015373 | S15: 0.016097 | T15: 0.016293 | U15: 0.016504 | V15: 0.016685 | W15: 0.016838 | X15: 0.016887 | Y15: 0.016861 | Z15: 0.016946 | AA15: 0.016841 | AB15: 0.016821 | AC15: 0.016794 | AD15: 0.016726 | AE15: 0.016657 | AF15: 0.016594 | AG15: 0.016554 | AH15: 0.016525 | AI15: 0.016506 | AJ15: 0.016498 | AK15: 0.016496 | AL15: 0.016498 | AM15: 0.016503 | AN15: 0.016508 | AO15: 0.016473 | AP15: 0.016476 | AQ15: =IF(B15<>"", B15, AQ14) -> 1 New England
A16: =IFERROR(INDEX(NEMS_mapping!C$15:C$29,MATCH(C16,NEMS_mapping!B$15:B$29,0)),"") | D16: Tot Subsidy Inv | E16: 0.003698 | F16: 0.003616 | G16: 0.003664 | H16: 0.003758 | I16: 0.003847 | J16: 0.004531 | K16: 0.004642 | L16: 0.003924 | M16: 0.003966 | N16: 0.00484 | O16: 0.007164 | P16: 0.006217 | Q16: 0.006309 | R16: 0.00616 | S16: 0.003603 | T16: 0.003664 | U16: 0.003728 | V16: 0.003785 | W16: 0.003834 | X16: 0.003859 | Y16: 0.003866 | Z16: 0.00395 | AA16: 0.003928 | AB16: 0.003945 | AC16: 0.003969 | AD16: 0.003965 | AE16: 0.003959 | AF16: 0.003955 | AG16: 0.003954 | AH16: 0.003958 | AI16: 0.003962 | AJ16: 0.003968 | AK16: 0.003976 | AL16: 0.003984 | AM16: 0.003992 | AN16: 0.003999 | AO16: 0.003979 | AP16: 0.003984 | AQ16: =IF(B16<>"", B16, AQ15) -> 1 New England
A17: =IFERROR(INDEX(NEMS_mapping!C$15:C$29,MATCH(C17,NEMS_mapping!B$15:B$29,0)),"") -> appliances | C17: 3 Water Heating Total | E17: 0.018188 | F17: 0.01793 | G17: 0.018249 | H17: 0.018584 | I17: 0.018444 | J17: 0.019413 | K17: 0.019845 | L17: 0.018993 | M17: 0.019106 | N17: 0.020769 | O17: 0.022578 | P17: 0.021442 | Q17: 0.021797 | R17: 0.021533 | S17: 0.0197 | T17: 0.019957 | U17: 0.020232 | V17: 0.02047 | W17: 0.020672 | X17: 0.020746 | Y17: 0.020727 | Z17: 0.020896 | AA17: 0.020769 | AB17: 0.020766 | AC17: 0.020763 | AD17: 0.020691 | AE17: 0.020616 | AF17: 0.020549 | AG17: 0.020508 | AH17: 0.020483 | AI17: 0.020468 | AJ17: 0.020466 | AK17: 0.020472 | AL17: 0.020482 | AM17: 0.020495 | AN17: 0.020507 | AO17: 0.020452 | AP17: 0.02046 | AQ17: =IF(B17<>"", B17, AQ16) -> 1 New England
A18: =IFERROR(INDEX(NEMS_mapping!C$15:C$29,MATCH(C18,NEMS_mapping!B$15:B$29,0)),"") -> 0 | C18: 4 Ventilation | D18: Capital Invest | E18: 0.241285 | F18: 0.235502 | G18: 0.228035 | H18: 0.223234 | I18: 0.21545 | J18: 0.210189 | K18: 0.206863 | L18: 0.201924 | M18: 0.200704 | N18: 0.193861 | O18: 0.19003 | P18: 0.188356 | Q18: 0.186841 | R18: 0.180743 | S18: 0.175589 | T18: 0.173059 | U18: 0.170695 | V18: 0.166102 | W18: 0.163166 | X18: 0.159169 | Y18: 0.154574 | Z18: 0.150118 | AA18: 0.145748 | AB18: 0.141586 | AC18: 0.137727 | AD18: 0.134021 | AE18: 0.130497 | AF18: 0.12721 | AG18: 0.124219 | AH18: 0.121452 | AI18: 0.118902 | AJ18: 0.116523 | AK18: 0.114286 | AL18: 0.112164 | AM18: 0.110128 | AN18: 0.108161 | AO18: 0.106248 | AP18: 0.104376 | AQ18: =IF(B18<>"", B18, AQ17) -> 1 New England
A19: =IFERROR(INDEX(NEMS_mapping!C$15:C$29,MATCH(C19,NEMS_mapping!B$15:B$29,0)),"") | D19: Tot Subsidy Inv | E19: 0 | F19: 0 | G19: 0 | H19: 0 | I19: 0 | J19: 0 | K19: 0 | L19: 0 | M19: 0 | N19: 2e-05 | O19: 2e-05 | P19: 2e-05 | Q19: 7e-06 | R19: 7e-06 | S19: 7e-06 | T19: 6e-06 | U19: 6e-06 | V19: 0.013241 | W19: 0.013024 | X19: 0.012719 | Y19: 0.012366 | Z19: 0.012024 | AA19: 0.011689 | AB19: 0.011371 | AC19: 0.011078 | AD19: 0.010797 | AE19: 0.010532 | AF19: 0.010286 | AG19: 0.010064 | AH19: 0.00986 | AI19: 0.009675 | AJ19: 0.009504 | AK19: 0.009345 | AL19: 0.009196 | AM19: 0.009054 | AN19: 0.008917 | AO19: 0.008786 | AP19: 0.008658 | AQ19: =IF(B19<>"", B19, AQ18) -> 1 New England
A20: =IFERROR(INDEX(NEMS_mapping!C$15:C$29,MATCH(C20,NEMS_mapping!B$15:B$29,0)),"") -> appliances | C20: 4 Ventilation Total | E20: 0.241285 | F20: 0.235502 | G20: 0.228035 | H20: 0.223234 | I20: 0.21545 | J20: 0.210189 | K20: 0.206863 | L20: 0.201924 | M20: 0.200704 | N20: 0.193881 | O20: 0.19005 | P20: 0.188376 | Q20: 0.186848 | R20: 0.18075 | S20: 0.175596 | T20: 0.173065 | U20: 0.170701 | V20: 0.179343 | W20: 0.17619 | X20: 0.171888 | Y20: 0.16694 | Z20: 0.162142 | AA20: 0.157437 | AB20: 0.152957 | AC20: 0.148805 | AD20: 0.144818 | AE20: 0.141029 | AF20: 0.137496 | AG20: 0.134283 | AH20: 0.131312 | AI20: 0.128577 | AJ20: 0.126027 | AK20: 0.123631 | AL20: 0.12136 | AM20: 0.119182 | AN20: 0.117078 | AO20: 0.115034 | AP20: 0.113034 | AQ20: =IF(B20<>"", B20, AQ19) -> 1 New England
A21: =IFERROR(INDEX(NEMS_mapping!C$15:C$29,MATCH(C21,NEMS_mapping!B$15:B$29,0)),"") -> 0 | C21: 5 Cooking | D21: Capital Invest | E21: 0.046835 | F21: 0.046846 | G21: 0.046573 | H21: 0.046745 | I21: 0.046025 | J21: 0.045877 | K21: 0.046728 | L21: 0.045887 | M21: 0.045674 | N21: 0.045422 | O21: 0.046172 | P21: 0.046801 | Q21: 0.047522 | R21: 0.047134 | S21: 0.046903 | T21: 0.047272 | U21: 0.047687 | V21: 0.048014 | W21: 0.048263 | X21: 0.048203 | Y21: 0.047926 | Z21: 0.047626 | AA21: 0.047276 | AB21: 0.046929 | AC21: 0.046607 | AD21: 0.046276 | AE21: 0.045947 | AF21: 0.045642 | AG21: 0.045402 | AH21: 0.045198 | AI21: 0.04503 | AJ21: 0.044891 | AK21: 0.044773 | AL21: 0.04467 | AM21: 0.044573 | AN21: 0.044477 | AO21: 0.044373 | AP21: 0.044266 | AQ21: =IF(B21<>"", B21, AQ20) -> 1 New England
A22: =IFERROR(INDEX(NEMS_mapping!C$15:C$29,MATCH(C22,NEMS_mapping!B$15:B$29,0)),"") | D22: Tot Subsidy Inv | E22: 0 | F22: 0 | G22: 0 | H22: 0 | I22: 0 | J22: 0 | K22: 0 | L22: 0 | M22: 0 | N22: 0 | O22: 0 | P22: 0 | Q22: 0 | R22: 0 | S22: 0 | T22: 0 | U22: 0 | V22: 0 | W22: 0 | X22: 0 | Y22: 0 | Z22: 0 | AA22: 0 | AB22: 0 | AC22: 0 | AD22: 0 | AE22: 0 | AF22: 0 | AG22: 0 | AH22: 0 | AI22: 0 | AJ22: 0 | AK22: 0 | AL22: 0 | AM22: 0 | AN22: 0 | AO22: 0 | AP22: 0 | AQ22: =IF(B22<>"", B22, AQ21) -> 1 New England
A23: =IFERROR(INDEX(NEMS_mapping!C$15:C$29,MATCH(C23,NEMS_mapping!B$15:B$29,0)),"") -> appliances | C23: 5 Cooking Total | E23: 0.046835 | F23: 0.046846 | G23: 0.046573 | H23: 0.046745 | I23: 0.046025 | J23: 0.045877 | K23: 0.046728 | L23: 0.045887 | M23: 0.045674 | N23: 0.045422 | O23: 0.046172 | P23: 0.046801 | Q23: 0.047522 | R23: 0.047134 | S23: 0.046903 | T23: 0.047272 | U23: 0.047687 | V23: 0.048014 | W23: 0.048263 | X23: 0.048203 | Y23: 0.047926 | Z23: 0.047626 | AA23: 0.047276 | AB23: 0.046929 | AC23: 0.046607 | AD23: 0.046276 | AE23: 0.045947 | AF23: 0.045642 | AG23: 0.045402 | AH23: 0.045198 | AI23: 0.04503 | AJ23: 0.044891 | AK23: 0.044773 | AL23: 0.04467 | AM23: 0.044573 | AN23: 0.044477 | AO23: 0.044373 | AP23: 0.044266 | AQ23: =IF(B23<>"", B23, AQ22) -> 1 New England
A24: =IFERROR(INDEX(NEMS_mapping!C$15:C$29,MATCH(C24,NEMS_mapping!B$15:B$29,0)),"") -> 0 | C24: 6 Lighting | D24: Capital Invest | E24: 0.062374 | F24: 0.055478 | G24: 0.052881 | H24: 0.046429 | I24: 0.040458 | J24: 0.035856 | K24: 0.032791 | L24: 0.029545 | M24: 0.026433 | N24: 0.03935 | O24: 0.039534 | P24: 0.039622 | Q24: 0.040465 | R24: 0.040502 | S24: 0.040325 | T24: 0.040628 | U24: 0.040964 | V24: 0.043937 | W24: 0.044661 | X24: 0.044434 | Y24: 0.044584 | Z24: 0.044584 | AA24: 0.043936 | AB24: 0.04371 | AC24: 0.043061 | AD24: 0.042666 | AE24: 0.042143 | AF24: 0.043939 | AG24: 0.044146 | AH24: 0.043928 | AI24: 0.043972 | AJ24: 0.044028 | AK24: 0.044114 | AL24: 0.044227 | AM24: 0.044338 | AN24: 0.044458 | AO24: 0.044557 | AP24: 0.044669 | AQ24: =IF(B24<>"", B24, AQ23) -> 1 New England
A25: =IFERROR(INDEX(NEMS_mapping!C$15:C$29,MATCH(C25,NEMS_mapping!B$15:B$29,0)),"") | D25: Tot Subsidy Inv | E25: 0.002874 | F25: 0.002743 | G25: 0.00926 | H25: 0.014804 | I25: 0.015047 | J25: 0.014989 | K25: 0.015282 | L25: 0.015039 | M25: 0.015105 | N25: 0.001547 | O25: 0.001501 | P25: 0.000795 | Q25: 0.000446 | R25: 9.4e-05 | S25: 7e-05 | T25: 4.7e-05 | U25: 2.3e-05 | V25: 0 | W25: 0 | X25: 0 | Y25: 0 | Z25: 0 | AA25: 0 | AB25: 0 | AC25: 0 | AD25: 0 | AE25: 0 | AF25: 0 | AG25: 0 | AH25: 0 | AI25: 0 | AJ25: 0 | AK25: 0 | AL25: 0 | AM25: 0 | AN25: 0 | AO25: 0 | AP25: 0 | AQ25: =IF(B25<>"", B25, AQ24) -> 1 New England
A26: =IFERROR(INDEX(NEMS_mapping!C$15:C$29,MATCH(C26,NEMS_mapping!B$15:B$29,0)),"") -> lighting | C26: 6 Lighting Total | E26: 0.065248 | F26: 0.058221 | G26: 0.062141 | H26: 0.061233 | I26: 0.055505 | J26: 0.050845 | K26: 0.048073 | L26: 0.044584 | M26: 0.041538 | N26: 0.040897 | O26: 0.041035 | P26: 0.040417 | Q26: 0.040911 | R26: 0.040596 | S26: 0.040395 | T26: 0.040675 | U26: 0.040987 | V26: 0.043937 | W26: 0.044661 | X26: 0.044434 | Y26: 0.044584 | Z26: 0.044584 | AA26: 0.043936 | AB26: 0.04371 | AC26: 0.043061 | AD26: 0.042666 | AE26: 0.042143 | AF26: 0.043939 | AG26: 0.044146 | AH26: 0.043928 | AI26: 0.043972 | AJ26: 0.044028 | AK26: 0.044114 | AL26: 0.044227 | AM26: 0.044338 | AN26: 0.044458 | AO26: 0.044557 | AP26: 0.044669 | AQ26: =IF(B26<>"", B26, AQ25) -> 1 New England
A27: =IFERROR(INDEX(NEMS_mapping!C$15:C$29,MATCH(C27,NEMS_mapping!B$15:B$29,0)),"") -> 0 | C27: 7 Refrigeration | D27: Capital Invest | E27: 2.560282 | F27: 2.570202 | G27: 2.557242 | H27: 2.570658 | I27: 2.538752 | J27: 2.573282 | K27: 2.616058 | L27: 2.586092 | M27: 2.573054 | N27: 2.470843 | O27: 2.518917 | P27: 2.562241 | Q27: 2.605556 | R27: 2.593944 | S27: 2.589575 | T27: 2.6152 | U27: 2.643184 | V27: 2.667063 | W27: 2.688585 | X27: 2.694498 | Y27: 2.689013 | Z27: 2.681486 | AA27: 2.671247 | AB27: 2.660178 | AC27: 2.650079 | AD27: 2.639028 | AE27: 2.627667 | AF27: 2.61717 | AG27: 2.610785 | AH27: 2.605925 | AI27: 2.602905 | AJ27: 2.601226 | AK27: 2.600616 | AL27: 2.60078 | AM27: 2.60129 | AN27: 2.601868 | AO27: 2.602266 | AP27: 2.602194 | AQ27: =IF(B27<>"", B27, AQ26) -> 1 New England
A28: =IFERROR(INDEX(NEMS_mapping!C$15:C$29,MATCH(C28,NEMS_mapping!B$15:B$29,0)),"") | D28: Tot Subsidy Inv | E28: 0 | F28: 0 | G28: 0 | H28: 0 | I28: 0 | J28: 0 | K28: 0 | L28: 0 | M28: 0 | N28: 0 | O28: 0 | P28: 0 | Q28: 0 | R28: 0 | S28: 0 | T28: 0 | U28: 0 | V28: 0 | W28: 0 | X28: 0 | Y28: 0 | Z28: 0 | AA28: 0 | AB28: 0 | AC28: 0 | AD28: 0 | AE28: 0 | AF28: 0 | AG28: 0 | AH28: 0 | AI28: 0 | AJ28: 0 | AK28: 0 | AL28: 0 | AM28: 0 | AN28: 0 | AO28: 0 | AP28: 0 | AQ28: =IF(B28<>"", B28, AQ27) -> 1 New England
A29: =IFERROR(INDEX(NEMS_mapping!C$15:C$29,MATCH(C29,NEMS_mapping!B$15:B$29,0)),"") -> appliances | C29: 7 Refrigeration Total | E29: 2.560282 | F29: 2.570202 | G29: 2.557242 | H29: 2.570658 | I29: 2.538752 | J29: 2.573282 | K29: 2.616058 | L29: 2.586092 | M29: 2.573054 | N29: 2.470843 | O29: 2.518917 | P29: 2.562241 | Q29: 2.605556 | R29: 2.593944 | S29: 2.589575 | T29: 2.6152 | U29: 2.643184 | V29: 2.667063 | W29: 2.688585 | X29: 2.694498 | Y29: 2.689013 | Z29: 2.681486 | AA29: 2.671247 | AB29: 2.660178 | AC29: 2.650079 | AD29: 2.639028 | AE29: 2.627667 | AF29: 2.61717 | AG29: 2.610785 | AH29: 2.605925 | AI29: 2.602905 | AJ29: 2.601226 | AK29: 2.600616 | AL29: 2.60078 | AM29: 2.60129 | AN29: 2.601868 | AO29: 2.602266 | AP29: 2.602194 | AQ29: =IF(B29<>"", B29, AQ28) -> 1 New England
A30: =IFERROR(INDEX(NEMS_mapping!C$15:C$29,MATCH(C30,NEMS_mapping!B$15:B$29,0)),"") | B30: 1 New England Total | E30: 3.785125 | F30: 3.558815 | G30: 3.510169 | H30: 3.502619 | I30: 3.438773 | J30: 3.429873 | K30: 3.47479 | L30: 3.418986 | M30: 3.404072 | N30: 3.296988 | O30: 3.413096 | P30: 3.449757 | Q30: 3.488314 | R30: 3.459979 | S30: 3.441923 | T30: 3.467714 | U30: 3.498691 | V30: 3.536519 | W30: 3.557144 | X30: 3.555132 | Y30: 3.480262 | Z30: 3.459516 | AA30: 3.434853 | AB30: 3.410655 | AC30: 3.387416 | AD30: 3.363625 | AE30: 3.340556 | AF30: 3.321951 | AG30: 3.306581 | AH30: 3.293473 | AI30: 3.282811 | AJ30: 3.274372 | AK30: 3.267881 | AL30: 3.262132 | AM30: 3.25732 | AN30: 3.252792 | AO30: 3.24798 | AP30: 3.242912 | AQ30: =IF(B30<>"", B30, AQ29) -> 1 New England Total
A31: =IFERROR(INDEX(NEMS_mapping!C$15:C$29,MATCH(C31,NEMS_mapping!B$15:B$29,0)),"") -> 0 | B31: 2 Middle Atlantic | C31: 1 Heating | D31: Capital Invest | E31: 1.300188 | F31: 1.265178 | G31: 1.239941 | H31: 1.199411 | I31: 1.213989 | J31: 1.049931 | K31: 1.041244 | L31: 1.019009 | M31: 0.998915 | N31: 0.991274 | O31: 1.000369 | P31: 0.982289 | Q31: 0.977043 | R31: 0.951057 | S31: 0.930728 | T31: 0.924898 | U31: 0.919659 | V31: 0.912733 | W31: 0.903926 | X31: 0.889235 | Y31: 0.886864 | Z31: 0.867554 | AA31: 0.848567 | AB31: 0.830266 | AC31: 0.812651 | AD31: 0.796018 | AE31: 0.780413 | AF31: 0.766107 | AG31: 0.752429 | AH31: 0.738775 | AI31: 0.725869 | AJ31: 0.713775 | AK31: 0.702692 | AL31: 0.691921 | AM31: 0.68015 | AN31: 0.669644 | AO31: 0.659283 | AP31: 0.648701 | AQ31: =IF(B31<>"", B31, AQ30) -> 2 Middle Atlantic
A32: =IFERROR(INDEX(NEMS_mapping!C$15:C$29,MATCH(C32,NEMS_mapping!B$15:B$29,0)),"") | D32: Tot Subsidy Inv | E32: 0.073642 | F32: 0.069443 | G32: 0.065535 | H32: 0.062001 | I32: 0.064598 | J32: 0.038081 | K32: 0.038253 | L32: 0.051575 | M32: 0.05097 | N32: 0.051794 | O32: 0.059657 | P32: 0.057403 | Q32: 0.053596 | R32: 0.050809 | S32: 0.049115 | T32: 0.048543 | U32: 0.047979 | V32: 0.047222 | W32: 0.046624 | X32: 0.045853 | Y32: 0.01535 | Z32: 0.014843 | AA32: 0.014502 | AB32: 0.014171 | AC32: 0.013817 | AD32: 0.013513 | AE32: 0.013248 | AF32: 0.012968 | AG32: 0.012811 | AH32: 0.01243 | AI32: 0.01201 | AJ32: 0.011702 | AK32: 0.011488 | AL32: 0.011267 | AM32: 0.010538 | AN32: 0.010284 | AO32: 0.01009 | AP32: 0.009885 | AQ32: =IF(B32<>"", B32, AQ31) -> 2 Middle Atlantic
A33: =IFERROR(INDEX(NEMS_mapping!C$15:C$29,MATCH(C33,NEMS_mapping!B$15:B$29,0)),"") -> heating | C33: 1 Heating Total | E33: 1.37383 | F33: 1.334621 | G33: 1.305476 | H33: 1.261412 | I33: 1.278587 | J33: 1.088012 | K33: 1.079497 | L33: 1.070584 | M33: 1.049885 | N33: 1.043068 | O33: 1.060026 | P33: 1.039692 | Q33: 1.030639 | R33: 1.001866 | S33: 0.979843 | T33: 0.973441 | U33: 0.967638 | V33: 0.959955 | W33: 0.95055 | X33: 0.935088 | Y33: 0.902214 | Z33: 0.882397 | AA33: 0.863069 | AB33: 0.844437 | AC33: 0.826468 | AD33: 0.809531 | AE33: 0.793661 | AF33: 0.779075 | AG33: 0.76524 | AH33: 0.751205 | AI33: 0.737879 | AJ33: 0.725477 | AK33: 0.71418 | AL33: 0.703188 | AM33: 0.690688 | AN33: 0.679928 | AO33: 0.669373 | AP33: 0.658586 | AQ33: =IF(B33<>"", B33, AQ32) -> 2 Middle Atlantic
A34: =IFERROR(INDEX(NEMS_mapping!C$15:C$29,MATCH(C34,NEMS_mapping!B$15:B$29,0)),"") -> 0 | C34: 2 Cooling | D34: Capital Invest | E34: 1.847958 | F34: 0.995834 | G34: 1.108218 | H34: 1.04177 | I34: 1.024655 | J34: 1.109292 | K34: 1.075084 | L34: 1.096808 | M34: 1.052453 | N34: 1.043475 | O34: 1.08129 | P34: 1.091433 | Q34: 1.100519 | R34: 1.086463 | S34: 1.078429 | T34: 1.088811 | U34: 1.100772 | V34: 1.110891 | W34: 1.117475 | X34: 1.115065 | Y34: 1.108573 | Z34: 1.099911 | AA34: 1.091116 | AB34: 1.081854 | AC34: 1.075058 | AD34: 1.068872 | AE34: 1.063183 | AF34: 1.059687 | AG34: 1.057319 | AH34: 1.057122 | AI34: 1.058382 | AJ34: 1.060739 | AK34: 1.064499 | AL34: 1.068855 | AM34: 1.074054 | AN34: 1.080072 | AO34: 1.085939 | AP34: 1.092529 | AQ34: =IF(B34<>"", B34, AQ33) -> 2 Middle Atlantic
A35: =IFERROR(INDEX(NEMS_mapping!C$15:C$29,MATCH(C35,NEMS_mapping!B$15:B$29,0)),"") | D35: Tot Subsidy Inv | E35: 0.052614 | F35: 0.051096 | G35: 0.055292 | H35: 0.050986 | I35: 0.048967 | J35: 0.054951 | K35: 0.052717 | L35: 0.054764 | M35: 0.053757 | N35: 0.052533 | O35: 0.015458 | P35: 0.019019 | Q35: 0.01765 | R35: 0.017155 | S35: 0.017563 | T35: 0.018379 | U35: 0.019173 | V35: 0.021565 | W35: 0.022143 | X35: 0.022449 | Y35: 0.019067 | Z35: 0.019084 | AA35: 0.019674 | AB35: 0.019032 | AC35: 0.019064 | AD35: 0.019551 | AE35: 0.019842 | AF35: 0.020542 | AG35: 0.020645 | AH35: 0.021163 | AI35: 0.02142 | AJ35: 0.021706 | AK35: 0.021719 | AL35: 0.02161 | AM35: 0.02197 | AN35: 0.022366 | AO35: 0.022742 | AP35: 0.023028 | AQ35: =IF(B35<>"", B35, AQ34) -> 2 Middle Atlantic
A36: =IFERROR(INDEX(NEMS_mapping!C$15:C$29,MATCH(C36,NEMS_mapping!B$15:B$29,0)),"") -> cooling and ventilation | C36: 2 Cooling Total | E36: 1.900572 | F36: 1.04693 | G36: 1.16351 | H36: 1.092756 | I36: 1.073622 | J36: 1.164243 | K36: 1.127801 | L36: 1.151572 | M36: 1.10621 | N36: 1.096008 | O36: 1.096748 | P36: 1.110452 | Q36: 1.118169 | R36: 1.103618 | S36: 1.095992 | T36: 1.10719 | U36: 1.119945 | V36: 1.132456 | W36: 1.139618 | X36: 1.137514 | Y36: 1.12764 | Z36: 1.118995 | AA36: 1.11079 | AB36: 1.100886 | AC36: 1.094122 | AD36: 1.088423 | AE36: 1.083025 | AF36: 1.080229 | AG36: 1.077964 | AH36: 1.078285 | AI36: 1.079802 | AJ36: 1.082445 | AK36: 1.086218 | AL36: 1.090465 | AM36: 1.096024 | AN36: 1.102438 | AO36: 1.108681 | AP36: 1.115557 | AQ36: =IF(B36<>"", B36, AQ35) -> 2 Middle Atlantic
A37: =IFERROR(INDEX(NEMS_mapping!C$15:C$29,MATCH(C37,NEMS_mapping!B$15:B$29,0)),"") -> 0 | C37: 3 Water Heating | D37: Capital Invest | E37: 0.126317 | F37: 0.128146 | G37: 0.132459 | H37: 0.134999 | I37: 0.138152 | J37: 0.139722 | K37: 0.141218 | L37: 0.142826 | M37: 0.143058 | N37: 0.142514 | O37: 0.146677 | P37: 0.150863 | Q37: 0.154613 | R37: 0.155013 | S37: 0.156918 | T37: 0.159488 | U37: 0.162178 | V37: 0.164573 | W37: 0.166689 | X37: 0.167808 | Y37: 0.168148 | Z37: 0.16833 | AA37: 0.168315 | AB37: 0.168223 | AC37: 0.168172 | AD37: 0.16823 | AE37: 0.168057 | AF37: 0.167922 | AG37: 0.167975 | AH37: 0.1682 | AI37: 0.168441 | AJ37: 0.168754 | AK37: 0.169125 | AL37: 0.169532 | AM37: 0.169954 | AN37: 0.170372 | AO37: 0.170693 | AP37: 0.171051 | AQ37: =IF(B37<>"", B37, AQ36) -> 2 Middle Atlantic
A38: =IFERROR(INDEX(NEMS_mapping!C$15:C$29,MATCH(C38,NEMS_mapping!B$15:B$29,0)),"") | D38: Tot Subsidy Inv | E38: 0.014485 | F38: 0.014883 | G38: 0.015117 | H38: 0.01534 | I38: 0.016093 | J38: 0.016343 | K38: 0.016594 | L38: 0.016414 | M38: 0.016454 | N38: 0.01674 | O38: 0.020698 | P38: 0.020924 | Q38: 0.021295 | R38: 0.021261 | S38: 0.016773 | T38: 0.017065 | U38: 0.01737 | V38: 0.017642 | W38: 0.017882 | X38: 0.018023 | Y38: 0.018068 | Z38: 0.018097 | AA38: 0.018102 | AB38: 0.018099 | AC38: 0.0181 | AD38: 0.018242 | AE38: 0.01823 | AF38: 0.018221 | AG38: 0.018233 | AH38: 0.018297 | AI38: 0.01833 | AJ38: 0.01837 | AK38: 0.018417 | AL38: 0.018465 | AM38: 0.018515 | AN38: 0.018563 | AO38: 0.018571 | AP38: 0.01861 | AQ38: =IF(B38<>"", B38, AQ37) -> 2 Middle Atlantic
A39: =IFERROR(INDEX(NEMS_mapping!C$15:C$29,MATCH(C39,NEMS_mapping!B$15:B$29,0)),"") -> appliances | C39: 3 Water Heating Total | E39: 0.140802 | F39: 0.143029 | G39: 0.147576 | H39: 0.150339 | I39: 0.154245 | J39: 0.156065 | K39: 0.157812 | L39: 0.15924 | M39: 0.159512 | N39: 0.159254 | O39: 0.167375 | P39: 0.171787 | Q39: 0.175908 | R39: 0.176274 | S39: 0.173691 | T39: 0.176553 | U39: 0.179548 | V39: 0.182215 | W39: 0.184571 | X39: 0.185831 | Y39: 0.186216 | Z39: 0.186427 | AA39: 0.186417 | AB39: 0.186322 | AC39: 0.186272 | AD39: 0.186472 | AE39: 0.186287 | AF39: 0.186143 | AG39: 0.186208 | AH39: 0.186497 | AI39: 0.186771 | AJ39: 0.187124 | AK39: 0.187542 | AL39: 0.187997 | AM39: 0.188469 | AN39: 0.188935 | AO39: 0.189264 | AP39: 0.189661 | AQ39: =IF(B39<>"", B39, AQ38) -> 2 Middle Atlantic
A40: =IFERROR(INDEX(NEMS_mapping!C$15:C$29,MATCH(C40,NEMS_mapping!B$15:B$29,0)),"") -> 0 | C40: 4 Ventilation | D40: Capital Invest | E40: 1.516564 | F40: 1.476081 | G40: 1.463484 | H40: 1.408254 | I40: 1.393922 | J40: 1.383118 | K40: 1.361188 | L40: 1.327955 | M40: 1.297655 | N40: 1.251207 | O40: 1.278188 | P40: 1.263533 | Q40: 1.261601 | R40: 1.224 | S40: 1.193117 | T40: 1.181656 | U40: 1.17134 | V40: 1.141194 | W40: 1.125808 | X40: 1.102259 | Y40: 1.073982 | Z40: 1.046577 | AA40: 1.01965 | AB40: 0.994147 | AC40: 0.97083 | AD40: 0.948544 | AE40: 0.927537 | AF40: 0.908249 | AG40: 0.890972 | AH40: 0.875401 | AI40: 0.861406 | AJ40: 0.848676 | AK40: 0.837004 | AL40: 0.82614 | AM40: 0.815939 | AN40: 0.806218 | AO40: 0.796863 | AP40: 0.787764 | AQ40: =IF(B40<>"", B40, AQ39) -> 2 Middle Atlantic
A41: =IFERROR(INDEX(NEMS_mapping!C$15:C$29,MATCH(C41,NEMS_mapping!B$15:B$29,0)),"") | D41: Tot Subsidy Inv | E41: 0 | F41: 0 | G41: 0 | H41: 0 | I41: 0 | J41: 0 | K41: 0 | L41: 0 | M41: 0 | N41: 2e-05 | O41: 1.8e-05 | P41: 2e-05 | Q41: 6e-06 | R41: 4e-06 | S41: 4e-06 | T41: 4e-06 | U41: 4e-06 | V41: 0.120271 | W41: 0.118778 | X41: 0.1164 | Y41: 0.113509 | Z41: 0.110709 | AA41: 0.107958 | AB41: 0.10536 | AC41: 0.102997 | AD41: 0.100746 | AE41: 0.098631 | AF41: 0.096705 | AG41: 0.094988 | AH41: 0.093453 | AI41: 0.092093 | AJ41: 0.090872 | AK41: 0.089765 | AL41: 0.08875 | AM41: 0.087803 | AN41: 0.086909 | AO41: 0.086052 | AP41: 0.085224 | AQ41: =IF(B41<>"", B41, AQ40) -> 2 Middle Atlantic
A42: =IFERROR(INDEX(NEMS_mapping!C$15:C$29,MATCH(C42,NEMS_mapping!B$15:B$29,0)),"") -> appliances | C42: 4 Ventilation Total | E42: 1.516564 | F42: 1.476081 | G42: 1.463484 | H42: 1.408254 | I42: 1.393922 | J42: 1.383118 | K42: 1.361188 | L42: 1.327955 | M42: 1.297655 | N42: 1.251227 | O42: 1.278206 | P42: 1.263553 | Q42: 1.261607 | R42: 1.224004 | S42: 1.193121 | T42: 1.18166 | U42: 1.171344 | V42: 1.261465 | W42: 1.244586 | X42: 1.218659 | Y42: 1.187491 | Z42: 1.157286 | AA42: 1.127608 | AB42: 1.099507 | AC42: 1.073827 | AD42: 1.04929 | AE42: 1.026168 | AF42: 1.004954 | AG42: 0.98596 | AH42: 0.968854 | AI42: 0.953499 | AJ42: 0.939548 | AK42: 0.926769 | AL42: 0.91489 | AM42: 0.903742 | AN42: 0.893127 | AO42: 0.882915 | AP42: 0.872988 | AQ42: =IF(B42<>"", B42, AQ41) -> 2 Middle Atlantic
A43: =IFERROR(INDEX(NEMS_mapping!C$15:C$29,MATCH(C43,NEMS_mapping!B$15:B$29,0)),"") -> 0 | C43: 5 Cooking | D43: Capital Invest | E43: 0.182338 | F43: 0.181136 | G43: 0.183196 | H43: 0.182071 | I43: 0.18392 | J43: 0.184374 | K43: 0.183902 | L43: 0.183806 | M43: 0.181857 | N43: 0.179343 | O43: 0.184984 | P43: 0.188665 | Q43: 0.192041 | R43: 0.19087 | S43: 0.190329 | T43: 0.192269 | U43: 0.194413 | V43: 0.196206 | W43: 0.197661 | X43: 0.197833 | Y43: 0.19709 | Z43: 0.196254 | AA43: 0.195209 | AB43: 0.194142 | AC43: 0.193194 | AD43: 0.192202 | AE43: 0.191218 | AF43: 0.190333 | AG43: 0.189707 | AH43: 0.189226 | AI43: 0.188903 | AJ43: 0.188697 | AK43: 0.188579 | AL43: 0.188525 | AM43: 0.188498 | AN43: 0.188476 | AO43: 0.188436 | AP43: 0.188357 | AQ43: =IF(B43<>"", B43, AQ42) -> 2 Middle Atlantic
A44: =IFERROR(INDEX(NEMS_mapping!C$15:C$29,MATCH(C44,NEMS_mapping!B$15:B$29,0)),"") | D44: Tot Subsidy Inv | E44: 0 | F44: 0 | G44: 0 | H44: 0 | I44: 0 | J44: 0 | K44: 0 | L44: 0 | M44: 0 | N44: 0 | O44: 0 | P44: 0 | Q44: 0 | R44: 0 | S44: 0 | T44: 0 | U44: 0 | V44: 0 | W44: 0 | X44: 0 | Y44: 0 | Z44: 0 | AA44: 0 | AB44: 0 | AC44: 0 | AD44: 0 | AE44: 0 | AF44: 0 | AG44: 0 | AH44: 0 | AI44: 0 | AJ44: 0 | AK44: 0 | AL44: 0 | AM44: 0 | AN44: 0 | AO44: 0 | AP44: 0 | AQ44: =IF(B44<>"", B44, AQ43) -> 2 Middle Atlantic
A45: =IFERROR(INDEX(NEMS_mapping!C$15:C$29,MATCH(C45,NEMS_mapping!B$15:B$29,0)),"") -> appliances | C45: 5 Cooking Total | E45: 0.182338 | F45: 0.181136 | G45: 0.183196 | H45: 0.182071 | I45: 0.18392 | J45: 0.184374 | K45: 0.183902 | L45: 0.183806 | M45: 0.181857 | N45: 0.179343 | O45: 0.184984 | P45: 0.188665 | Q45: 0.192041 | R45: 0.19087 | S45: 0.190329 | T45: 0.192269 | U45: 0.194413 | V45: 0.196206 | W45: 0.197661 | X45: 0.197833 | Y45: 0.19709 | Z45: 0.196254 | AA45: 0.195209 | AB45: 0.194142 | AC45: 0.193194 | AD45: 0.192202 | AE45: 0.191218 | AF45: 0.190333 | AG45: 0.189707 | AH45: 0.189226 | AI45: 0.188903 | AJ45: 0.188697 | AK45: 0.188579 | AL45: 0.188525 | AM45: 0.188498 | AN45: 0.188476 | AO45: 0.188436 | AP45: 0.188357 | AQ45: =IF(B45<>"", B45, AQ44) -> 2 Middle Atlantic
A46: =IFERROR(INDEX(NEMS_mapping!C$15:C$29,MATCH(C46,NEMS_mapping!B$15:B$29,0)),"") -> 0 | C46: 6 Lighting | D46: Capital Invest | E46: 0.255414 | F46: 0.226772 | G46: 0.212427 | H46: 0.186617 | I46: 0.166268 | J46: 0.148472 | K46: 0.134013 | L46: 0.122075 | M46: 0.109162 | N46: 0.163772 | O46: 0.166137 | P46: 0.168998 | Q46: 0.17229 | R46: 0.172389 | S46: 0.171783 | T46: 0.173105 | U46: 0.174613 | V46: 0.183948 | W46: 0.185485 | X46: 0.186495 | Y46: 0.185988 | Z46: 0.187287 | AA46: 0.185754 | AB46: 0.184258 | AC46: 0.183309 | AD46: 0.181005 | AE46: 0.178986 | AF46: 0.18303 | AG46: 0.182978 | AH46: 0.186147 | AI46: 0.186372 | AJ46: 0.186697 | AK46: 0.187103 | AL46: 0.187576 | AM46: 0.184979 | AN46: 0.185501 | AO46: 0.186016 | AP46: 0.1865 | AQ46: =IF(B46<>"", B46, AQ45) -> 2 Middle Atlantic
A47: =IFERROR(INDEX(NEMS_mapping!C$15:C$29,MATCH(C47,NEMS_mapping!B$15:B$29,0)),"") | D47: Tot Subsidy Inv | E47: 0.011094 | F47: 0.010669 | G47: 0.037671 | H47: 0.062386 | I47: 0.064485 | J47: 0.064619 | K47: 0.065085 | L47: 0.064661 | M47: 0.064584 | N47: 0.006216 | O47: 0.005989 | P47: 0.003288 | Q47: 0.001832 | R47: 0.00032 | S47: 0.000238 | T47: 0.00016 | U47: 7.8e-05 | V47: 0 | W47: 0 | X47: 0 | Y47: 0 | Z47: 0 | AA47: 0 | AB47: 0 | AC47: 0 | AD47: 0 | AE47: 0 | AF47: 0 | AG47: 0 | AH47: 0 | AI47: 0 | AJ47: 0 | AK47: 0 | AL47: 0 | AM47: 0 | AN47: 0 | AO47: 0 | AP47: 0 | AQ47: =IF(B47<>"", B47, AQ46) -> 2 Middle Atlantic
A48: =IFERROR(INDEX(NEMS_mapping!C$15:C$29,MATCH(C48,NEMS_mapping!B$15:B$29,0)),"") -> lighting | C48: 6 Lighting Total | E48: 0.266508 | F48: 0.237441 | G48: 0.250098 | H48: 0.249003 | I48: 0.230753 | J48: 0.213091 | K48: 0.199098 | L48: 0.186736 | M48: 0.173746 | N48: 0.169988 | O48: 0.172126 | P48: 0.172286 | Q48: 0.174122 | R48: 0.172709 | S48: 0.172021 | T48: 0.173265 | U48: 0.174691 | V48: 0.183948 | W48: 0.185485 | X48: 0.186495 | Y48: 0.185988 | Z48: 0.187287 | AA48: 0.185754 | AB48: 0.184258 | AC48: 0.183309 | AD48: 0.181005 | AE48: 0.178986 | AF48: 0.18303 | AG48: 0.182978 | AH48: 0.186147 | AI48: 0.186372 | AJ48: 0.186697 | AK48: 0.187103 | AL48: 0.187576 | AM48: 0.184979 | AN48: 0.185501 | AO48: 0.186016 | AP48: 0.1865 | AQ48: =IF(B48<>"", B48, AQ47) -> 2 Middle Atlantic
A49: =IFERROR(INDEX(NEMS_mapping!C$15:C$29,MATCH(C49,NEMS_mapping!B$15:B$29,0)),"") -> 0 | C49: 7 Refrigeration | D49: Capital Invest | E49: 6.979039 | F49: 6.980902 | G49: 7.043346 | H49: 7.004824 | I49: 7.069838 | J49: 7.133008 | K49: 7.096408 | L49: 7.071371 | M49: 7.012146 | N49: 6.720685 | O49: 6.918021 | P49: 7.066034 | Q49: 7.186697 | R49: 7.157597 | S49: 7.147447 | T49: 7.21901 | U49: 7.298033 | V49: 7.365751 | W49: 7.427742 | X49: 7.446698 | Y49: 7.434785 | Z49: 7.416663 | AA49: 7.391016 | AB49: 7.363108 | AC49: 7.337877 | AD49: 7.309996 | AE49: 7.28132 | AF49: 7.255049 | AG49: 7.240922 | AH49: 7.230901 | AI49: 7.225944 | AJ49: 7.224781 | AK49: 7.226614 | AL49: 7.230633 | AM49: 7.235331 | AN49: 7.240629 | AO49: 7.24547 | AP49: 7.249042 | AQ49: =IF(B49<>"", B49, AQ48) -> 2 Middle Atlantic
A50: =IFERROR(INDEX(NEMS_mapping!C$15:C$29,MATCH(C50,NEMS_mapping!B$15:B$29,0)),"") | D50: Tot Subsidy Inv | E50: 0 | F50: 0 | G50: 0 | H50: 0 | I50: 0 | J50: 0 | K50: 0 | L50: 0 | M50: 0 | N50: 0 | O50: 0 | P50: 0 | Q50: 0 | R50: 0 | S50: 0 | T50: 0 | U50: 0 | V50: 0 | W50: 0 | X50: 0 | Y50: 0 | Z50: 0 | AA50: 0 | AB50: 0 | AC50: 0 | AD50: 0 | AE50: 0 | AF50: 0 | AG50: 0 | AH50: 0 | AI50: 0 | AJ50: 0 | AK50: 0 | AL50: 0 | AM50: 0 | AN50: 0 | AO50: 0 | AP50: 0 | AQ50: =IF(B50<>"", B50, AQ49) -> 2 Middle Atlantic
A51: =IFERROR(INDEX(NEMS_mapping!C$15:C$29,MATCH(C51,NEMS_mapping!B$15:B$29,0)),"") -> appliances | C51: 7 Refrigeration Total | E51: 6.979039 | F51: 6.980902 | G51: 7.043346 | H51: 7.004824 | I51: 7.069838 | J51: 7.133008 | K51: 7.096408 | L51: 7.071371 | M51: 7.012146 | N51: 6.720685 | O51: 6.918021 | P51: 7.066034 | Q51: 7.186697 | R51: 7.157597 | S51: 7.147447 | T51: 7.21901 | U51: 7.298033 | V51: 7.365751 | W51: 7.427742 | X51: 7.446698 | Y51: 7.434785 | Z51: 7.416663 | AA51: 7.391016 | AB51: 7.363108 | AC51: 7.337877 | AD51: 7.309996 | AE51: 7.28132 | AF51: 7.255049 | AG51: 7.240922 | AH51: 7.230901 | AI51: 7.225944 | AJ51: 7.224781 | AK51: 7.226614 | AL51: 7.230633 | AM51: 7.235331 | AN51: 7.240629 | AO51: 7.24547 | AP51: 7.249042 | AQ51: =IF(B51<>"", B51, AQ50) -> 2 Middle Atlantic
A52: =IFERROR(INDEX(NEMS_mapping!C$15:C$29,MATCH(C52,NEMS_mapping!B$15:B$29,0)),"") | B52: 2 Middle Atlantic Total | E52: 12.359653 | F52: 11.40014 | G52: 11.556686 | H52: 11.348659 | I52: 11.384887 | J52: 11.321911 | K52: 11.205706 | L52: 11.151264 | M52: 10.981011 | N52: 10.619573 | O52: 10.877486 | P52: 11.012469 | Q52: 11.139183 | R52: 11.026938 | S52: 10.952444 | T52: 11.023388 | U52: 11.105612 | V52: 11.281996 | W52: 11.330213 | X52: 11.308118 | Y52: 11.221424 | Z52: 11.145309 | AA52: 11.059863 | AB52: 10.97266 | AC52: 10.895069 | AD52: 10.816919 | AE52: 10.740665 | AF52: 10.678813 | AG52: 10.628979 | AH52: 10.591115 | AI52: 10.55917 | AJ52: 10.534769 | AK52: 10.517005 | AL52: 10.503274 | AM52: 10.487731 | AN52: 10.479034 | AO52: 10.470155 | AP52: 10.460691 | AQ52: =IF(B52<>"", B52, AQ51) -> 2 Middle Atlantic Total
A53: =IFERROR(INDEX(NEMS_mapping!C$15:C$29,MATCH(C53,NEMS_mapping!B$15:B$29,0)),"") -> 0 | B53: 3 East North Central | C53: 1 Heating | D53: Capital Invest | E53: 1.698877 | F53: 1.686386 | G53: 1.663162 | H53: 1.64933 | I53: 1.673189 | J53: 1.254986 | K53: 1.235014 | L53: 1.198289 | M53: 1.174899 | N53: 1.158965 | O53: 1.130364 | P53: 1.125297 | Q53: 1.122917 | R53: 1.091103 | S53: 1.067733 | T53: 1.060483 | U53: 1.054312 | V53: 1.044787 | W53: 1.024419 | X53: 1.006824 | Y53: 1.005368 | Z53: 0.983551 | AA53: 0.961406 | AB53: 0.935924 | AC53: 0.915967 | AD53: 0.896354 | AE53: 0.877624 | AF53: 0.858783 | AG53: 0.842361 | AH53: 0.827223 | AI53: 0.812535 | AJ53: 0.798743 | AK53: 0.785796 | AL53: 0.773242 | AM53: 0.760928 | AN53: 0.748756 | AO53: 0.736664 | AP53: 0.724615 | AQ53: =IF(B53<>"", B53, AQ52) -> 3 East North Central
A54: =IFERROR(INDEX(NEMS_mapping!C$15:C$29,MATCH(C54,NEMS_mapping!B$15:B$29,0)),"") | D54: Tot Subsidy Inv | E54: 0.068711 | F54: 0.066546 | G54: 0.064582 | H54: 0.063374 | I54: 0.064589 | J54: 0.036604 | K54: 0.035626 | L54: 0.046381 | M54: 0.044989 | N54: 0.045483 | O54: 0.047566 | P54: 0.046159 | Q54: 0.042992 | R54: 0.040353 | S54: 0.038554 | T54: 0.037454 | U54: 0.036704 | V54: 0.035393 | W54: 0.033788 | X54: 0.032646 | Y54: 0.008232 | Z54: 0.008132 | AA54: 0.007979 | AB54: 0.007592 | AC54: 0.00745 | AD54: 0.007302 | AE54: 0.007166 | AF54: 0.006971 | AG54: 0.006837 | AH54: 0.006726 | AI54: 0.006551 | AJ54: 0.006276 | AK54: 0.006179 | AL54: 0.006084 | AM54: 0.005991 | AN54: 0.005894 | AO54: 0.005786 | AP54: 0.005695 | AQ54: =IF(B54<>"", B54, AQ53) -> 3 East North Central
A55: =IFERROR(INDEX(NEMS_mapping!C$15:C$29,MATCH(C55,NEMS_mapping!B$15:B$29,0)),"") -> heating | C55: 1 Heating Total | E55: 1.767588 | F55: 1.752932 | G55: 1.727744 | H55: 1.712704 | I55: 1.737778 | J55: 1.29159 | K55: 1.27064 | L55: 1.24467 | M55: 1.219888 | N55: 1.204448 | O55: 1.17793 | P55: 1.171456 | Q55: 1.165909 | R55: 1.131456 | S55: 1.106287 | T55: 1.097937 | U55: 1.091016 | V55: 1.08018 | W55: 1.058207 | X55: 1.03947 | Y55: 1.0136 | Z55: 0.991683 | AA55: 0.969385 | AB55: 0.943516 | AC55: 0.923417 | AD55: 0.903656 | AE55: 0.88479 | AF55: 0.865754 | AG55: 0.849198 | AH55: 0.833949 | AI55: 0.819086 | AJ55: 0.805019 | AK55: 0.791975 | AL55: 0.779326 | AM55: 0.766919 | AN55: 0.75465 | AO55: 0.74245 | AP55: 0.73031 | AQ55: =IF(B55<>"", B55, AQ54) -> 3 East North Central
A56: =IFERROR(INDEX(NEMS_mapping!C$15:C$29,MATCH(C56,NEMS_mapping!B$15:B$29,0)),"") -> 0 | C56: 2 Cooling | D56: Capital Invest | E56: 1.188797 | F56: 0.819744 | G56: 0.849961 | H56: 0.873886 | I56: 0.840025 | J56: 0.874615 | K56: 0.868002 | L56: 0.860548 | M56: 0.847873 | N56: 0.847986 | O56: 0.848877 | P56: 0.863885 | Q56: 0.873401 | R56: 0.86042 | S56: 0.851167 | T56: 0.858294 | U56: 0.866698 | V56: 0.874471 | W56: 0.87813 | X56: 0.874139 | Y56: 0.865459 | Z56: 0.856432 | AA56: 0.846869 | AB56: 0.837788 | AC56: 0.829919 | AD56: 0.822473 | AE56: 0.815594 | AF56: 0.811877 | AG56: 0.807581 | AH56: 0.804452 | AI56: 0.802541 | AJ56: 0.801592 | AK56: 0.801213 | AL56: 0.801249 | AM56: 0.801722 | AN56: 0.802604 | AO56: 0.803582 | AP56: 0.802754 | AQ56: =IF(B56<>"", B56, AQ55) -> 3 East North Central
A57: =IFERROR(INDEX(NEMS_mapping!C$15:C$29,MATCH(C57,NEMS_mapping!B$15:B$29,0)),"") | D57: Tot Subsidy Inv | E57: 0.008051 | F57: 0.008289 | G57: 0.009415 | H57: 0.008971 | I57: 0.006403 | J57: 0.006081 | K57: 0.005524 | L57: 0.006428 | M57: 0.006826 | N57: 0.006467 | O57: 0.006417 | P57: 0.007469 | Q57: 0.00577 | R57: 0.005433 | S57: 0.005255 | T57: 0.005426 | U57: 0.005625 | V57: 0.007422 | W57: 0.007606 | X57: 0.007679 | Y57: 0.006375 | Z57: 0.006382 | AA57: 0.006376 | AB57: 0.006367 | AC57: 0.006375 | AD57: 0.006412 | AE57: 0.006492 | AF57: 0.007998 | AG57: 0.008061 | AH57: 0.008125 | AI57: 0.00822 | AJ57: 0.008333 | AK57: 0.008457 | AL57: 0.008591 | AM57: 0.008534 | AN57: 0.008455 | AO57: 0.008593 | AP57: 0.008369 | AQ57: =IF(B57<>"", B57, AQ56) -> 3 East North Central
A58: =IFERROR(INDEX(NEMS_mapping!C$15:C$29,MATCH(C58,NEMS_mapping!B$15:B$29,0)),"") -> cooling and ventilation | C58: 2 Cooling Total | E58: 1.196848 | F58: 0.828033 | G58: 0.859376 | H58: 0.882857 | I58: 0.846428 | J58: 0.880696 | K58: 0.873526 | L58: 0.866976 | M58: 0.854699 | N58: 0.854453 | O58: 0.855294 | P58: 0.871354 | Q58: 0.879171 | R58: 0.865853 | S58: 0.856422 | T58: 0.86372 | U58: 0.872323 | V58: 0.881893 | W58: 0.885736 | X58: 0.881818 | Y58: 0.871834 | Z58: 0.862814 | AA58: 0.853245 | AB58: 0.844155 | AC58: 0.836294 | AD58: 0.828885 | AE58: 0.822086 | AF58: 0.819875 | AG58: 0.815642 | AH58: 0.812577 | AI58: 0.810761 | AJ58: 0.809925 | AK58: 0.80967 | AL58: 0.80984 | AM58: 0.810256 | AN58: 0.811059 | AO58: 0.812175 | AP58: 0.811123 | AQ58: =IF(B58<>"", B58, AQ57) -> 3 East North Central
A59: =IFERROR(INDEX(NEMS_mapping!C$15:C$29,MATCH(C59,NEMS_mapping!B$15:B$29,0)),"") -> 0 | C59: 3 Water Heating | D59: Capital Invest | E59: 0.101914 | F59: 0.103061 | G59: 0.104724 | H59: 0.107214 | I59: 0.109698 | J59: 0.111069 | K59: 0.113094 | L59: 0.114231 | M59: 0.114434 | N59: 0.114174 | O59: 0.115231 | P59: 0.118166 | Q59: 0.12092 | R59: 0.120904 | S59: 0.122051 | T59: 0.12403 | U59: 0.126121 | V59: 0.127988 | W59: 0.129646 | X59: 0.130496 | Y59: 0.130755 | Z59: 0.130909 | AA59: 0.130914 | AB59: 0.13088 | AC59: 0.131102 | AD59: 0.131058 | AE59: 0.131011 | AF59: 0.130993 | AG59: 0.131133 | AH59: 0.131352 | AI59: 0.131664 | AJ59: 0.132045 | AK59: 0.132479 | AL59: 0.132952 | AM59: 0.133444 | AN59: 0.13394 | AO59: 0.134426 | AP59: 0.134888 | AQ59: =IF(B59<>"", B59, AQ58) -> 3 East North Central
A60: =IFERROR(INDEX(NEMS_mapping!C$15:C$29,MATCH(C60,NEMS_mapping!B$15:B$29,0)),"") | D60: Tot Subsidy Inv | E60: 0.00492 | F60: 0.004895 | G60: 0.004904 | H60: 0.005057 | I60: 0.006378 | J60: 0.006586 | K60: 0.006682 | L60: 0.006528 | M60: 0.006495 | N60: 0.006518 | O60: 0.010301 | P60: 0.010089 | Q60: 0.009687 | R60: 0.008609 | S60: 0.004586 | T60: 0.004652 | U60: 0.004722 | V60: 0.004783 | W60: 0.004834 | X60: 0.004855 | Y60: 0.004853 | Z60: 0.004848 | AA60: 0.004836 | AB60: 0.004825 | AC60: 0.004978 | AD60: 0.004968 | AE60: 0.004964 | AF60: 0.004955 | AG60: 0.004952 | AH60: 0.004952 | AI60: 0.004955 | AJ60: 0.004961 | AK60: 0.004968 | AL60: 0.004976 | AM60: 0.004985 | AN60: 0.004993 | AO60: 0.005001 | AP60: 0.005007 | AQ60: =IF(B60<>"", B60, AQ59) -> 3 East North Central
A61: =IFERROR(INDEX(NEMS_mapping!C$15:C$29,MATCH(C61,NEMS_mapping!B$15:B$29,0)),"") -> appliances | C61: 3 Water Heating Total | E61: 0.106834 | F61: 0.107956 | G61: 0.109628 | H61: 0.112271 | I61: 0.116076 | J61: 0.117655 | K61: 0.119776 | L61: 0.120759 | M61: 0.120929 | N61: 0.120692 | O61: 0.125532 | P61: 0.128255 | Q61: 0.130607 | R61: 0.129513 | S61: 0.126637 | T61: 0.128682 | U61: 0.130843 | V61: 0.132771 | W61: 0.13448 | X61: 0.135351 | Y61: 0.135608 | Z61: 0.135757 | AA61: 0.13575 | AB61: 0.135705 | AC61: 0.13608 | AD61: 0.136026 | AE61: 0.135975 | AF61: 0.135948 | AG61: 0.136085 | AH61: 0.136304 | AI61: 0.136619 | AJ61: 0.137006 | AK61: 0.137447 | AL61: 0.137928 | AM61: 0.138429 | AN61: 0.138933 | AO61: 0.139427 | AP61: 0.139895 | AQ61: =IF(B61<>"", B61, AQ60) -> 3 East North Central
A62: =IFERROR(INDEX(NEMS_mapping!C$15:C$29,MATCH(C62,NEMS_mapping!B$15:B$29,0)),"") -> 0 | C62: 4 Ventilation | D62: Capital Invest | E62: 1.183035 | F62: 1.148296 | G62: 1.119197 | H62: 1.102604 | I62: 1.096834 | J62: 1.058473 | K62: 1.036523 | L62: 1.007899 | M62: 0.981576 | N62: 0.953777 | O62: 0.939723 | P62: 0.929796 | Q62: 0.92425 | R62: 0.894301 | S62: 0.869095 | T62: 0.857201 | U62: 0.846111 | V62: 0.823307 | W62: 0.809116 | X62: 0.789474 | Y62: 0.766753 | Z62: 0.744709 | AA62: 0.723081 | AB62: 0.702491 | AC62: 0.683429 | AD62: 0.665126 | AE62: 0.647739 | AF62: 0.631544 | AG62: 0.616798 | AH62: 0.60319 | AI62: 0.590671 | AJ62: 0.579021 | AK62: 0.568079 | AL62: 0.557721 | AM62: 0.547793 | AN62: 0.538208 | AO62: 0.528889 | AP62: 0.519768 | AQ62: =IF(B62<>"", B62, AQ61) -> 3 East North Central
A63: =IFERROR(INDEX(NEMS_mapping!C$15:C$29,MATCH(C63,NEMS_mapping!B$15:B$29,0)),"") | D63: Tot Subsidy Inv | E63: 0 | F63: 0 | G63: 0 | H63: 0 | I63: 0 | J63: 0 | K63: 0 | L63: 0 | M63: 0 | N63: 1e-06 | O63: 1e-06 | P63: 1e-06 | Q63: 1e-06 | R63: 1e-06 | S63: 0 | T63: 0 | U63: 0 | V63: 0.069574 | W63: 0.068482 | X63: 0.06691 | Y63: 0.065066 | Z63: 0.063279 | AA63: 0.061526 | AB63: 0.059863 | AC63: 0.058333 | AD63: 0.056869 | AE63: 0.055484 | AF63: 0.054204 | AG63: 0.053046 | AH63: 0.051988 | AI63: 0.051027 | AJ63: 0.050143 | AK63: 0.049321 | AL63: 0.048552 | AM63: 0.04782 | AN63: 0.047118 | AO63: 0.046439 | AP63: 0.045778 | AQ63: =IF(B63<>"", B63, AQ62) -> 3 East North Central
A64: =IFERROR(INDEX(NEMS_mapping!C$15:C$29,MATCH(C64,NEMS_mapping!B$15:B$29,0)),"") -> appliances | C64: 4 Ventilation Total | E64: 1.183035 | F64: 1.148296 | G64: 1.119197 | H64: 1.102604 | I64: 1.096834 | J64: 1.058473 | K64: 1.036523 | L64: 1.007899 | M64: 0.981576 | N64: 0.953778 | O64: 0.939724 | P64: 0.929797 | Q64: 0.924251 | R64: 0.894302 | S64: 0.869095 | T64: 0.857201 | U64: 0.846111 | V64: 0.892881 | W64: 0.877598 | X64: 0.856384 | Y64: 0.831819 | Z64: 0.807988 | AA64: 0.784607 | AB64: 0.762354 | AC64: 0.741762 | AD64: 0.721995 | AE64: 0.703223 | AF64: 0.685748 | AG64: 0.669844 | AH64: 0.655178 | AI64: 0.641698 | AJ64: 0.629164 | AK64: 0.6174 | AL64: 0.606273 | AM64: 0.595613 | AN64: 0.585326 | AO64: 0.575328 | AP64: 0.565546 | AQ64: =IF(B64<>"", B64, AQ63) -> 3 East North Central
A65: =IFERROR(INDEX(NEMS_mapping!C$15:C$29,MATCH(C65,NEMS_mapping!B$15:B$29,0)),"") -> 0 | C65: 5 Cooking | D65: Capital Invest | E65: 0.250765 | F65: 0.251361 | G65: 0.25071 | H65: 0.251911 | I65: 0.251954 | J65: 0.250348 | K65: 0.250404 | L65: 0.249345 | M65: 0.24619 | N65: 0.243315 | O65: 0.246632 | P65: 0.25146 | Q65: 0.255252 | R65: 0.253173 | S65: 0.251913 | T65: 0.253838 | U65: 0.256011 | V65: 0.257724 | W65: 0.259018 | X65: 0.258671 | Y65: 0.257176 | Z65: 0.255536 | AA65: 0.253678 | AB65: 0.2518 | AC65: 0.25008 | AD65: 0.24831 | AE65: 0.246555 | AF65: 0.244931 | AG65: 0.243657 | AH65: 0.242568 | AI65: 0.241679 | AJ65: 0.24094 | AK65: 0.240311 | AL65: 0.239767 | AM65: 0.239257 | AN65: 0.238756 | AO65: 0.238238 | AP65: 0.237674 | AQ65: =IF(B65<>"", B65, AQ64) -> 3 East North Central
A66: =IFERROR(INDEX(NEMS_mapping!C$15:C$29,MATCH(C66,NEMS_mapping!B$15:B$29,0)),"") | D66: Tot Subsidy Inv | E66: 0 | F66: 0 | G66: 0 | H66: 0 | I66: 0 | J66: 0 | K66: 0 | L66: 0 | M66: 0 | N66: 0 | O66: 0 | P66: 0 | Q66: 0 | R66: 0 | S66: 0 | T66: 0 | U66: 0 | V66: 0 | W66: 0 | X66: 0 | Y66: 0 | Z66: 0 | AA66: 0 | AB66: 0 | AC66: 0 | AD66: 0 | AE66: 0 | AF66: 0 | AG66: 0 | AH66: 0 | AI66: 0 | AJ66: 0 | AK66: 0 | AL66: 0 | AM66: 0 | AN66: 0 | AO66: 0 | AP66: 0 | AQ66: =IF(B66<>"", B66, AQ65) -> 3 East North Central
A67: =IFERROR(INDEX(NEMS_mapping!C$15:C$29,MATCH(C67,NEMS_mapping!B$15:B$29,0)),"") -> appliances | C67: 5 Cooking Total | E67: 0.250765 | F67: 0.251361 | G67: 0.25071 | H67: 0.251911 | I67: 0.251954 | J67: 0.250348 | K67: 0.250404 | L67: 0.249345 | M67: 0.24619 | N67: 0.243315 | O67: 0.246632 | P67: 0.25146 | Q67: 0.255252 | R67: 0.253173 | S67: 0.251913 | T67: 0.253838 | U67: 0.256011 | V67: 0.257724 | W67: 0.259018 | X67: 0.258671 | Y67: 0.257176 | Z67: 0.255536 | AA67: 0.253678 | AB67: 0.2518 | AC67: 0.25008 | AD67: 0.24831 | AE67: 0.246555 | AF67: 0.244931 | AG67: 0.243657 | AH67: 0.242568 | AI67: 0.241679 | AJ67: 0.24094 | AK67: 0.240311 | AL67: 0.239767 | AM67: 0.239257 | AN67: 0.238756 | AO67: 0.238238 | AP67: 0.237674 | AQ67: =IF(B67<>"", B67, AQ66) -> 3 East North Central
A68: =IFERROR(INDEX(NEMS_mapping!C$15:C$29,MATCH(C68,NEMS_mapping!B$15:B$29,0)),"") -> 0 | C68: 6 Lighting | D68: Capital Invest | E68: 0.226553 | F68: 0.210098 | G68: 0.201381 | H68: 0.182636 | I68: 0.163718 | J68: 0.145739 | K68: 0.131038 | L68: 0.11971 | M68: 0.107019 | N68: 0.157366 | O68: 0.157147 | P68: 0.160453 | Q68: 0.163709 | R68: 0.163844 | S68: 0.162858 | T68: 0.163936 | U68: 0.165133 | V68: 0.173197 | W68: 0.173886 | X68: 0.174009 | Y68: 0.172941 | Z68: 0.171955 | AA68: 0.170917 | AB68: 0.170449 | AC68: 0.169947 | AD68: 0.168605 | AE68: 0.167351 | AF68: 0.167371 | AG68: 0.167474 | AH68: 0.167379 | AI68: 0.167411 | AJ68: 0.167228 | AK68: 0.167432 | AL68: 0.167694 | AM68: 0.167977 | AN68: 0.168277 | AO68: 0.168522 | AP68: 0.16879 | AQ68: =IF(B68<>"", B68, AQ67) -> 3 East North Central
A69: =IFERROR(INDEX(NEMS_mapping!C$15:C$29,MATCH(C69,NEMS_mapping!B$15:B$29,0)),"") | D69: Tot Subsidy Inv | E69: 0.009003 | F69: 0.009559 | G69: 0.03611 | H69: 0.059994 | I69: 0.06239 | J69: 0.061977 | K69: 0.06205 | L69: 0.061526 | M69: 0.06137 | N69: 0.00599 | O69: 0.005754 | P69: 0.003113 | Q69: 0.001687 | R69: 0.000279 | S69: 0.000197 | T69: 0.000133 | U69: 6.1e-05 | V69: 0 | W69: 0 | X69: 0 | Y69: 0 | Z69: 0 | AA69: 0 | AB69: 0 | AC69: 0 | AD69: 0 | AE69: 0 | AF69: 0 | AG69: 0 | AH69: 0 | AI69: 0 | AJ69: 0 | AK69: 0 | AL69: 0 | AM69: 0 | AN69: 0 | AO69: 0 | AP69: 0 | AQ69: =IF(B69<>"", B69, AQ68) -> 3 East North Central
A70: =IFERROR(INDEX(NEMS_mapping!C$15:C$29,MATCH(C70,NEMS_mapping!B$15:B$29,0)),"") -> lighting | C70: 6 Lighting Total | E70: 0.235556 | F70: 0.219657 | G70: 0.237491 | H70: 0.24263 | I70: 0.226108 | J70: 0.207716 | K70: 0.193088 | L70: 0.181236 | M70: 0.168389 | N70: 0.163356 | O70: 0.162901 | P70: 0.163566 | Q70: 0.165396 | R70: 0.164123 | S70: 0.163055 | T70: 0.164069 | U70: 0.165194 | V70: 0.173197 | W70: 0.173886 | X70: 0.174009 | Y70: 0.172941 | Z70: 0.171955 | AA70: 0.170917 | AB70: 0.170449 | AC70: 0.169947 | AD70: 0.168605 | AE70: 0.167351 | AF70: 0.167371 | AG70: 0.167474 | AH70: 0.167379 | AI70: 0.167411 | AJ70: 0.167228 | AK70: 0.167432 | AL70: 0.167694 | AM70: 0.167977 | AN70: 0.168277 | AO70: 0.168522 | AP70: 0.16879 | AQ70: =IF(B70<>"", B70, AQ69) -> 3 East North Central
A71: =IFERROR(INDEX(NEMS_mapping!C$15:C$29,MATCH(C71,NEMS_mapping!B$15:B$29,0)),"") -> 0 | C71: 7 Refrigeration | D71: Capital Invest | E71: 5.989024 | F71: 6.020617 | G71: 6.018108 | H71: 6.061346 | I71: 6.086519 | J71: 6.189385 | K71: 6.199104 | L71: 6.199433 | M71: 6.150312 | N71: 5.838843 | O71: 5.920627 | P71: 6.036035 | Q71: 6.139503 | R71: 6.113654 | S71: 6.104667 | T71: 6.166085 | U71: 6.233969 | V71: 6.292346 | W71: 6.343627 | X71: 6.358001 | Y71: 6.345498 | Z71: 6.328342 | AA71: 6.304918 | AB71: 6.279665 | AC71: 6.256821 | AD71: 6.231787 | AE71: 6.206147 | AF71: 6.182619 | AG71: 6.167728 | AH71: 6.156593 | AI71: 6.149732 | AJ71: 6.146059 | AK71: 6.144847 | AL71: 6.145442 | AM71: 6.14682 | AN71: 6.148333 | AO71: 6.149367 | AP71: 6.149257 | AQ71: =IF(B71<>"", B71, AQ70) -> 3 East North Central
A72: =IFERROR(INDEX(NEMS_mapping!C$15:C$29,MATCH(C72,NEMS_mapping!B$15:B$29,0)),"") | D72: Tot Subsidy Inv | E72: 0 | F72: 0 | G72: 0 | H72: 0 | I72: 0 | J72: 0 | K72: 0 | L72: 0 | M72: 0 | N72: 0 | O72: 0 | P72: 0 | Q72: 0 | R72: 0 | S72: 0 | T72: 0 | U72: 0 | V72: 0 | W72: 0 | X72: 0 | Y72: 0 | Z72: 0 | AA72: 0 | AB72: 0 | AC72: 0 | AD72: 0 | AE72: 0 | AF72: 0 | AG72: 0 | AH72: 0 | AI72: 0 | AJ72: 0 | AK72: 0 | AL72: 0 | AM72: 0 | AN72: 0 | AO72: 0 | AP72: 0 | AQ72: =IF(B72<>"", B72, AQ71) -> 3 East North Central
A73: =IFERROR(INDEX(NEMS_mapping!C$15:C$29,MATCH(C73,NEMS_mapping!B$15:B$29,0)),"") -> appliances | C73: 7 Refrigeration Total | E73: 5.989024 | F73: 6.020617 | G73: 6.018108 | H73: 6.061346 | I73: 6.086519 | J73: 6.189385 | K73: 6.199104 | L73: 6.199433 | M73: 6.150312 | N73: 5.838843 | O73: 5.920627 | P73: 6.036035 | Q73: 6.139503 | R73: 6.113654 | S73: 6.104667 | T73: 6.166085 | U73: 6.233969 | V73: 6.292346 | W73: 6.343627 | X73: 6.358001 | Y73: 6.345498 | Z73: 6.328342 | AA73: 6.304918 | AB73: 6.279665 | AC73: 6.256821 | AD73: 6.231787 | AE73: 6.206147 | AF73: 6.182619 | AG73: 6.167728 | AH73: 6.156593 | AI73: 6.149732 | AJ73: 6.146059 | AK73: 6.144847 | AL73: 6.145442 | AM73: 6.14682 | AN73: 6.148333 | AO73: 6.149367 | AP73: 6.149257 | AQ73: =IF(B73<>"", B73, AQ72) -> 3 East North Central
A74: =IFERROR(INDEX(NEMS_mapping!C$15:C$29,MATCH(C74,NEMS_mapping!B$15:B$29,0)),"") | B74: 3 East North Central Total | E74: 10.72965 | F74: 10.328852 | G74: 10.322254 | H74: 10.366323 | I74: 10.361697 | J74: 9.995863 | K74: 9.943061 | L74: 9.870318 | M74: 9.741983 | N74: 9.378885 | O74: 9.42864 | P74: 9.551923 | Q74: 9.660089 | R74: 9.552074 | S74: 9.478076 | T74: 9.531532 | U74: 9.595467 | V74: 9.710992 | W74: 9.732552 | X74: 9.703704 | Y74: 9.628476 | Z74: 9.554075 | AA74: 9.4725 | AB74: 9.387644 | AC74: 9.314401 | AD74: 9.239264 | AE74: 9.166127 | AF74: 9.102246 | AG74: 9.049628 | AH74: 9.004548 | AI74: 8.966986 | AJ74: 8.935341 | AK74: 8.909082 | AL74: 8.88627 | AM74: 8.865271 | AN74: 8.845334 | AO74: 8.825507 | AP74: 8.802595 | AQ74: =IF(B74<>"", B74, AQ73) -> 3 East North Central Total
A75: =IFERROR(INDEX(NEMS_mapping!C$15:C$29,MATCH(C75,NEMS_mapping!B$15:B$29,0)),"") -> 0 | B75: 4 West North Central | C75: 1 Heating | D75: Capital Invest | E75: 0.736383 | F75: 0.748611 | G75: 0.743213 | H75: 0.746528 | I75: 0.761504 | J75: 0.578536 | K75: 0.559018 | L75: 0.53211 | M75: 0.518407 | N75: 0.509891 | O75: 0.49419 | P75: 0.48273 | Q75: 0.477609 | R75: 0.465715 | S75: 0.455986 | T75: 0.45283 | U75: 0.449699 | V75: 0.445185 | W75: 0.440649 | X75: 0.431398 | Y75: 0.451989 | Z75: 0.442007 | AA75: 0.432037 | AB75: 0.420708 | AC75: 0.411653 | AD75: 0.402812 | AE75: 0.394312 | AF75: 0.386333 | AG75: 0.378913 | AH75: 0.371955 | AI75: 0.365396 | AJ75: 0.359102 | AK75: 0.353105 | AL75: 0.347316 | AM75: 0.341171 | AN75: 0.335576 | AO75: 0.329945 | AP75: 0.324439 | AQ75: =IF(B75<>"", B75, AQ74) -> 4 West North Central
A76: =IFERROR(INDEX(NEMS_mapping!C$15:C$29,MATCH(C76,NEMS_mapping!B$15:B$29,0)),"") | D76: Tot Subsidy Inv | E76: 0.060359 | F76: 0.059538 | G76: 0.057794 | H76: 0.056148 | I76: 0.055798 | J76: 0.040597 | K76: 0.038435 | L76: 0.058505 | M76: 0.055974 | N76: 0.054241 | O76: 0.055685 | P76: 0.053171 | Q76: 0.051047 | R76: 0.048633 | S76: 0.046549 | T76: 0.044959 | U76: 0.043394 | V76: 0.041817 | W76: 0.040317 | X76: 0.038662 | Y76: 0.003437 | Z76: 0.003381 | AA76: 0.003321 | AB76: 0.003189 | AC76: 0.003132 | AD76: 0.003074 | AE76: 0.003018 | AF76: 0.002966 | AG76: 0.002917 | AH76: 0.002872 | AI76: 0.002827 | AJ76: 0.002783 | AK76: 0.002743 | AL76: 0.002704 | AM76: 0.002637 | AN76: 0.002596 | AO76: 0.002519 | AP76: 0.002481 | AQ76: =IF(B76<>"", B76, AQ75) -> 4 West North Central
A77: =IFERROR(INDEX(NEMS_mapping!C$15:C$29,MATCH(C77,NEMS_mapping!B$15:B$29,0)),"") -> heating | C77: 1 Heating Total | E77: 0.796742 | F77: 0.808149 | G77: 0.801007 | H77: 0.802676 | I77: 0.817302 | J77: 0.619133 | K77: 0.597453 | L77: 0.590615 | M77: 0.574381 | N77: 0.564132 | O77: 0.549875 | P77: 0.535901 | Q77: 0.528656 | R77: 0.514348 | S77: 0.502535 | T77: 0.497789 | U77: 0.493093 | V77: 0.487002 | W77: 0.480966 | X77: 0.47006 | Y77: 0.455426 | Z77: 0.445388 | AA77: 0.435358 | AB77: 0.423897 | AC77: 0.414785 | AD77: 0.405886 | AE77: 0.39733 | AF77: 0.389299 | AG77: 0.38183 | AH77: 0.374827 | AI77: 0.368223 | AJ77: 0.361885 | AK77: 0.355848 | AL77: 0.35002 | AM77: 0.343808 | AN77: 0.338172 | AO77: 0.332464 | AP77: 0.32692 | AQ77: =IF(B77<>"", B77, AQ76) -> 4 West North Central
A78: =IFERROR(INDEX(NEMS_mapping!C$15:C$29,MATCH(C78,NEMS_mapping!B$15:B$29,0)),"") -> 0 | C78: 2 Cooling | D78: Capital Invest | E78: 0.664155 | F78: 0.412634 | G78: 0.464236 | H78: 0.44777 | I78: 0.43229 | J78: 0.445309 | K78: 0.440554 | L78: 0.442745 | M78: 0.434829 | N78: 0.427841 | O78: 0.428298 | P78: 0.436192 | Q78: 0.441665 | R78: 0.43588 | S78: 0.432642 | T78: 0.43685 | U78: 0.441459 | V78: 0.445975 | W78: 0.448417 | X78: 0.447012 | Y78: 0.444087 | Z78: 0.440581 | AA78: 0.436758 | AB78: 0.43325 | AC78: 0.430308 | AD78: 0.427567 | AE78: 0.425081 | AF78: 0.42436 | AG78: 0.423371 | AH78: 0.422696 | AI78: 0.422626 | AJ78: 0.422895 | AK78: 0.423758 | AL78: 0.425102 | AM78: 0.426562 | AN78: 0.428123 | AO78: 0.429743 | AP78: 0.431488 | AQ78: =IF(B78<>"", B78, AQ77) -> 4 West North Central
A79: =IFERROR(INDEX(NEMS_mapping!C$15:C$29,MATCH(C79,NEMS_mapping!B$15:B$29,0)),"") | D79: Tot Subsidy Inv | E79: 0.004405 | F79: 0.004464 | G79: 0.006322 | H79: 0.006146 | I79: 0.004564 | J79: 0.004306 | K79: 0.003388 | L79: 0.004819 | M79: 0.005368 | N79: 0.004206 | O79: 0.004103 | P79: 0.004639 | Q79: 0.003976 | R79: 0.003831 | S79: 0.003783 | T79: 0.00389 | U79: 0.003915 | V79: 0.004586 | W79: 0.004449 | X79: 0.004439 | Y79: 0.002383 | Z79: 0.002383 | AA79: 0.002367 | AB79: 0.002359 | AC79: 0.002359 | AD79: 0.002361 | AE79: 0.002373 | AF79: 0.003344 | AG79: 0.003391 | AH79: 0.003422 | AI79: 0.003477 | AJ79: 0.003538 | AK79: 0.003511 | AL79: 0.00356 | AM79: 0.003505 | AN79: 0.00354 | AO79: 0.003476 | AP79: 0.003542 | AQ79: =IF(B79<>"", B79, AQ78) -> 4 West North Central
A80: =IFERROR(INDEX(NEMS_mapping!C$15:C$29,MATCH(C80,NEMS_mapping!B$15:B$29,0)),"") -> cooling and ventilation | C80: 2 Cooling Total | E80: 0.66856 | F80: 0.417098 | G80: 0.470558 | H80: 0.453916 | I80: 0.436854 | J80: 0.449615 | K80: 0.443942 | L80: 0.447564 | M80: 0.440197 | N80: 0.432047 | O80: 0.432401 | P80: 0.440831 | Q80: 0.445641 | R80: 0.439711 | S80: 0.436425 | T80: 0.44074 | U80: 0.445374 | V80: 0.450561 | W80: 0.452866 | X80: 0.451451 | Y80: 0.44647 | Z80: 0.442964 | AA80: 0.439125 | AB80: 0.435609 | AC80: 0.432667 | AD80: 0.429928 | AE80: 0.427454 | AF80: 0.427704 | AG80: 0.426762 | AH80: 0.426118 | AI80: 0.426103 | AJ80: 0.426433 | AK80: 0.427269 | AL80: 0.428662 | AM80: 0.430067 | AN80: 0.431663 | AO80: 0.433219 | AP80: 0.43503 | AQ80: =IF(B80<>"", B80, AQ79) -> 4 West North Central
A81: =IFERROR(INDEX(NEMS_mapping!C$15:C$29,MATCH(C81,NEMS_mapping!B$15:B$29,0)),"") -> 0 | C81: 3 Water Heating | D81: Capital Invest | E81: 0.026227 | F81: 0.027019 | G81: 0.027533 | H81: 0.028323 | I81: 0.029784 | J81: 0.029887 | K81: 0.029655 | L81: 0.0302 | M81: 0.029774 | N81: 0.029547 | O81: 0.030018 | P81: 0.030478 | Q81: 0.031086 | R81: 0.03104 | S81: 0.031551 | T81: 0.032054 | U81: 0.032587 | V81: 0.033062 | W81: 0.033485 | X81: 0.033702 | Y81: 0.03377 | Z81: 0.033811 | AA81: 0.033818 | AB81: 0.033812 | AC81: 0.03382 | AD81: 0.033858 | AE81: 0.03385 | AF81: 0.033852 | AG81: 0.033896 | AH81: 0.033966 | AI81: 0.034054 | AJ81: 0.034157 | AK81: 0.034277 | AL81: 0.034407 | AM81: 0.034543 | AN81: 0.034679 | AO81: 0.034813 | AP81: 0.03494 | AQ81: =IF(B81<>"", B81, AQ80) -> 4 West North Central
A82: =IFERROR(INDEX(NEMS_mapping!C$15:C$29,MATCH(C82,NEMS_mapping!B$15:B$29,0)),"") | D82: Tot Subsidy Inv | E82: 0.001859 | F82: 0.001844 | G82: 0.001881 | H82: 0.002058 | I82: 0.002955 | J82: 0.003047 | K82: 0.003 | L82: 0.002537 | M82: 0.002143 | N82: 0.002093 | O82: 0.004306 | P82: 0.004341 | Q82: 0.003842 | R82: 0.003627 | S82: 0.001542 | T82: 0.001558 | U82: 0.001576 | V82: 0.001591 | W82: 0.001604 | X82: 0.001606 | Y82: 0.0016 | Z82: 0.001594 | AA82: 0.001586 | AB82: 0.001578 | AC82: 0.001571 | AD82: 0.001595 | AE82: 0.001589 | AF82: 0.001583 | AG82: 0.001579 | AH82: 0.001576 | AI82: 0.001574 | AJ82: 0.001573 | AK82: 0.001572 | AL82: 0.001572 | AM82: 0.001572 | AN82: 0.001572 | AO82: 0.001572 | AP82: 0.001571 | AQ82: =IF(B82<>"", B82, AQ81) -> 4 West North Central
A83: =IFERROR(INDEX(NEMS_mapping!C$15:C$29,MATCH(C83,NEMS_mapping!B$15:B$29,0)),"") -> appliances | C83: 3 Water Heating Total | E83: 0.028086 | F83: 0.028863 | G83: 0.029414 | H83: 0.030381 | I83: 0.032739 | J83: 0.032934 | K83: 0.032655 | L83: 0.032737 | M83: 0.031917 | N83: 0.03164 | O83: 0.034324 | P83: 0.034819 | Q83: 0.034928 | R83: 0.034667 | S83: 0.033093 | T83: 0.033612 | U83: 0.034163 | V83: 0.034653 | W83: 0.035089 | X83: 0.035308 | Y83: 0.03537 | Z83: 0.035405 | AA83: 0.035404 | AB83: 0.03539 | AC83: 0.035391 | AD83: 0.035453 | AE83: 0.035439 | AF83: 0.035435 | AG83: 0.035475 | AH83: 0.035542 | AI83: 0.035628 | AJ83: 0.03573 | AK83: 0.035849 | AL83: 0.035979 | AM83: 0.036115 | AN83: 0.036251 | AO83: 0.036385 | AP83: 0.036511 | AQ83: =IF(B83<>"", B83, AQ82) -> 4 West North Central
A84: =IFERROR(INDEX(NEMS_mapping!C$15:C$29,MATCH(C84,NEMS_mapping!B$15:B$29,0)),"") -> 0 | C84: 4 Ventilation | D84: Capital Invest | E84: 0.469486 | F84: 0.467004 | G84: 0.457693 | H84: 0.451842 | I84: 0.452968 | J84: 0.436007 | K84: 0.424089 | L84: 0.41959 | M84: 0.407835 | N84: 0.390697 | O84: 0.381054 | P84: 0.381376 | Q84: 0.379281 | R84: 0.370038 | S84: 0.360215 | T84: 0.355678 | U84: 0.351457 | V84: 0.34244 | W84: 0.336988 | X84: 0.329347 | Y84: 0.320456 | Z84: 0.311819 | AA84: 0.303331 | AB84: 0.295244 | AC84: 0.287758 | AD84: 0.280564 | AE84: 0.273729 | AF84: 0.267364 | AG84: 0.26159 | AH84: 0.256269 | AI84: 0.251388 | AJ84: 0.246856 | AK84: 0.24261 | AL84: 0.238602 | AM84: 0.234769 | AN84: 0.231075 | AO84: 0.227491 | AP84: 0.221517 | AQ84: =IF(B84<>"", B84, AQ83) -> 4 West North Central
A85: =IFERROR(INDEX(NEMS_mapping!C$15:C$29,MATCH(C85,NEMS_mapping!B$15:B$29,0)),"") | D85: Tot Subsidy Inv | E85: 0 | F85: 0 | G85: 0 | H85: 0 | I85: 0 | J85: 0 | K85: 0 | L85: 0 | M85: 0 | N85: 0.001245 | O85: 0.001219 | P85: 0.001218 | Q85: 0.001081 | R85: 0.002976 | S85: 0.002892 | T85: 0.002848 | U85: 0.002807 | V85: 0.03137 | W85: 0.030919 | X85: 0.03026 | Y85: 0.029481 | Z85: 0.028724 | AA85: 0.027981 | AB85: 0.027274 | AC85: 0.026624 | AD85: 0.026001 | AE85: 0.025411 | AF85: 0.024866 | AG85: 0.024374 | AH85: 0.023926 | AI85: 0.023519 | AJ85: 0.023146 | AK85: 0.0228 | AL85: 0.022476 | AM85: 0.02217 | AN85: 0.021876 | AO85: 0.021593 | AP85: 0.01961 | AQ85: =IF(B85<>"", B85, AQ84) -> 4 West North Central
A86: =IFERROR(INDEX(NEMS_mapping!C$15:C$29,MATCH(C86,NEMS_mapping!B$15:B$29,0)),"") -> appliances | C86: 4 Ventilation Total | E86: 0.469486 | F86: 0.467004 | G86: 0.457693 | H86: 0.451842 | I86: 0.452968 | J86: 0.436007 | K86: 0.424089 | L86: 0.41959 | M86: 0.407835 | N86: 0.391942 | O86: 0.382273 | P86: 0.382594 | Q86: 0.380362 | R86: 0.373014 | S86: 0.363107 | T86: 0.358526 | U86: 0.354264 | V86: 0.37381 | W86: 0.367907 | X86: 0.359607 | Y86: 0.349937 | Z86: 0.340543 | AA86: 0.331312 | AB86: 0.322518 | AC86: 0.314382 | AD86: 0.306565 | AE86: 0.29914 | AF86: 0.29223 | AG86: 0.285964 | AH86: 0.280195 | AI86: 0.274907 | AJ86: 0.270002 | AK86: 0.26541 | AL86: 0.261078 | AM86: 0.256939 | AN86: 0.252951 | AO86: 0.249084 | AP86: 0.241127 | AQ86: =IF(B86<>"", B86, AQ85) -> 4 West North Central
A87: =IFERROR(INDEX(NEMS_mapping!C$15:C$29,MATCH(C87,NEMS_mapping!B$15:B$29,0)),"") -> 0 | C87: 5 Cooking | D87: Capital Invest | E87: 0.103395 | F87: 0.105619 | G87: 0.105577 | H87: 0.105713 | I87: 0.10626 | J87: 0.105586 | K87: 0.104283 | L87: 0.105075 | M87: 0.103367 | N87: 0.101837 | O87: 0.104116 | P87: 0.106499 | Q87: 0.108316 | R87: 0.107695 | S87: 0.107411 | T87: 0.108458 | U87: 0.109614 | V87: 0.110582 | W87: 0.11138 | X87: 0.111491 | Y87: 0.111114 | Z87: 0.110674 | AA87: 0.110138 | AB87: 0.109589 | AC87: 0.109103 | AD87: 0.108593 | AE87: 0.108086 | AF87: 0.107632 | AG87: 0.107329 | AH87: 0.107105 | AI87: 0.106966 | AJ87: 0.10689 | AK87: 0.106863 | AL87: 0.106872 | AM87: 0.106896 | AN87: 0.106925 | AO87: 0.106946 | AP87: 0.106947 | AQ87: =IF(B87<>"", B87, AQ86) -> 4 West North Central
A88: =IFERROR(INDEX(NEMS_mapping!C$15:C$29,MATCH(C88,NEMS_mapping!B$15:B$29,0)),"") | D88: Tot Subsidy Inv | E88: 0 | F88: 0 | G88: 0 | H88: 0 | I88: 0 | J88: 0 | K88: 0 | L88: 0 | M88: 0 | N88: 0 | O88: 0 | P88: 0 | Q88: 0 | R88: 0 | S88: 0 | T88: 0 | U88: 0 | V88: 0 | W88: 0 | X88: 0 | Y88: 0 | Z88: 0 | AA88: 0 | AB88: 0 | AC88: 0 | AD88: 0 | AE88: 0 | AF88: 0 | AG88: 0 | AH88: 0 | AI88: 0 | AJ88: 0 | AK88: 0 | AL88: 0 | AM88: 0 | AN88: 0 | AO88: 0 | AP88: 0 | AQ88: =IF(B88<>"", B88, AQ87) -> 4 West North Central
A89: =IFERROR(INDEX(NEMS_mapping!C$15:C$29,MATCH(C89,NEMS_mapping!B$15:B$29,0)),"") -> appliances | C89: 5 Cooking Total | E89: 0.103395 | F89: 0.105619 | G89: 0.105577 | H89: 0.105713 | I89: 0.10626 | J89: 0.105586 | K89: 0.104283 | L89: 0.105075 | M89: 0.103367 | N89: 0.101837 | O89: 0.104116 | P89: 0.106499 | Q89: 0.108316 | R89: 0.107695 | S89: 0.107411 | T89: 0.108458 | U89: 0.109614 | V89: 0.110582 | W89: 0.11138 | X89: 0.111491 | Y89: 0.111114 | Z89: 0.110674 | AA89: 0.110138 | AB89: 0.109589 | AC89: 0.109103 | AD89: 0.108593 | AE89: 0.108086 | AF89: 0.107632 | AG89: 0.107329 | AH89: 0.107105 | AI89: 0.106966 | AJ89: 0.10689 | AK89: 0.106863 | AL89: 0.106872 | AM89: 0.106896 | AN89: 0.106925 | AO89: 0.106946 | AP89: 0.106947 | AQ89: =IF(B89<>"", B89, AQ88) -> 4 West North Central
A90: =IFERROR(INDEX(NEMS_mapping!C$15:C$29,MATCH(C90,NEMS_mapping!B$15:B$29,0)),"") -> 0 | C90: 6 Lighting | D90: Capital Invest | E90: 0.094175 | F90: 0.089236 | G90: 0.085443 | H90: 0.078636 | I90: 0.071639 | J90: 0.063985 | K90: 0.058492 | L90: 0.053964 | M90: 0.048172 | N90: 0.07026 | O90: 0.0702 | P90: 0.071788 | Q90: 0.073514 | R90: 0.073927 | S90: 0.073769 | T90: 0.074496 | U90: 0.075334 | V90: 0.079078 | W90: 0.079758 | X90: 0.079949 | Y90: 0.079886 | Z90: 0.079691 | AA90: 0.079474 | AB90: 0.079138 | AC90: 0.079381 | AD90: 0.079234 | AE90: 0.078964 | AF90: 0.079353 | AG90: 0.079544 | AH90: 0.079788 | AI90: 0.080088 | AJ90: 0.080369 | AK90: 0.080746 | AL90: 0.081158 | AM90: 0.081569 | AN90: 0.082004 | AO90: 0.082363 | AP90: 0.082781 | AQ90: =IF(B90<>"", B90, AQ89) -> 4 West North Central
A91: =IFERROR(INDEX(NEMS_mapping!C$15:C$29,MATCH(C91,NEMS_mapping!B$15:B$29,0)),"") | D91: Tot Subsidy Inv | E91: 0.003693 | F91: 0.00402 | G91: 0.015621 | H91: 0.025994 | I91: 0.027379 | J91: 0.02739 | K91: 0.027666 | L91: 0.027634 | M91: 0.027536 | N91: 0.002652 | O91: 0.002541 | P91: 0.001379 | Q91: 0.000764 | R91: 0.000129 | S91: 8.9e-05 | T91: 6e-05 | U91: 3e-05 | V91: 0 | W91: 0 | X91: 0 | Y91: 0 | Z91: 0 | AA91: 0 | AB91: 0 | AC91: 0 | AD91: 0 | AE91: 0 | AF91: 0 | AG91: 0 | AH91: 0 | AI91: 0 | AJ91: 0 | AK91: 0 | AL91: 0 | AM91: 0 | AN91: 0 | AO91: 0 | AP91: 0 | AQ91: =IF(B91<>"", B91, AQ90) -> 4 West North Central
A92: =IFERROR(INDEX(NEMS_mapping!C$15:C$29,MATCH(C92,NEMS_mapping!B$15:B$29,0)),"") -> lighting | C92: 6 Lighting Total | E92: 0.097868 | F92: 0.093256 | G92: 0.101064 | H92: 0.10463 | I92: 0.099018 | J92: 0.091375 | K92: 0.086158 | L92: 0.081598 | M92: 0.075708 | N92: 0.072912 | O92: 0.072741 | P92: 0.073167 | Q92: 0.074278 | R92: 0.074056 | S92: 0.073858 | T92: 0.074556 | U92: 0.075364 | V92: 0.079078 | W92: 0.079758 | X92: 0.079949 | Y92: 0.079886 | Z92: 0.079691 | AA92: 0.079474 | AB92: 0.079138 | AC92: 0.079381 | AD92: 0.079234 | AE92: 0.078964 | AF92: 0.079353 | AG92: 0.079544 | AH92: 0.079788 | AI92: 0.080088 | AJ92: 0.080369 | AK92: 0.080746 | AL92: 0.081158 | AM92: 0.081569 | AN92: 0.082004 | AO92: 0.082363 | AP92: 0.082781 | AQ92: =IF(B92<>"", B92, AQ91) -> 4 West North Central
A93: =IFERROR(INDEX(NEMS_mapping!C$15:C$29,MATCH(C93,NEMS_mapping!B$15:B$29,0)),"") -> 0 | C93: 7 Refrigeration | D93: Capital Invest | E93: 2.621827 | F93: 2.68197 | G93: 2.693367 | H93: 2.713712 | I93: 2.751616 | J93: 2.798668 | K93: 2.781373 | L93: 2.809014 | M93: 2.785802 | N93: 2.649797 | O93: 2.706739 | P93: 2.757148 | Q93: 2.813187 | R93: 2.812079 | S93: 2.818271 | T93: 2.85605 | U93: 2.89697 | V93: 2.933836 | W93: 2.96835 | X93: 2.986285 | Y93: 2.991985 | Z93: 2.995502 | AA93: 2.996056 | AB93: 2.99568 | AC93: 2.99633 | AD93: 2.995878 | AE93: 2.995061 | AF93: 2.995151 | AG93: 2.999831 | AH93: 3.006298 | AI93: 3.014828 | AJ93: 3.024927 | AK93: 3.036285 | AL93: 3.048593 | AM93: 3.061386 | AN93: 3.074333 | AO93: 3.087171 | AP93: 3.099544 | AQ93: =IF(B93<>"", B93, AQ92) -> 4 West North Central
A94: =IFERROR(INDEX(NEMS_mapping!C$15:C$29,MATCH(C94,NEMS_mapping!B$15:B$29,0)),"") | D94: Tot Subsidy Inv | E94: 0 | F94: 0 | G94: 0 | H94: 0 | I94: 0 | J94: 0 | K94: 0 | L94: 0 | M94: 0 | N94: 0 | O94: 0 | P94: 0 | Q94: 0 | R94: 0 | S94: 0 | T94: 0 | U94: 0 | V94: 0 | W94: 0 | X94: 0 | Y94: 0 | Z94: 0 | AA94: 0 | AB94: 0 | AC94: 0 | AD94: 0 | AE94: 0 | AF94: 0 | AG94: 0 | AH94: 0 | AI94: 0 | AJ94: 0 | AK94: 0 | AL94: 0 | AM94: 0 | AN94: 0 | AO94: 0 | AP94: 0 | AQ94: =IF(B94<>"", B94, AQ93) -> 4 West North Central
A95: =IFERROR(INDEX(NEMS_mapping!C$15:C$29,MATCH(C95,NEMS_mapping!B$15:B$29,0)),"") -> appliances | C95: 7 Refrigeration Total | E95: 2.621827 | F95: 2.68197 | G95: 2.693367 | H95: 2.713712 | I95: 2.751616 | J95: 2.798668 | K95: 2.781373 | L95: 2.809014 | M95: 2.785802 | N95: 2.649797 | O95: 2.706739 | P95: 2.757148 | Q95: 2.813187 | R95: 2.812079 | S95: 2.818271 | T95: 2.85605 | U95: 2.89697 | V95: 2.933836 | W95: 2.96835 | X95: 2.986285 | Y95: 2.991985 | Z95: 2.995502 | AA95: 2.996056 | AB95: 2.99568 | AC95: 2.99633 | AD95: 2.995878 | AE95: 2.995061 | AF95: 2.995151 | AG95: 2.999831 | AH95: 3.006298 | AI95: 3.014828 | AJ95: 3.024927 | AK95: 3.036285 | AL95: 3.048593 | AM95: 3.061386 | AN95: 3.074333 | AO95: 3.087171 | AP95: 3.099544 | AQ95: =IF(B95<>"", B95, AQ94) -> 4 West North Central
A96: =IFERROR(INDEX(NEMS_mapping!C$15:C$29,MATCH(C96,NEMS_mapping!B$15:B$29,0)),"") | B96: 4 West North Central Total | E96: 4.785964 | F96: 4.601959 | G96: 4.65868 | H96: 4.66287 | I96: 4.696757 | J96: 4.533318 | K96: 4.469953 | L96: 4.486193 | M96: 4.419207 | N96: 4.244307 | O96: 4.282469 | P96: 4.330959 | Q96: 4.385368 | R96: 4.35557 | S96: 4.3347 | T96: 4.369731 | U96: 4.408842 | V96: 4.469522 | W96: 4.496316 | X96: 4.494151 | Y96: 4.470188 | Z96: 4.450167 | AA96: 4.426867 | AB96: 4.401821 | AC96: 4.382039 | AD96: 4.361537 | AE96: 4.341474 | AF96: 4.326804 | AG96: 4.316735 | AH96: 4.309873 | AI96: 4.306743 | AJ96: 4.306236 | AK96: 4.30827 | AL96: 4.312362 | AM96: 4.31678 | AN96: 4.322299 | AO96: 4.327632 | AP96: 4.32886 | AQ96: =IF(B96<>"", B96, AQ95) -> 4 West North Central Total
A97: =IFERROR(INDEX(NEMS_mapping!C$15:C$29,MATCH(C97,NEMS_mapping!B$15:B$29,0)),"") -> 0 | B97: 5 South Atlantic | C97: 1 Heating | D97: Capital Invest | E97: 1.973576 | F97: 1.948166 | G97: 1.940998 | H97: 1.93859 | I97: 1.9491 | J97: 1.641436 | K97: 1.619071 | L97: 1.560749 | M97: 1.534008 | N97: 1.501134 | O97: 1.433999 | P97: 1.39855 | Q97: 1.38954 | R97: 1.352807 | S97: 1.321932 | T97: 1.30667 | U97: 1.293292 | V97: 1.267972 | W97: 1.25073 | X97: 1.225597 | Y97: 1.255349 | Z97: 1.225457 | AA97: 1.195735 | AB97: 1.166955 | AC97: 1.13978 | AD97: 1.113425 | AE97: 1.087972 | AF97: 1.0638 | AG97: 1.041547 | AH97: 1.020473 | AI97: 1.000465 | AJ97: 0.98137 | AK97: 0.962984 | AL97: 0.944278 | AM97: 0.926846 | AN97: 0.906204 | AO97: 0.889244 | AP97: 0.865277 | AQ97: =IF(B97<>"", B97, AQ96) -> 5 South Atlantic
A98: =IFERROR(INDEX(NEMS_mapping!C$15:C$29,MATCH(C98,NEMS_mapping!B$15:B$29,0)),"") | D98: Tot Subsidy Inv | E98: 0.157867 | F98: 0.153943 | G98: 0.151653 | H98: 0.149575 | I98: 0.14989 | J98: 0.090179 | K98: 0.087493 | L98: 0.124182 | M98: 0.119729 | N98: 0.115324 | O98: 0.117313 | P98: 0.112687 | Q98: 0.109193 | R98: 0.104583 | S98: 0.1005 | T98: 0.097282 | U98: 0.094324 | V98: 0.090731 | W98: 0.08771 | X98: 0.084456 | Y98: 0.015033 | Z98: 0.014685 | AA98: 0.01431 | AB98: 0.013916 | AC98: 0.013567 | AD98: 0.013235 | AE98: 0.012913 | AF98: 0.012606 | AG98: 0.012321 | AH98: 0.01205 | AI98: 0.011763 | AJ98: 0.011504 | AK98: 0.011264 | AL98: 0.01098 | AM98: 0.010753 | AN98: 0.010331 | AO98: 0.01011 | AP98: 0.009486 | AQ98: =IF(B98<>"", B98, AQ97) -> 5 South Atlantic
A99: =IFERROR(INDEX(NEMS_mapping!C$15:C$29,MATCH(C99,NEMS_mapping!B$15:B$29,0)),"") -> heating | C99: 1 Heating Total | E99: 2.131443 | F99: 2.102109 | G99: 2.092651 | H99: 2.088165 | I99: 2.09899 | J99: 1.731615 | K99: 1.706564 | L99: 1.684931 | M99: 1.653737 | N99: 1.616458 | O99: 1.551312 | P99: 1.511237 | Q99: 1.498733 | R99: 1.45739 | S99: 1.422432 | T99: 1.403952 | U99: 1.387616 | V99: 1.358703 | W99: 1.33844 | X99: 1.310053 | Y99: 1.270382 | Z99: 1.240142 | AA99: 1.210045 | AB99: 1.180871 | AC99: 1.153347 | AD99: 1.12666 | AE99: 1.100885 | AF99: 1.076406 | AG99: 1.053868 | AH99: 1.032523 | AI99: 1.012228 | AJ99: 0.992874 | AK99: 0.974248 | AL99: 0.955258 | AM99: 0.937599 | AN99: 0.916535 | AO99: 0.899354 | AP99: 0.874763 | AQ99: =IF(B99<>"", B99, AQ98) -> 5 South Atlantic
A100: =IFERROR(INDEX(NEMS_mapping!C$15:C$29,MATCH(C100,NEMS_mapping!B$15:B$29,0)),"") -> 0 | C100: 2 Cooling | D100: Capital Invest | E100: 9.009157 | F100: 2.750783 | G100: 3.566782 | H100: 2.736471 | I100: 2.811116 | J100: 2.965207 | K100: 3.099661 | L100: 2.9852 | M100: 3.02804 | N100: 2.946592 | O100: 2.990443 | P100: 3.032672 | Q100: 3.040199 | R100: 3.004031 | S100: 2.979156 | T100: 3.006235 | U100: 3.036912 | V100: 3.063713 | W100: 3.081075 | X100: 3.071108 | Y100: 3.05591 | Z100: 3.031749 | AA100: 3.006183 | AB100: 2.979692 | AC100: 2.958746 | AD100: 2.937978 | AE100: 2.919029 | AF100: 2.914659 | AG100: 2.901031 | AH100: 2.893883 | AI100: 2.890038 | AJ100: 2.889838 | AK100: 2.891544 | AL100: 2.895376 | AM100: 2.898588 | AN100: 2.903833 | AO100: 2.907711 | AP100: 2.909498 | AQ100: =IF(B100<>"", B100, AQ99) -> 5 South Atlantic
A101: =IFERROR(INDEX(NEMS_mapping!C$15:C$29,MATCH(C101,NEMS_mapping!B$15:B$29,0)),"") | D101: Tot Subsidy Inv | E101: 0.14798 | F101: 0.145867 | G101: 0.16651 | H101: 0.147251 | I101: 0.150673 | J101: 0.146229 | K101: 0.158398 | L101: 0.155666 | M101: 0.151726 | N101: 0.14933 | O101: 0.035438 | P101: 0.040482 | Q101: 0.032104 | R101: 0.031824 | S101: 0.031703 | T101: 0.032063 | U101: 0.032527 | V101: 0.034152 | W101: 0.034416 | X101: 0.03356 | Y101: 0.01824 | Z101: 0.01838 | AA101: 0.018505 | AB101: 0.018619 | AC101: 0.01875 | AD101: 0.018864 | AE101: 0.018995 | AF101: 0.029508 | AG101: 0.027779 | AH101: 0.026706 | AI101: 0.026739 | AJ101: 0.026742 | AK101: 0.027156 | AL101: 0.027329 | AM101: 0.027678 | AN101: 0.028153 | AO101: 0.027631 | AP101: 0.026437 | AQ101: =IF(B101<>"", B101, AQ100) -> 5 South Atlantic
A102: =IFERROR(INDEX(NEMS_mapping!C$15:C$29,MATCH(C102,NEMS_mapping!B$15:B$29,0)),"") -> cooling and ventilation | C102: 2 Cooling Total | E102: 9.157137 | F102: 2.89665 | G102: 3.733292 | H102: 2.883722 | I102: 2.961789 | J102: 3.111436 | K102: 3.258059 | L102: 3.140866 | M102: 3.179766 | N102: 3.095922 | O102: 3.025881 | P102: 3.073154 | Q102: 3.072303 | R102: 3.035855 | S102: 3.010859 | T102: 3.038298 | U102: 3.069439 | V102: 3.097865 | W102: 3.115491 | X102: 3.104668 | Y102: 3.07415 | Z102: 3.050129 | AA102: 3.024688 | AB102: 2.998311 | AC102: 2.977496 | AD102: 2.956842 | AE102: 2.938024 | AF102: 2.944167 | AG102: 2.92881 | AH102: 2.920589 | AI102: 2.916777 | AJ102: 2.91658 | AK102: 2.9187 | AL102: 2.922705 | AM102: 2.926266 | AN102: 2.931986 | AO102: 2.935342 | AP102: 2.935935 | AQ102: =IF(B102<>"", B102, AQ101) -> 5 South Atlantic
A103: =IFERROR(INDEX(NEMS_mapping!C$15:C$29,MATCH(C103,NEMS_mapping!B$15:B$29,0)),"") -> 0 | C103: 3 Water Heating | D103: Capital Invest | E103: 0.157536 | F103: 0.159415 | G103: 0.162504 | H103: 0.164993 | I103: 0.167196 | J103: 0.168576 | K103: 0.172386 | L103: 0.17513 | M103: 0.175893 | N103: 0.174915 | O103: 0.172889 | P103: 0.176065 | Q103: 0.180218 | R103: 0.180375 | S103: 0.187573 | T103: 0.190665 | U103: 0.193941 | V103: 0.196893 | W103: 0.199569 | X103: 0.201033 | Y103: 0.201623 | Z103: 0.202056 | AA103: 0.202286 | AB103: 0.202463 | AC103: 0.202724 | AD103: 0.202914 | AE103: 0.203087 | AF103: 0.203341 | AG103: 0.203855 | AH103: 0.2045 | AI103: 0.205296 | AJ103: 0.206206 | AK103: 0.207213 | AL103: 0.20828 | AM103: 0.209382 | AN103: 0.210486 | AO103: 0.211588 | AP103: 0.212652 | AQ103: =IF(B103<>"", B103, AQ102) -> 5 South Atlantic
...

Sheet NEMS_mapping
B2: residential
B3: Cooking | C3: appliances
B4: Cooling | C4: cooling and ventilation
B5: Clothes Washing | C5: appliances
B6: Clothes Drying | C6: appliances
B7: Dishwashing | C7: appliances
B8: Freezing | C8: appliances
B9: Refrigeration | C9: appliances
B10: Heating | C10: heating
B11: Water Heating | C11: appliances
B12: Lighting | C12: lighting
B14: commercial
B15: 1 Heating
B16: 1 Heating Total | C16: heating
B17: 2 Cooling
B18: 2 Cooling Total | C18: cooling and ventilation
B19: 3 Water Heating
B20: 3 Water Heating Total | C20: appliances
B21: 4 Ventilation
B22: 4 Ventilation Total | C22: appliances
B23: 5 Cooking
B24: 5 Cooking Total | C24: appliances
B25: 6 Lighting
B26: 6 Lighting Total | C26: lighting
B27: 7 Refrigeration
B28: 7 Refrigeration Total | C28: appliances

Sheet NEMS_residential_agg
A1: NEMS Residential capex by division x component x year
A2: Aggregated from NEMS_residential via SUMIFS. Values in 2017 USD (source NEMS units); converted to 2012 USD in Calcs.
A4: nems_div_num | B4: nems_div_label | C4: component | D4: 2024 | E4: 2025 | F4: 2026 | G4: 2027 | H4: 2028 | I4: 2029 | J4: 2030 | K4: 2031 | L4: 2032 | M4: 2033 | N4: 2034 | O4: 2035 | P4: 2036 | Q4: 2037 | R4: 2038 | S4: 2039 | T4: 2040 | U4: 2041 | V4: 2042 | W4: 2043 | X4: 2044 | Y4: 2045 | Z4: 2046 | AA4: 2047 | AB4: 2048 | AC4: 2049 | AD4: 2050
A5: 1 | B5: 1 New England | C5: heating | D5: =SUMIFS(NEMS_residential!P7:P9972, NEMS_residential!$A$7:$A$9972, Keys!$C$5, NEMS_residential!$DH$7:$DH$9972, Keys!$C$11, NEMS_residential!$G$7:$G$9972, Keys!$C$4) -> 754556322 | E5: =SUMIFS(NEMS_residential!Q7:Q9972, NEMS_residential!$A$7:$A$9972, Keys!$C$5, NEMS_residential!$DH$7:$DH$9972, Keys!$C$11, NEMS_residential!$G$7:$G$9972, Keys!$C$4) -> 761969011 | F5: =SUMIFS(NEMS_residential!R7:R9972, NEMS_residential!$A$7:$A$9972, Keys!$C$5, NEMS_residential!$DH$7:$DH$9972, Keys!$C$11, NEMS_residential!$G$7:$G$9972, Keys!$C$4) -> 767777496 | G5: =SUMIFS(NEMS_residential!S7:S9972, NEMS_residential!$A$7:$A$9972, Keys!$C$5, NEMS_residential!$DH$7:$DH$9972, Keys!$C$11, NEMS_residential!$G$7:$G$9972, Keys!$C$4) -> 755938545 | H5: =SUMIFS(NEMS_residential!T7:T9972, NEMS_residential!$A$7:$A$9972, Keys!$C$5, NEMS_residential!$DH$7:$DH$9972, Keys!$C$11, NEMS_residential!$G$7:$G$9972, Keys!$C$4) -> 742797786 | I5: =SUMIFS(NEMS_residential!U7:U9972, NEMS_residential!$A$7:$A$9972, Keys!$C$5, NEMS_residential!$DH$7:$DH$9972, Keys!$C$11, NEMS_residential!$G$7:$G$9972, Keys!$C$4) -> 724547764 | J5: =SUMIFS(NEMS_residential!V7:V9972, NEMS_residential!$A$7:$A$9972, Keys!$C$5, NEMS_residential!$DH$7:$DH$9972, Keys!$C$11, NEMS_residential!$G$7:$G$9972, Keys!$C$4) -> 710586870 | K5: =SUMIFS(NEMS_residential!W7:W9972, NEMS_residential!$A$7:$A$9972, Keys!$C$5, NEMS_residential!$DH$7:$DH$9972, Keys!$C$11, NEMS_residential!$G$7:$G$9972, Keys!$C$4) -> 705970707 | ... AD5: =SUMIFS(NEMS_residential!AP7:AP9972, NEMS_residential!$A$7:$A$9972, Keys!$C$5, NEMS_residential!$DH$7:$DH$9972, Keys!$C$11, NEMS_residential!$G$7:$G$9972, Keys!$C$4) -> 797772936
A6: 1 | B6: 1 New England | C6: cooling and ventilation | D6: =SUMIFS(NEMS_residential!P7:P9972, NEMS_residential!$A$7:$A$9972, Keys!$C$6, NEMS_residential!$DH$7:$DH$9972, Keys!$C$11, NEMS_residential!$G$7:$G$9972, Keys!$C$4) -> 710903771 | E6: =SUMIFS(NEMS_residential!Q7:Q9972, NEMS_residential!$A$7:$A$9972, Keys!$C$6, NEMS_residential!$DH$7:$DH$9972, Keys!$C$11, NEMS_residential!$G$7:$G$9972, Keys!$C$4) -> 709517312 | F6: =SUMIFS(NEMS_residential!R7:R9972, NEMS_residential!$A$7:$A$9972, Keys!$C$6, NEMS_residential!$DH$7:$DH$9972, Keys!$C$11, NEMS_residential!$G$7:$G$9972, Keys!$C$4) -> 700371752 | G6: =SUMIFS(NEMS_residential!S7:S9972, NEMS_residential!$A$7:$A$9972, Keys!$C$6, NEMS_residential!$DH$7:$DH$9972, Keys!$C$11, NEMS_residential!$G$7:$G$9972, Keys!$C$4) -> 693874456 | H6: =SUMIFS(NEMS_residential!T7:T9972, NEMS_residential!$A$7:$A$9972, Keys!$C$6, NEMS_residential!$DH$7:$DH$9972, Keys!$C$11, NEMS_residential!$G$7:$G$9972, Keys!$C$4) -> 692877544 | I6: =SUMIFS(NEMS_residential!U7:U9972, NEMS_residential!$A$7:$A$9972, Keys!$C$6, NEMS_residential!$DH$7:$DH$9972, Keys!$C$11, NEMS_residential!$G$7:$G$9972, Keys!$C$4) -> 691060217 | J6: =SUMIFS(NEMS_residential!V7:V9972, NEMS_residential!$A$7:$A$9972, Keys!$C$6, NEMS_residential!$DH$7:$DH$9972, Keys!$C$11, NEMS_residential!$G$7:$G$9972, Keys!$C$4) -> 681500804 | K6: =SUMIFS(NEMS_residential!W7:W9972, NEMS_residential!$A$7:$A$9972, Keys!$C$6, NEMS_residential!$DH$7:$DH$9972, Keys!$C$11, NEMS_residential!$G$7:$G$9972, Keys!$C$4) -> 664444180 | ... AD6: =SUMIFS(NEMS_residential!AP7:AP9972, NEMS_residential!$A$7:$A$9972, Keys!$C$6, NEMS_residential!$DH$7:$DH$9972, Keys!$C$11, NEMS_residential!$G$7:$G$9972, Keys!$C$4) -> 837625719
A7: 1 | B7: 1 New England | C7: lighting | D7: =SUMIFS(NEMS_residential!P7:P9972, NEMS_residential!$A$7:$A$9972, Keys!$C$7, NEMS_residential!$DH$7:$DH$9972, Keys!$C$11, NEMS_residential!$G$7:$G$9972, Keys!$C$4) -> 78422579 | E7: =SUMIFS(NEMS_residential!Q7:Q9972, NEMS_residential!$A$7:$A$9972, Keys!$C$7, NEMS_residential!$DH$7:$DH$9972, Keys!$C$11, NEMS_residential!$G$7:$G$9972, Keys!$C$4) -> 73301047 | F7: =SUMIFS(NEMS_residential!R7:R9972, NEMS_residential!$A$7:$A$9972, Keys!$C$7, NEMS_residential!$DH$7:$DH$9972, Keys!$C$11, NEMS_residential!$G$7:$G$9972, Keys!$C$4) -> 71118008 | G7: =SUMIFS(NEMS_residential!S7:S9972, NEMS_residential!$A$7:$A$9972, Keys!$C$7, NEMS_residential!$DH$7:$DH$9972, Keys!$C$11, NEMS_residential!$G$7:$G$9972, Keys!$C$4) -> 67374176 | H7: =SUMIFS(NEMS_residential!T7:T9972, NEMS_residential!$A$7:$A$9972, Keys!$C$7, NEMS_residential!$DH$7:$DH$9972, Keys!$C$11, NEMS_residential!$G$7:$G$9972, Keys!$C$4) -> 63704246 | I7: =SUMIFS(NEMS_residential!U7:U9972, NEMS_residential!$A$7:$A$9972, Keys!$C$7, NEMS_residential!$DH$7:$DH$9972, Keys!$C$11, NEMS_residential!$G$7:$G$9972, Keys!$C$4) -> 63771116 | J7: =SUMIFS(NEMS_residential!V7:V9972, NEMS_residential!$A$7:$A$9972, Keys!$C$7, NEMS_residential!$DH$7:$DH$9972, Keys!$C$11, NEMS_residential!$G$7:$G$9972, Keys!$C$4) -> 47686231 | K7: =SUMIFS(NEMS_residential!W7:W9972, NEMS_residential!$A$7:$A$9972, Keys!$C$7, NEMS_residential!$DH$7:$DH$9972, Keys!$C$11, NEMS_residential!$G$7:$G$9972, Keys!$C$4) -> 48713064 | ... AD7: =SUMIFS(NEMS_residential!AP7:AP9972, NEMS_residential!$A$7:$A$9972, Keys!$C$7, NEMS_residential!$DH$7:$DH$9972, Keys!$C$11, NEMS_residential!$G$7:$G$9972, Keys!$C$4) -> 59549554
A8: 1 | B8: 1 New England | C8: appliances | D8: =SUMIFS(NEMS_residential!P7:P9972, NEMS_residential!$A$7:$A$9972, Keys!$C$8, NEMS_residential!$DH$7:$DH$9972, Keys!$C$11, NEMS_residential!$G$7:$G$9972, Keys!$C$4) -> 2017008274 | E8: =SUMIFS(NEMS_residential!Q7:Q9972, NEMS_residential!$A$7:$A$9972, Keys!$C$8, NEMS_residential!$DH$7:$DH$9972, Keys!$C$11, NEMS_residential!$G$7:$G$9972, Keys!$C$4) -> 2023788592 | F8: =SUMIFS(NEMS_residential!R7:R9972, NEMS_residential!$A$7:$A$9972, Keys!$C$8, NEMS_residential!$DH$7:$DH$9972, Keys!$C$11, NEMS_residential!$G$7:$G$9972, Keys!$C$4) -> 2049958722 | G8: =SUMIFS(NEMS_residential!S7:S9972, NEMS_residential!$A$7:$A$9972, Keys!$C$8, NEMS_residential!$DH$7:$DH$9972, Keys!$C$11, NEMS_residential!$G$7:$G$9972, Keys!$C$4) -> 2085180974 | H8: =SUMIFS(NEMS_residential!T7:T9972, NEMS_residential!$A$7:$A$9972, Keys!$C$8, NEMS_residential!$DH$7:$DH$9972, Keys!$C$11, NEMS_residential!$G$7:$G$9972, Keys!$C$4) -> 2064650776 | I8: =SUMIFS(NEMS_residential!U7:U9972, NEMS_residential!$A$7:$A$9972, Keys!$C$8, NEMS_residential!$DH$7:$DH$9972, Keys!$C$11, NEMS_residential!$G$7:$G$9972, Keys!$C$4) -> 2066137038 | J8: =SUMIFS(NEMS_residential!V7:V9972, NEMS_residential!$A$7:$A$9972, Keys!$C$8, NEMS_residential!$DH$7:$DH$9972, Keys!$C$11, NEMS_residential!$G$7:$G$9972, Keys!$C$4) -> 2071236714 | K8: =SUMIFS(NEMS_residential!W7:W9972, NEMS_residential!$A$7:$A$9972, Keys!$C$8, NEMS_residential!$DH$7:$DH$9972, Keys!$C$11, NEMS_residential!$G$7:$G$9972, Keys!$C$4) -> 2143473002 | ... AD8: =SUMIFS(NEMS_residential!AP7:AP9972, NEMS_residential!$A$7:$A$9972, Keys!$C$8, NEMS_residential!$DH$7:$DH$9972, Keys!$C$11, NEMS_residential!$G$7:$G$9972, Keys!$C$4) -> 1945158757
A9: 2 | B9: 2 Middle Atlantic | C9: heating | D9: =SUMIFS(NEMS_residential!P7:P9972, NEMS_residential!$A$7:$A$9972, Keys!$C$5, NEMS_residential!$DH$7:$DH$9972, Keys!$C$12, NEMS_residential!$G$7:$G$9972, Keys!$C$4) -> 1782975314 | E9: =SUMIFS(NEMS_residential!Q7:Q9972, NEMS_residential!$A$7:$A$9972, Keys!$C$5, NEMS_residential!$DH$7:$DH$9972, Keys!$C$12, NEMS_residential!$G$7:$G$9972, Keys!$C$4) -> 1806853852 | F9: =SUMIFS(NEMS_residential!R7:R9972, NEMS_residential!$A$7:$A$9972, Keys!$C$5, NEMS_residential!$DH$7:$DH$9972, Keys!$C$12, NEMS_residential!$G$7:$G$9972, Keys!$C$4) -> 1820524965 | G9: =SUMIFS(NEMS_residential!S7:S9972, NEMS_residential!$A$7:$A$9972, Keys!$C$5, NEMS_residential!$DH$7:$DH$9972, Keys!$C$12, NEMS_residential!$G$7:$G$9972, Keys!$C$4) -> 1791107935 | H9: =SUMIFS(NEMS_residential!T7:T9972, NEMS_residential!$A$7:$A$9972, Keys!$C$5, NEMS_residential!$DH$7:$DH$9972, Keys!$C$12, NEMS_residential!$G$7:$G$9972, Keys!$C$4) -> 1766582991 | I9: =SUMIFS(NEMS_residential!U7:U9972, NEMS_residential!$A$7:$A$9972, Keys!$C$5, NEMS_residential!$DH$7:$DH$9972, Keys!$C$12, NEMS_residential!$G$7:$G$9972, Keys!$C$4) -> 1732218542 | J9: =SUMIFS(NEMS_residential!V7:V9972, NEMS_residential!$A$7:$A$9972, Keys!$C$5, NEMS_residential!$DH$7:$DH$9972, Keys!$C$12, NEMS_residential!$G$7:$G$9972, Keys!$C$4) -> 1710753264 | K9: =SUMIFS(NEMS_residential!W7:W9972, NEMS_residential!$A$7:$A$9972, Keys!$C$5, NEMS_residential!$DH$7:$DH$9972, Keys!$C$12, NEMS_residential!$G$7:$G$9972, Keys!$C$4) -> 1710388620 | ... AD9: =SUMIFS(NEMS_residential!AP7:AP9972, NEMS_residential!$A$7:$A$9972, Keys!$C$5, NEMS_residential!$DH$7:$DH$9972, Keys!$C$12, NEMS_residential!$G$7:$G$9972, Keys!$C$4) -> 1743352771
A10: 2 | B10: 2 Middle Atlantic | C10: cooling and ventilation | D10: =SUMIFS(NEMS_residential!P7:P9972, NEMS_residential!$A$7:$A$9972, Keys!$C$6, NEMS_residential!$DH$7:$DH$9972, Keys!$C$12, NEMS_residential!$G$7:$G$9972, Keys!$C$4) -> 2391906134 | E10: =SUMIFS(NEMS_residential!Q7:Q9972, NEMS_residential!$A$7:$A$9972, Keys!$C$6, NEMS_residential!$DH$7:$DH$9972, Keys!$C$12, NEMS_residential!$G$7:$G$9972, Keys!$C$4) -> 2375338832 | F10: =SUMIFS(NEMS_residential!R7:R9972, NEMS_residential!$A$7:$A$9972, Keys!$C$6, NEMS_residential!$DH$7:$DH$9972, Keys!$C$12, NEMS_residential!$G$7:$G$9972, Keys!$C$4) -> 2333218998 | G10: =SUMIFS(NEMS_residential!S7:S9972, NEMS_residential!$A$7:$A$9972, Keys!$C$6, NEMS_residential!$DH$7:$DH$9972, Keys!$C$12, NEMS_residential!$G$7:$G$9972, Keys!$C$4) -> 2298911215 | H10: =SUMIFS(NEMS_residential!T7:T9972, NEMS_residential!$A$7:$A$9972, Keys!$C$6, NEMS_residential!$DH$7:$DH$9972, Keys!$C$12, NEMS_residential!$G$7:$G$9972, Keys!$C$4) -> 2281037918 | I10: =SUMIFS(NEMS_residential!U7:U9972, NEMS_residential!$A$7:$A$9972, Keys!$C$6, NEMS_residential!$DH$7:$DH$9972, Keys!$C$12, NEMS_residential!$G$7:$G$9972, Keys!$C$4) -> 2262244583 | J10: =SUMIFS(NEMS_residential!V7:V9972, NEMS_residential!$A$7:$A$9972, Keys!$C$6, NEMS_residential!$DH$7:$DH$9972, Keys!$C$12, NEMS_residential!$G$7:$G$9972, Keys!$C$4) -> 2217399155 | K10: =SUMIFS(NEMS_residential!W7:W9972, NEMS_residential!$A$7:$A$9972, Keys!$C$6, NEMS_residential!$DH$7:$DH$9972, Keys!$C$12, NEMS_residential!$G$7:$G$9972, Keys!$C$4) -> 2148970420 | ... AD10: =SUMIFS(NEMS_residential!AP7:AP9972, NEMS_residential!$A$7:$A$9972, Keys!$C$6, NEMS_residential!$DH$7:$DH$9972, Keys!$C$12, NEMS_residential!$G$7:$G$9972, Keys!$C$4) -> 2572381200
A11: 2 | B11: 2 Middle Atlantic | C11: lighting | D11: =SUMIFS(NEMS_residential!P7:P9972, NEMS_residential!$A$7:$A$9972, Keys!$C$7, NEMS_residential!$DH$7:$DH$9972, Keys!$C$12, NEMS_residential!$G$7:$G$9972, Keys!$C$4) -> 198265507 | E11: =SUMIFS(NEMS_residential!Q7:Q9972, NEMS_residential!$A$7:$A$9972, Keys!$C$7, NEMS_residential!$DH$7:$DH$9972, Keys!$C$12, NEMS_residential!$G$7:$G$9972, Keys!$C$4) -> 184103196 | F11: =SUMIFS(NEMS_residential!R7:R9972, NEMS_residential!$A$7:$A$9972, Keys!$C$7, NEMS_residential!$DH$7:$DH$9972, Keys!$C$12, NEMS_residential!$G$7:$G$9972, Keys!$C$4) -> 178046728 | G11: =SUMIFS(NEMS_residential!S7:S9972, NEMS_residential!$A$7:$A$9972, Keys!$C$7, NEMS_residential!$DH$7:$DH$9972, Keys!$C$12, NEMS_residential!$G$7:$G$9972, Keys!$C$4) -> 168138330 | H11: =SUMIFS(NEMS_residential!T7:T9972, NEMS_residential!$A$7:$A$9972, Keys!$C$7, NEMS_residential!$DH$7:$DH$9972, Keys!$C$12, NEMS_residential!$G$7:$G$9972, Keys!$C$4) -> 159221568 | I11: =SUMIFS(NEMS_residential!U7:U9972, NEMS_residential!$A$7:$A$9972, Keys!$C$7, NEMS_residential!$DH$7:$DH$9972, Keys!$C$12, NEMS_residential!$G$7:$G$9972, Keys!$C$4) -> 159768334 | J11: =SUMIFS(NEMS_residential!V7:V9972, NEMS_residential!$A$7:$A$9972, Keys!$C$7, NEMS_residential!$DH$7:$DH$9972, Keys!$C$12, NEMS_residential!$G$7:$G$9972, Keys!$C$4) -> 119556660 | K11: =SUMIFS(NEMS_residential!W7:W9972, NEMS_residential!$A$7:$A$9972, Keys!$C$7, NEMS_residential!$DH$7:$DH$9972, Keys!$C$12, NEMS_residential!$G$7:$G$9972, Keys!$C$4) -> 122229151 | ... AD11: =SUMIFS(NEMS_residential!AP7:AP9972, NEMS_residential!$A$7:$A$9972, Keys!$C$7, NEMS_residential!$DH$7:$DH$9972, Keys!$C$12, NEMS_residential!$G$7:$G$9972, Keys!$C$4) -> 148545545
A12: 2 | B12: 2 Middle Atlantic | C12: appliances | D12: =SUMIFS(NEMS_residential!P7:P9972, NEMS_residential!$A$7:$A$9972, Keys!$C$8, NEMS_residential!$DH$7:$DH$9972, Keys!$C$12, NEMS_residential!$G$7:$G$9972, Keys!$C$4) -> 4501782798 | E12: =SUMIFS(NEMS_residential!Q7:Q9972, NEMS_residential!$A$7:$A$9972, Keys!$C$8, NEMS_residential!$DH$7:$DH$9972, Keys!$C$12, NEMS_residential!$G$7:$G$9972, Keys!$C$4) -> 4543820298 | F12: =SUMIFS(NEMS_residential!R7:R9972, NEMS_residential!$A$7:$A$9972, Keys!$C$8, NEMS_residential!$DH$7:$DH$9972, Keys!$C$12, NEMS_residential!$G$7:$G$9972, Keys!$C$4) -> 4625646575 | G12: =SUMIFS(NEMS_residential!S7:S9972, NEMS_residential!$A$7:$A$9972, Keys!$C$8, NEMS_residential!$DH$7:$DH$9972, Keys!$C$12, NEMS_residential!$G$7:$G$9972, Keys!$C$4) -> 4746452021 | H12: =SUMIFS(NEMS_residential!T7:T9972, NEMS_residential!$A$7:$A$9972, Keys!$C$8, NEMS_residential!$DH$7:$DH$9972, Keys!$C$12, NEMS_residential!$G$7:$G$9972, Keys!$C$4) -> 4705980412 | I12: =SUMIFS(NEMS_residential!U7:U9972, NEMS_residential!$A$7:$A$9972, Keys!$C$8, NEMS_residential!$DH$7:$DH$9972, Keys!$C$12, NEMS_residential!$G$7:$G$9972, Keys!$C$4) -> 4717518621 | J12: =SUMIFS(NEMS_residential!V7:V9972, NEMS_residential!$A$7:$A$9972, Keys!$C$8, NEMS_residential!$DH$7:$DH$9972, Keys!$C$12, NEMS_residential!$G$7:$G$9972, Keys!$C$4) -> 4746096084 | K12: =SUMIFS(NEMS_residential!W7:W9972, NEMS_residential!$A$7:$A$9972, Keys!$C$8, NEMS_residential!$DH$7:$DH$9972, Keys!$C$12, NEMS_residential!$G$7:$G$9972, Keys!$C$4) -> 4885723611 | ... AD12: =SUMIFS(NEMS_residential!AP7:AP9972, NEMS_residential!$A$7:$A$9972, Keys!$C$8, NEMS_residential!$DH$7:$DH$9972, Keys!$C$12, NEMS_residential!$G$7:$G$9972, Keys!$C$4) -> 4973456067
A13: 3 | B13: 3 East North Central | C13: heating | D13: =SUMIFS(NEMS_residential!P7:P9972, NEMS_residential!$A$7:$A$9972, Keys!$C$5, NEMS_residential!$DH$7:$DH$9972, Keys!$C$13, NEMS_residential!$G$7:$G$9972, Keys!$C$4) -> 1599404000 | E13: =SUMIFS(NEMS_residential!Q7:Q9972, NEMS_residential!$A$7:$A$9972, Keys!$C$5, NEMS_residential!$DH$7:$DH$9972, Keys!$C$13, NEMS_residential!$G$7:$G$9972, Keys!$C$4) -> 1631112641 | F13: =SUMIFS(NEMS_residential!R7:R9972, NEMS_residential!$A$7:$A$9972, Keys!$C$5, NEMS_residential!$DH$7:$DH$9972, Keys!$C$13, NEMS_residential!$G$7:$G$9972, Keys!$C$4) -> 1664950106 | G13: =SUMIFS(NEMS_residential!S7:S9972, NEMS_residential!$A$7:$A$9972, Keys!$C$5, NEMS_residential!$DH$7:$DH$9972, Keys!$C$13, NEMS_residential!$G$7:$G$9972, Keys!$C$4) -> 1613416903 | H13: =SUMIFS(NEMS_residential!T7:T9972, NEMS_residential!$A$7:$A$9972, Keys!$C$5, NEMS_residential!$DH$7:$DH$9972, Keys!$C$13, NEMS_residential!$G$7:$G$9972, Keys!$C$4) -> 1568093872 | I13: =SUMIFS(NEMS_residential!U7:U9972, NEMS_residential!$A$7:$A$9972, Keys!$C$5, NEMS_residential!$DH$7:$DH$9972, Keys!$C$13, NEMS_residential!$G$7:$G$9972, Keys!$C$4) -> 1515823179 | J13: =SUMIFS(NEMS_residential!V7:V9972, NEMS_residential!$A$7:$A$9972, Keys!$C$5, NEMS_residential!$DH$7:$DH$9972, Keys!$C$13, NEMS_residential!$G$7:$G$9972, Keys!$C$4) -> 1464863231 | K13: =SUMIFS(NEMS_residential!W7:W9972, NEMS_residential!$A$7:$A$9972, Keys!$C$5, NEMS_residential!$DH$7:$DH$9972, Keys!$C$13, NEMS_residential!$G$7:$G$9972, Keys!$C$4) -> 1430132629 | ... AD13: =SUMIFS(NEMS_residential!AP7:AP9972, NEMS_residential!$A$7:$A$9972, Keys!$C$5, NEMS_residential!$DH$7:$DH$9972, Keys!$C$13, NEMS_residential!$G$7:$G$9972, Keys!$C$4) -> 1502799882
A14: 3 | B14: 3 East North Central | C14: cooling and ventilation | D14: =SUMIFS(NEMS_residential!P7:P9972, NEMS_residential!$A$7:$A$9972, Keys!$C$6, NEMS_residential!$DH$7:$DH$9972, Keys!$C$13, NEMS_residential!$G$7:$G$9972, Keys!$C$4) -> 3223748330 | E14: =SUMIFS(NEMS_residential!Q7:Q9972, NEMS_residential!$A$7:$A$9972, Keys!$C$6, NEMS_residential!$DH$7:$DH$9972, Keys!$C$13, NEMS_residential!$G$7:$G$9972, Keys!$C$4) -> 3158597029 | F14: =SUMIFS(NEMS_residential!R7:R9972, NEMS_residential!$A$7:$A$9972, Keys!$C$6, NEMS_residential!$DH$7:$DH$9972, Keys!$C$13, NEMS_residential!$G$7:$G$9972, Keys!$C$4) -> 3070267396 | G14: =SUMIFS(NEMS_residential!S7:S9972, NEMS_residential!$A$7:$A$9972, Keys!$C$6, NEMS_residential!$DH$7:$DH$9972, Keys!$C$13, NEMS_residential!$G$7:$G$9972, Keys!$C$4) -> 2991889720 | H14: =SUMIFS(NEMS_residential!T7:T9972, NEMS_residential!$A$7:$A$9972, Keys!$C$6, NEMS_residential!$DH$7:$DH$9972, Keys!$C$13, NEMS_residential!$G$7:$G$9972, Keys!$C$4) -> 2923664270 | I14: =SUMIFS(NEMS_residential!U7:U9972, NEMS_residential!$A$7:$A$9972, Keys!$C$6, NEMS_residential!$DH$7:$DH$9972, Keys!$C$13, NEMS_residential!$G$7:$G$9972, Keys!$C$4) -> 2878801868 | J14: =SUMIFS(NEMS_residential!V7:V9972, NEMS_residential!$A$7:$A$9972, Keys!$C$6, NEMS_residential!$DH$7:$DH$9972, Keys!$C$13, NEMS_residential!$G$7:$G$9972, Keys!$C$4) -> 2812776580 | K14: =SUMIFS(NEMS_residential!W7:W9972, NEMS_residential!$A$7:$A$9972, Keys!$C$6, NEMS_residential!$DH$7:$DH$9972, Keys!$C$13, NEMS_residential!$G$7:$G$9972, Keys!$C$4) -> 2738621485 | ... AD14: =SUMIFS(NEMS_residential!AP7:AP9972, NEMS_residential!$A$7:$A$9972, Keys!$C$6, NEMS_residential!$DH$7:$DH$9972, Keys!$C$13, NEMS_residential!$G$7:$G$9972, Keys!$C$4) -> 3043996103
A15: 3 | B15: 3 East North Central | C15: lighting | D15: =SUMIFS(NEMS_residential!P7:P9972, NEMS_residential!$A$7:$A$9972, Keys!$C$7, NEMS_residential!$DH$7:$DH$9972, Keys!$C$13, NEMS_residential!$G$7:$G$9972, Keys!$C$4) -> 259507038 | E15: =SUMIFS(NEMS_residential!Q7:Q9972, NEMS_residential!$A$7:$A$9972, Keys!$C$7, NEMS_residential!$DH$7:$DH$9972, Keys!$C$13, NEMS_residential!$G$7:$G$9972, Keys!$C$4) -> 240142764 | F15: =SUMIFS(NEMS_residential!R7:R9972, NEMS_residential!$A$7:$A$9972, Keys!$C$7, NEMS_residential!$DH$7:$DH$9972, Keys!$C$13, NEMS_residential!$G$7:$G$9972, Keys!$C$4) -> 229974443 | G15: =SUMIFS(NEMS_residential!S7:S9972, NEMS_residential!$A$7:$A$9972, Keys!$C$7, NEMS_residential!$DH$7:$DH$9972, Keys!$C$13, NEMS_residential!$G$7:$G$9972, Keys!$C$4) -> 216452184 | H15: =SUMIFS(NEMS_residential!T7:T9972, NEMS_residential!$A$7:$A$9972, Keys!$C$7, NEMS_residential!$DH$7:$DH$9972, Keys!$C$13, NEMS_residential!$G$7:$G$9972, Keys!$C$4) -> 206100887 | I15: =SUMIFS(NEMS_residential!U7:U9972, NEMS_residential!$A$7:$A$9972, Keys!$C$7, NEMS_residential!$DH$7:$DH$9972, Keys!$C$13, NEMS_residential!$G$7:$G$9972, Keys!$C$4) -> 207530304 | J15: =SUMIFS(NEMS_residential!V7:V9972, NEMS_residential!$A$7:$A$9972, Keys!$C$7, NEMS_residential!$DH$7:$DH$9972, Keys!$C$13, NEMS_residential!$G$7:$G$9972, Keys!$C$4) -> 155407463 | K15: =SUMIFS(NEMS_residential!W7:W9972, NEMS_residential!$A$7:$A$9972, Keys!$C$7, NEMS_residential!$DH$7:$DH$9972, Keys!$C$13, NEMS_residential!$G$7:$G$9972, Keys!$C$4) -> 158905033 | ... AD15: =SUMIFS(NEMS_residential!AP7:AP9972, NEMS_residential!$A$7:$A$9972, Keys!$C$7, NEMS_residential!$DH$7:$DH$9972, Keys!$C$13, NEMS_residential!$G$7:$G$9972, Keys!$C$4) -> 194135837
A16: 3 | B16: 3 East North Central | C16: appliances | D16: =SUMIFS(NEMS_residential!P7:P9972, NEMS_residential!$A$7:$A$9972, Keys!$C$8, NEMS_residential!$DH$7:$DH$9972, Keys!$C$13, NEMS_residential!$G$7:$G$9972, Keys!$C$4) -> 5188369051 | E16: =SUMIFS(NEMS_residential!Q7:Q9972, NEMS_residential!$A$7:$A$9972, Keys!$C$8, NEMS_residential!$DH$7:$DH$9972, Keys!$C$13, NEMS_residential!$G$7:$G$9972, Keys!$C$4) -> 5273425507 | F16: =SUMIFS(NEMS_residential!R7:R9972, NEMS_residential!$A$7:$A$9972, Keys!$C$8, NEMS_residential!$DH$7:$DH$9972, Keys!$C$13, NEMS_residential!$G$7:$G$9972, Keys!$C$4) -> 5392549515 | G16: =SUMIFS(NEMS_residential!S7:S9972, NEMS_residential!$A$7:$A$9972, Keys!$C$8, NEMS_residential!$DH$7:$DH$9972, Keys!$C$13, NEMS_residential!$G$7:$G$9972, Keys!$C$4) -> 5551997197 | H16: =SUMIFS(NEMS_residential!T7:T9972, NEMS_residential!$A$7:$A$9972, Keys!$C$8, NEMS_residential!$DH$7:$DH$9972, Keys!$C$13, NEMS_residential!$G$7:$G$9972, Keys!$C$4) -> 5498091005 | I16: =SUMIFS(NEMS_residential!U7:U9972, NEMS_residential!$A$7:$A$9972, Keys!$C$8, NEMS_residential!$DH$7:$DH$9972, Keys!$C$13, NEMS_residential!$G$7:$G$9972, Keys!$C$4) -> 5511497000 | J16: =SUMIFS(NEMS_residential!V7:V9972, NEMS_residential!$A$7:$A$9972, Keys!$C$8, NEMS_residential!$DH$7:$DH$9972, Keys!$C$13, NEMS_residential!$G$7:$G$9972, Keys!$C$4) -> 5545186788 | K16: =SUMIFS(NEMS_residential!W7:W9972, NEMS_residential!$A$7:$A$9972, Keys!$C$8, NEMS_residential!$DH$7:$DH$9972, Keys!$C$13, NEMS_residential!$G$7:$G$9972, Keys!$C$4) -> 5691468420 | ... AD16: =SUMIFS(NEMS_residential!AP7:AP9972, NEMS_residential!$A$7:$A$9972, Keys!$C$8, NEMS_residential!$DH$7:$DH$9972, Keys!$C$13, NEMS_residential!$G$7:$G$9972, Keys!$C$4) -> 5949267921
A17: 4 | B17: 4 West North Central | C17: heating | D17: =SUMIFS(NEMS_residential!P7:P9972, NEMS_residential!$A$7:$A$9972, Keys!$C$5, NEMS_residential!$DH$7:$DH$9972, Keys!$C$14, NEMS_residential!$G$7:$G$9972, Keys!$C$4) -> 836958547 | E17: =SUMIFS(NEMS_residential!Q7:Q9972, NEMS_residential!$A$7:$A$9972, Keys!$C$5, NEMS_residential!$DH$7:$DH$9972, Keys!$C$14, NEMS_residential!$G$7:$G$9972, Keys!$C$4) -> 850184269 | F17: =SUMIFS(NEMS_residential!R7:R9972, NEMS_residential!$A$7:$A$9972, Keys!$C$5, NEMS_residential!$DH$7:$DH$9972, Keys!$C$14, NEMS_residential!$G$7:$G$9972, Keys!$C$4) -> 862382716 | G17: =SUMIFS(NEMS_residential!S7:S9972, NEMS_residential!$A$7:$A$9972, Keys!$C$5, NEMS_residential!$DH$7:$DH$9972, Keys!$C$14, NEMS_residential!$G$7:$G$9972, Keys!$C$4) -> 839566892 | H17: =SUMIFS(NEMS_residential!T7:T9972, NEMS_residential!$A$7:$A$9972, Keys!$C$5, NEMS_residential!$DH$7:$DH$9972, Keys!$C$14, NEMS_residential!$G$7:$G$9972, Keys!$C$4) -> 820567389 | I17: =SUMIFS(NEMS_residential!U7:U9972, NEMS_residential!$A$7:$A$9972, Keys!$C$5, NEMS_residential!$DH$7:$DH$9972, Keys!$C$14, NEMS_residential!$G$7:$G$9972, Keys!$C$4) -> 799039463 | J17: =SUMIFS(NEMS_residential!V7:V9972, NEMS_residential!$A$7:$A$9972, Keys!$C$5, NEMS_residential!$DH$7:$DH$9972, Keys!$C$14, NEMS_residential!$G$7:$G$9972, Keys!$C$4) -> 780195175 | K17: =SUMIFS(NEMS_residential!W7:W9972, NEMS_residential!$A$7:$A$9972, Keys!$C$5, NEMS_residential!$DH$7:$DH$9972, Keys!$C$14, NEMS_residential!$G$7:$G$9972, Keys!$C$4) -> 769881080 | ... AD17: =SUMIFS(NEMS_residential!AP7:AP9972, NEMS_residential!$A$7:$A$9972, Keys!$C$5, NEMS_residential!$DH$7:$DH$9972, Keys!$C$14, NEMS_residential!$G$7:$G$9972, Keys!$C$4) -> 843578719
A18: 4 | B18: 4 West North Central | C18: cooling and ventilation | D18: =SUMIFS(NEMS_residential!P7:P9972, NEMS_residential!$A$7:$A$9972, Keys!$C$6, NEMS_residential!$DH$7:$DH$9972, Keys!$C$14, NEMS_residential!$G$7:$G$9972, Keys!$C$4) -> 1509345172 | E18: =SUMIFS(NEMS_residential!Q7:Q9972, NEMS_residential!$A$7:$A$9972, Keys!$C$6, NEMS_residential!$DH$7:$DH$9972, Keys!$C$14, NEMS_residential!$G$7:$G$9972, Keys!$C$4) -> 1477770239 | F18: =SUMIFS(NEMS_residential!R7:R9972, NEMS_residential!$A$7:$A$9972, Keys!$C$6, NEMS_residential!$DH$7:$DH$9972, Keys!$C$14, NEMS_residential!$G$7:$G$9972, Keys!$C$4) -> 1434434314 | G18: =SUMIFS(NEMS_residential!S7:S9972, NEMS_residential!$A$7:$A$9972, Keys!$C$6, NEMS_residential!$DH$7:$DH$9972, Keys!$C$14, NEMS_residential!$G$7:$G$9972, Keys!$C$4) -> 1396294431 | H18: =SUMIFS(NEMS_residential!T7:T9972, NEMS_residential!$A$7:$A$9972, Keys!$C$6, NEMS_residential!$DH$7:$DH$9972, Keys!$C$14, NEMS_residential!$G$7:$G$9972, Keys!$C$4) -> 1361897106 | I18: =SUMIFS(NEMS_residential!U7:U9972, NEMS_residential!$A$7:$A$9972, Keys!$C$6, NEMS_residential!$DH$7:$DH$9972, Keys!$C$14, NEMS_residential!$G$7:$G$9972, Keys!$C$4) -> 1338819662 | J18: =SUMIFS(NEMS_residential!V7:V9972, NEMS_residential!$A$7:$A$9972, Keys!$C$6, NEMS_residential!$DH$7:$DH$9972, Keys!$C$14, NEMS_residential!$G$7:$G$9972, Keys!$C$4) -> 1305652298 | K18: =SUMIFS(NEMS_residential!W7:W9972, NEMS_residential!$A$7:$A$9972, Keys!$C$6, NEMS_residential!$DH$7:$DH$9972, Keys!$C$14, NEMS_residential!$G$7:$G$9972, Keys!$C$4) -> 1271470322 | ... AD18: =SUMIFS(NEMS_residential!AP7:AP9972, NEMS_residential!$A$7:$A$9972, Keys!$C$6, NEMS_residential!$DH$7:$DH$9972, Keys!$C$14, NEMS_residential!$G$7:$G$9972, Keys!$C$4) -> 1375180096
A19: 4 | B19: 4 West North Central | C19: lighting | D19: =SUMIFS(NEMS_residential!P7:P9972, NEMS_residential!$A$7:$A$9972, Keys!$C$7, NEMS_residential!$DH$7:$DH$9972, Keys!$C$14, NEMS_residential!$G$7:$G$9972, Keys!$C$4) -> 129380904 | E19: =SUMIFS(NEMS_residential!Q7:Q9972, NEMS_residential!$A$7:$A$9972, Keys!$C$7, NEMS_residential!$DH$7:$DH$9972, Keys!$C$14, NEMS_residential!$G$7:$G$9972, Keys!$C$4) -> 122834064 | F19: =SUMIFS(NEMS_residential!R7:R9972, NEMS_residential!$A$7:$A$9972, Keys!$C$7, NEMS_residential!$DH$7:$DH$9972, Keys!$C$14, NEMS_residential!$G$7:$G$9972, Keys!$C$4) -> 117372656 | G19: =SUMIFS(NEMS_residential!S7:S9972, NEMS_residential!$A$7:$A$9972, Keys!$C$7, NEMS_residential!$DH$7:$DH$9972, Keys!$C$14, NEMS_residential!$G$7:$G$9972, Keys!$C$4) -> 111271314 | H19: =SUMIFS(NEMS_residential!T7:T9972, NEMS_residential!$A$7:$A$9972, Keys!$C$7, NEMS_residential!$DH$7:$DH$9972, Keys!$C$14, NEMS_residential!$G$7:$G$9972, Keys!$C$4) -> 107365530 | I19: =SUMIFS(NEMS_residential!U7:U9972, NEMS_residential!$A$7:$A$9972, Keys!$C$7, NEMS_residential!$DH$7:$DH$9972, Keys!$C$14, NEMS_residential!$G$7:$G$9972, Keys!$C$4) -> 108417596 | J19: =SUMIFS(NEMS_residential!V7:V9972, NEMS_residential!$A$7:$A$9972, Keys!$C$7, NEMS_residential!$DH$7:$DH$9972, Keys!$C$14, NEMS_residential!$G$7:$G$9972, Keys!$C$4) -> 81236294 | K19: =SUMIFS(NEMS_residential!W7:W9972, NEMS_residential!$A$7:$A$9972, Keys!$C$7, NEMS_residential!$DH$7:$DH$9972, Keys!$C$14, NEMS_residential!$G$7:$G$9972, Keys!$C$4) -> 83002380 | ... AD19: =SUMIFS(NEMS_residential!AP7:AP9972, NEMS_residential!$A$7:$A$9972, Keys!$C$7, NEMS_residential!$DH$7:$DH$9972, Keys!$C$14, NEMS_residential!$G$7:$G$9972, Keys!$C$4) -> 103431745
A20: 4 | B20: 4 West North Central | C20: appliances | D20: =SUMIFS(NEMS_residential!P7:P9972, NEMS_residential!$A$7:$A$9972, Keys!$C$8, NEMS_residential!$DH$7:$DH$9972, Keys!$C$14, NEMS_residential!$G$7:$G$9972, Keys!$C$4) -> 2705663427 | E20: =SUMIFS(NEMS_residential!Q7:Q9972, NEMS_residential!$A$7:$A$9972, Keys!$C$8, NEMS_residential!$DH$7:$DH$9972, Keys!$C$14, NEMS_residential!$G$7:$G$9972, Keys!$C$4) -> 2759351820 | F20: =SUMIFS(NEMS_residential!R7:R9972, NEMS_residential!$A$7:$A$9972, Keys!$C$8, NEMS_residential!$DH$7:$DH$9972, Keys!$C$14, NEMS_residential!$G$7:$G$9972, Keys!$C$4) -> 2830451669 | G20: =SUMIFS(NEMS_residential!S7:S9972, NEMS_residential!$A$7:$A$9972, Keys!$C$8, NEMS_residential!$DH$7:$DH$9972, Keys!$C$14, NEMS_residential!$G$7:$G$9972, Keys!$C$4) -> 2923054395 | H20: =SUMIFS(NEMS_residential!T7:T9972, NEMS_residential!$A$7:$A$9972, Keys!$C$8, NEMS_residential!$DH$7:$DH$9972, Keys!$C$14, NEMS_residential!$G$7:$G$9972, Keys!$C$4) -> 2914988748 | I20: =SUMIFS(NEMS_residential!U7:U9972, NEMS_residential!$A$7:$A$9972, Keys!$C$8, NEMS_residential!$DH$7:$DH$9972, Keys!$C$14, NEMS_residential!$G$7:$G$9972, Keys!$C$4) -> 2946048957 | J20: =SUMIFS(NEMS_residential!V7:V9972, NEMS_residential!$A$7:$A$9972, Keys!$C$8, NEMS_residential!$DH$7:$DH$9972, Keys!$C$14, NEMS_residential!$G$7:$G$9972, Keys!$C$4) -> 2986522005 | K20: =SUMIFS(NEMS_residential!W7:W9972, NEMS_residential!$A$7:$A$9972, Keys!$C$8, NEMS_residential!$DH$7:$DH$9972, Keys!$C$14, NEMS_residential!$G$7:$G$9972, Keys!$C$4) -> 3080723038 | ... AD20: =SUMIFS(NEMS_residential!AP7:AP9972, NEMS_residential!$A$7:$A$9972, Keys!$C$8, NEMS_residential!$DH$7:$DH$9972, Keys!$C$14, NEMS_residential!$G$7:$G$9972, Keys!$C$4) -> 3431586734
A21: 5 | B21: 5 South Atlantic | C21: heating | D21: =SUMIFS(NEMS_residential!P7:P9972, NEMS_residential!$A$7:$A$9972, Keys!$C$5, NEMS_residential!$DH$7:$DH$9972, Keys!$C$15, NEMS_residential!$G$7:$G$9972, Keys!$C$4) -> 4165291619 | E21: =SUMIFS(NEMS_residential!Q7:Q9972, NEMS_residential!$A$7:$A$9972, Keys!$C$5, NEMS_residential!$DH$7:$DH$9972, Keys!$C$15, NEMS_residential!$G$7:$G$9972, Keys!$C$4) -> 4180034638 | F21: =SUMIFS(NEMS_residential!R7:R9972, NEMS_residential!$A$7:$A$9972, Keys!$C$5, NEMS_residential!$DH$7:$DH$9972, Keys!$C$15, NEMS_residential!$G$7:$G$9972, Keys!$C$4) -> 4179192849 | G21: =SUMIFS(NEMS_residential!S7:S9972, NEMS_residential!$A$7:$A$9972, Keys!$C$5, NEMS_residential!$DH$7:$DH$9972, Keys!$C$15, NEMS_residential!$G$7:$G$9972, Keys!$C$4) -> 4153681581 | H21: =SUMIFS(NEMS_residential!T7:T9972, NEMS_residential!$A$7:$A$9972, Keys!$C$5, NEMS_residential!$DH$7:$DH$9972, Keys!$C$15, NEMS_residential!$G$7:$G$9972, Keys!$C$4) -> 4143378937 | I21: =SUMIFS(NEMS_residential!U7:U9972, NEMS_residential!$A$7:$A$9972, Keys!$C$5, NEMS_residential!$DH$7:$DH$9972, Keys!$C$15, NEMS_residential!$G$7:$G$9972, Keys!$C$4) -> 4142092653 | J21: =SUMIFS(NEMS_residential!V7:V9972, NEMS_residential!$A$7:$A$9972, Keys!$C$5, NEMS_residential!$DH$7:$DH$9972, Keys!$C$15, NEMS_residential!$G$7:$G$9972, Keys!$C$4) -> 4140571846 | K21: =SUMIFS(NEMS_residential!W7:W9972, NEMS_residential!$A$7:$A$9972, Keys!$C$5, NEMS_residential!$DH$7:$DH$9972, Keys!$C$15, NEMS_residential!$G$7:$G$9972, Keys!$C$4) -> 4171915589 | ... AD21: =SUMIFS(NEMS_residential!AP7:AP9972, NEMS_residential!$A$7:$A$9972, Keys!$C$5, NEMS_residential!$DH$7:$DH$9972, Keys!$C$15, NEMS_residential!$G$7:$G$9972, Keys!$C$4) -> 5039094587
A22: 5 | B22: 5 South Atlantic | C22: cooling and ventilation | D22: =SUMIFS(NEMS_residential!P7:P9972, NEMS_residential!$A$7:$A$9972, Keys!$C$6, NEMS_residential!$DH$7:$DH$9972, Keys!$C$15, NEMS_residential!$G$7:$G$9972, Keys!$C$4) -> 3152231874 | E22: =SUMIFS(NEMS_residential!Q7:Q9972, NEMS_residential!$A$7:$A$9972, Keys!$C$6, NEMS_residential!$DH$7:$DH$9972, Keys!$C$15, NEMS_residential!$G$7:$G$9972, Keys!$C$4) -> 3099175202 | F22: =SUMIFS(NEMS_residential!R7:R9972, NEMS_residential!$A$7:$A$9972, Keys!$C$6, NEMS_residential!$DH$7:$DH$9972, Keys!$C$15, NEMS_residential!$G$7:$G$9972, Keys!$C$4) -> 3020876441 | G22: =SUMIFS(NEMS_residential!S7:S9972, NEMS_residential!$A$7:$A$9972, Keys!$C$6, NEMS_residential!$DH$7:$DH$9972, Keys!$C$15, NEMS_residential!$G$7:$G$9972, Keys!$C$4) -> 2953782504 | H22: =SUMIFS(NEMS_residential!T7:T9972, NEMS_residential!$A$7:$A$9972, Keys!$C$6, NEMS_residential!$DH$7:$DH$9972, Keys!$C$15, NEMS_residential!$G$7:$G$9972, Keys!$C$4) -> 2895455692 | I22: =SUMIFS(NEMS_residential!U7:U9972, NEMS_residential!$A$7:$A$9972, Keys!$C$6, NEMS_residential!$DH$7:$DH$9972, Keys!$C$15, NEMS_residential!$G$7:$G$9972, Keys!$C$4) -> 2853265696 | J22: =SUMIFS(NEMS_residential!V7:V9972, NEMS_residential!$A$7:$A$9972, Keys!$C$6, NEMS_residential!$DH$7:$DH$9972, Keys!$C$15, NEMS_residential!$G$7:$G$9972, Keys!$C$4) -> 2788422966 | K22: =SUMIFS(NEMS_residential!W7:W9972, NEMS_residential!$A$7:$A$9972, Keys!$C$6, NEMS_residential!$DH$7:$DH$9972, Keys!$C$15, NEMS_residential!$G$7:$G$9972, Keys!$C$4) -> 2715855682 | ... AD22: =SUMIFS(NEMS_residential!AP7:AP9972, NEMS_residential!$A$7:$A$9972, Keys!$C$6, NEMS_residential!$DH$7:$DH$9972, Keys!$C$15, NEMS_residential!$G$7:$G$9972, Keys!$C$4) -> 3264369279
A23: 5 | B23: 5 South Atlantic | C23: lighting | D23: =SUMIFS(NEMS_residential!P7:P9972, NEMS_residential!$A$7:$A$9972, Keys!$C$7, NEMS_residential!$DH$7:$DH$9972, Keys!$C$15, NEMS_residential!$G$7:$G$9972, Keys!$C$4) -> 392197849 | E23: =SUMIFS(NEMS_residential!Q7:Q9972, NEMS_residential!$A$7:$A$9972, Keys!$C$7, NEMS_residential!$DH$7:$DH$9972, Keys!$C$15, NEMS_residential!$G$7:$G$9972, Keys!$C$4) -> 377114506 | F23: =SUMIFS(NEMS_residential!R7:R9972, NEMS_residential!$A$7:$A$9972, Keys!$C$7, NEMS_residential!$DH$7:$DH$9972, Keys!$C$15, NEMS_residential!$G$7:$G$9972, Keys!$C$4) -> 363093960 | G23: =SUMIFS(NEMS_residential!S7:S9972, NEMS_residential!$A$7:$A$9972, Keys!$C$7, NEMS_residential!$DH$7:$DH$9972, Keys!$C$15, NEMS_residential!$G$7:$G$9972, Keys!$C$4) -> 347816479 | H23: =SUMIFS(NEMS_residential!T7:T9972, NEMS_residential!$A$7:$A$9972, Keys!$C$7, NEMS_residential!$DH$7:$DH$9972, Keys!$C$15, NEMS_residential!$G$7:$G$9972, Keys!$C$4) -> 338898636 | I23: =SUMIFS(NEMS_residential!U7:U9972, NEMS_residential!$A$7:$A$9972, Keys!$C$7, NEMS_residential!$DH$7:$DH$9972, Keys!$C$15, NEMS_residential!$G$7:$G$9972, Keys!$C$4) -> 343268388 | J23: =SUMIFS(NEMS_residential!V7:V9972, NEMS_residential!$A$7:$A$9972, Keys!$C$7, NEMS_residential!$DH$7:$DH$9972, Keys!$C$15, NEMS_residential!$G$7:$G$9972, Keys!$C$4) -> 257486684 | K23: =SUMIFS(NEMS_residential!W7:W9972, NEMS_residential!$A$7:$A$9972, Keys!$C$7, NEMS_residential!$DH$7:$DH$9972, Keys!$C$15, NEMS_residential!$G$7:$G$9972, Keys!$C$4) -> 263022970 | ... AD23: =SUMIFS(NEMS_residential!AP7:AP9972, NEMS_residential!$A$7:$A$9972, Keys!$C$7, NEMS_residential!$DH$7:$DH$9972, Keys!$C$15, NEMS_residential!$G$7:$G$9972, Keys!$C$4) -> 338901594
A24: 5 | B24: 5 South Atlantic | C24: appliances | D24: =SUMIFS(NEMS_residential!P7:P9972, NEMS_residential!$A$7:$A$9972, Keys!$C$8, NEMS_residential!$DH$7:$DH$9972, Keys!$C$15, NEMS_residential!$G$7:$G$9972, Keys!$C$4) -> 7983339511 | E24: =SUMIFS(NEMS_residential!Q7:Q9972, NEMS_residential!$A$7:$A$9972, Keys!$C$8, NEMS_residential!$DH$7:$DH$9972, Keys!$C$15, NEMS_residential!$G$7:$G$9972, Keys!$C$4) -> 8215531171 | F24: =SUMIFS(NEMS_residential!R7:R9972, NEMS_residential!$A$7:$A$9972, Keys!$C$8, NEMS_residential!$DH$7:$DH$9972, Keys!$C$15, NEMS_residential!$G$7:$G$9972, Keys!$C$4) -> 8490512297 | G24: =SUMIFS(NEMS_residential!S7:S9972, NEMS_residential!$A$7:$A$9972, Keys!$C$8, NEMS_residential!$DH$7:$DH$9972, Keys!$C$15, NEMS_residential!$G$7:$G$9972, Keys!$C$4) -> 8770518992 | H24: =SUMIFS(NEMS_residential!T7:T9972, NEMS_residential!$A$7:$A$9972, Keys!$C$8, NEMS_residential!$DH$7:$DH$9972, Keys!$C$15, NEMS_residential!$G$7:$G$9972, Keys!$C$4) -> 8785850851 | I24: =SUMIFS(NEMS_residential!U7:U9972, NEMS_residential!$A$7:$A$9972, Keys!$C$8, NEMS_residential!$DH$7:$DH$9972, Keys!$C$15, NEMS_residential!$G$7:$G$9972, Keys!$C$4) -> 8916414540 | J24: =SUMIFS(NEMS_residential!V7:V9972, NEMS_residential!$A$7:$A$9972, Keys!$C$8, NEMS_residential!$DH$7:$DH$9972, Keys!$C$15, NEMS_residential!$G$7:$G$9972, Keys!$C$4) -> 9073180158 | K24: =SUMIFS(NEMS_residential!W7:W9972, NEMS_residential!$A$7:$A$9972, Keys!$C$8, NEMS_residential!$DH$7:$DH$9972, Keys!$C$15, NEMS_residential!$G$7:$G$9972, Keys!$C$4) -> 9334464985 | ... AD24: =SUMIFS(NEMS_residential!AP7:AP9972, NEMS_residential!$A$7:$A$9972, Keys!$C$8, NEMS_residential!$DH$7:$DH$9972, Keys!$C$15, NEMS_residential!$G$7:$G$9972, Keys!$C$4) -> 10174283701
A25: 6 | B25: 6 East South Central | C25: heating | D25: =SUMIFS(NEMS_residential!P7:P9972, NEMS_residential!$A$7:$A$9972, Keys!$C$5, NEMS_residential!$DH$7:$DH$9972, Keys!$C$16, NEMS_residential!$G$7:$G$9972, Keys!$C$4) -> 1236413994 | E25: =SUMIFS(NEMS_residential!Q7:Q9972, NEMS_residential!$A$7:$A$9972, Keys!$C$5, NEMS_residential!$DH$7:$DH$9972, Keys!$C$16, NEMS_residential!$G$7:$G$9972, Keys!$C$4) -> 1236344010 | F25: =SUMIFS(NEMS_residential!R7:R9972, NEMS_residential!$A$7:$A$9972, Keys!$C$5, NEMS_residential!$DH$7:$DH$9972, Keys!$C$16, NEMS_residential!$G$7:$G$9972, Keys!$C$4) -> 1231742291 | G25: =SUMIFS(NEMS_residential!S7:S9972, NEMS_residential!$A$7:$A$9972, Keys!$C$5, NEMS_residential!$DH$7:$DH$9972, Keys!$C$16, NEMS_residential!$G$7:$G$9972, Keys!$C$4) -> 1218688959 | H25: =SUMIFS(NEMS_residential!T7:T9972, NEMS_residential!$A$7:$A$9972, Keys!$C$5, NEMS_residential!$DH$7:$DH$9972, Keys!$C$16, NEMS_residential!$G$7:$G$9972, Keys!$C$4) -> 1210556816 | I25: =SUMIFS(NEMS_residential!U7:U9972, NEMS_residential!$A$7:$A$9972, Keys!$C$5, NEMS_residential!$DH$7:$DH$9972, Keys!$C$16, NEMS_residential!$G$7:$G$9972, Keys!$C$4) -> 1206340111 | J25: =SUMIFS(NEMS_residential!V7:V9972, NEMS_residential!$A$7:$A$9972, Keys!$C$5, NEMS_residential!$DH$7:$DH$9972, Keys!$C$16, NEMS_residential!$G$7:$G$9972, Keys!$C$4) -> 1204336426 | K25: =SUMIFS(NEMS_residential!W7:W9972, NEMS_residential!$A$7:$A$9972, Keys!$C$5, NEMS_residential!$DH$7:$DH$9972, Keys!$C$16, NEMS_residential!$G$7:$G$9972, Keys!$C$4) -> 1212063888 | ... AD25: =SUMIFS(NEMS_residential!AP7:AP9972, NEMS_residential!$A$7:$A$9972, Keys!$C$5, NEMS_residential!$DH$7:$DH$9972, Keys!$C$16, NEMS_residential!$G$7:$G$9972, Keys!$C$4) -> 1395860700
A26: 6 | B26: 6 East South Central | C26: cooling and ventilation | D26: =SUMIFS(NEMS_residential!P7:P9972, NEMS_residential!$A$7:$A$9972, Keys!$C$6, NEMS_residential!$DH$7:$DH$9972, Keys!$C$16, NEMS_residential!$G$7:$G$9972, Keys!$C$4) -> 925379350 | E26: =SUMIFS(NEMS_residential!Q7:Q9972, NEMS_residential!$A$7:$A$9972, Keys!$C$6, NEMS_residential!$DH$7:$DH$9972, Keys!$C$16, NEMS_residential!$G$7:$G$9972, Keys!$C$4) -> 907875066 | F26: =SUMIFS(NEMS_residential!R7:R9972, NEMS_residential!$A$7:$A$9972, Keys!$C$6, NEMS_residential!$DH$7:$DH$9972, Keys!$C$16, NEMS_residential!$G$7:$G$9972, Keys!$C$4) -> 883110675 | G26: =SUMIFS(NEMS_residential!S7:S9972, NEMS_residential!$A$7:$A$9972, Keys!$C$6, NEMS_residential!$DH$7:$DH$9972, Keys!$C$16, NEMS_residential!$G$7:$G$9972, Keys!$C$4) -> 861161735 | H26: =SUMIFS(NEMS_residential!T7:T9972, NEMS_residential!$A$7:$A$9972, Keys!$C$6, NEMS_residential!$DH$7:$DH$9972, Keys!$C$16, NEMS_residential!$G$7:$G$9972, Keys!$C$4) -> 842001413 | I26: =SUMIFS(NEMS_residential!U7:U9972, NEMS_residential!$A$7:$A$9972, Keys!$C$6, NEMS_residential!$DH$7:$DH$9972, Keys!$C$16, NEMS_residential!$G$7:$G$9972, Keys!$C$4) -> 826756348 | J26: =SUMIFS(NEMS_residential!V7:V9972, NEMS_residential!$A$7:$A$9972, Keys!$C$6, NEMS_residential!$DH$7:$DH$9972, Keys!$C$16, NEMS_residential!$G$7:$G$9972, Keys!$C$4) -> 803693613 | K26: =SUMIFS(NEMS_residential!W7:W9972, NEMS_residential!$A$7:$A$9972, Keys!$C$6, NEMS_residential!$DH$7:$DH$9972, Keys!$C$16, NEMS_residential!$G$7:$G$9972, Keys!$C$4) -> 777126338 | ... AD26: =SUMIFS(NEMS_residential!AP7:AP9972, NEMS_residential!$A$7:$A$9972, Keys!$C$6, NEMS_residential!$DH$7:$DH$9972, Keys!$C$16, NEMS_residential!$G$7:$G$9972, Keys!$C$4) -> 881353800
A27: 6 | B27: 6 East South Central | C27: lighting | D27: =SUMIFS(NEMS_residential!P7:P9972, NEMS_residential!$A$7:$A$9972, Keys!$C$7, NEMS_residential!$DH$7:$DH$9972, Keys!$C$16, NEMS_residential!$G$7:$G$9972, Keys!$C$4) -> 147837990 | E27: =SUMIFS(NEMS_residential!Q7:Q9972, NEMS_residential!$A$7:$A$9972, Keys!$C$7, NEMS_residential!$DH$7:$DH$9972, Keys!$C$16, NEMS_residential!$G$7:$G$9972, Keys!$C$4) -> 122666823 | F27: =SUMIFS(NEMS_residential!R7:R9972, NEMS_residential!$A$7:$A$9972, Keys!$C$7, NEMS_residential!$DH$7:$DH$9972, Keys!$C$16, NEMS_residential!$G$7:$G$9972, Keys!$C$4) -> 114976072 | G27: =SUMIFS(NEMS_residential!S7:S9972, NEMS_residential!$A$7:$A$9972, Keys!$C$7, NEMS_residential!$DH$7:$DH$9972, Keys!$C$16, NEMS_residential!$G$7:$G$9972, Keys!$C$4) -> 106768868 | H27: =SUMIFS(NEMS_residential!T7:T9972, NEMS_residential!$A$7:$A$9972, Keys!$C$7, NEMS_residential!$DH$7:$DH$9972, Keys!$C$16, NEMS_residential!$G$7:$G$9972, Keys!$C$4) -> 100339613 | I27: =SUMIFS(NEMS_residential!U7:U9972, NEMS_residential!$A$7:$A$9972, Keys!$C$7, NEMS_residential!$DH$7:$DH$9972, Keys!$C$16, NEMS_residential!$G$7:$G$9972, Keys!$C$4) -> 101192104 | J27: =SUMIFS(NEMS_residential!V7:V9972, NEMS_residential!$A$7:$A$9972, Keys!$C$7, NEMS_residential!$DH$7:$DH$9972, Keys!$C$16, NEMS_residential!$G$7:$G$9972, Keys!$C$4) -> 75650839 | K27: =SUMIFS(NEMS_residential!W7:W9972, NEMS_residential!$A$7:$A$9972, Keys!$C$7, NEMS_residential!$DH$7:$DH$9972, Keys!$C$16, NEMS_residential!$G$7:$G$9972, Keys!$C$4) -> 77163661 | ... AD27: =SUMIFS(NEMS_residential!AP7:AP9972, NEMS_residential!$A$7:$A$9972, Keys!$C$7, NEMS_residential!$DH$7:$DH$9972, Keys!$C$16, NEMS_residential!$G$7:$G$9972, Keys!$C$4) -> 96484781
A28: 6 | B28: 6 East South Central | C28: appliances | D28: =SUMIFS(NEMS_residential!P7:P9972, NEMS_residential!$A$7:$A$9972, Keys!$C$8, NEMS_residential!$DH$7:$DH$9972, Keys!$C$16, NEMS_residential!$G$7:$G$9972, Keys!$C$4) -> 2275604654 | E28: =SUMIFS(NEMS_residential!Q7:Q9972, NEMS_residential!$A$7:$A$9972, Keys!$C$8, NEMS_residential!$DH$7:$DH$9972, Keys!$C$16, NEMS_residential!$G$7:$G$9972, Keys!$C$4) -> 2336722718 | F28: =SUMIFS(NEMS_residential!R7:R9972, NEMS_residential!$A$7:$A$9972, Keys!$C$8, NEMS_residential!$DH$7:$DH$9972, Keys!$C$16, NEMS_residential!$G$7:$G$9972, Keys!$C$4) -> 2413059830 | G28: =SUMIFS(NEMS_residential!S7:S9972, NEMS_residential!$A$7:$A$9972, Keys!$C$8, NEMS_residential!$DH$7:$DH$9972, Keys!$C$16, NEMS_residential!$G$7:$G$9972, Keys!$C$4) -> 2489123934 | H28: =SUMIFS(NEMS_residential!T7:T9972, NEMS_residential!$A$7:$A$9972, Keys!$C$8, NEMS_residential!$DH$7:$DH$9972, Keys!$C$16, NEMS_residential!$G$7:$G$9972, Keys!$C$4) -> 2488202288 | I28: =SUMIFS(NEMS_residential!U7:U9972, NEMS_residential!$A$7:$A$9972, Keys!$C$8, NEMS_residential!$DH$7:$DH$9972, Keys!$C$16, NEMS_residential!$G$7:$G$9972, Keys!$C$4) -> 2521855018 | J28: =SUMIFS(NEMS_residential!V7:V9972, NEMS_residential!$A$7:$A$9972, Keys!$C$8, NEMS_residential!$DH$7:$DH$9972, Keys!$C$16, NEMS_residential!$G$7:$G$9972, Keys!$C$4) -> 2561203291 | K28: =SUMIFS(NEMS_residential!W7:W9972, NEMS_residential!$A$7:$A$9972, Keys!$C$8, NEMS_residential!$DH$7:$DH$9972, Keys!$C$16, NEMS_residential!$G$7:$G$9972, Keys!$C$4) -> 2627903450 | ... AD28: =SUMIFS(NEMS_residential!AP7:AP9972, NEMS_residential!$A$7:$A$9972, Keys!$C$8, NEMS_residential!$DH$7:$DH$9972, Keys!$C$16, NEMS_residential!$G$7:$G$9972, Keys!$C$4) -> 2640686147
A29: 7 | B29: 7 West South Central | C29: heating | D29: =SUMIFS(NEMS_residential!P7:P9972, NEMS_residential!$A$7:$A$9972, Keys!$C$5, NEMS_residential!$DH$7:$DH$9972, Keys!$C$17, NEMS_residential!$G$7:$G$9972, Keys!$C$4) -> 1537904710 | E29: =SUMIFS(NEMS_residential!Q7:Q9972, NEMS_residential!$A$7:$A$9972, Keys!$C$5, NEMS_residential!$DH$7:$DH$9972, Keys!$C$17, NEMS_residential!$G$7:$G$9972, Keys!$C$4) -> 1557698909 | F29: =SUMIFS(NEMS_residential!R7:R9972, NEMS_residential!$A$7:$A$9972, Keys!$C$5, NEMS_residential!$DH$7:$DH$9972, Keys!$C$17, NEMS_residential!$G$7:$G$9972, Keys!$C$4) -> 1572591807 | G29: =SUMIFS(NEMS_residential!S7:S9972, NEMS_residential!$A$7:$A$9972, Keys!$C$5, NEMS_residential!$DH$7:$DH$9972, Keys!$C$17, NEMS_residential!$G$7:$G$9972, Keys!$C$4) -> 1553825463 | H29: =SUMIFS(NEMS_residential!T7:T9972, NEMS_residential!$A$7:$A$9972, Keys!$C$5, NEMS_residential!$DH$7:$DH$9972, Keys!$C$17, NEMS_residential!$G$7:$G$9972, Keys!$C$4) -> 1541028522 | I29: =SUMIFS(NEMS_residential!U7:U9972, NEMS_residential!$A$7:$A$9972, Keys!$C$5, NEMS_residential!$DH$7:$DH$9972, Keys!$C$17, NEMS_residential!$G$7:$G$9972, Keys!$C$4) -> 1525467729 | J29: =SUMIFS(NEMS_residential!V7:V9972, NEMS_residential!$A$7:$A$9972, Keys!$C$5, NEMS_residential!$DH$7:$DH$9972, Keys!$C$17, NEMS_residential!$G$7:$G$9972, Keys!$C$4) -> 1508497707 | K29: =SUMIFS(NEMS_residential!W7:W9972, NEMS_residential!$A$7:$A$9972, Keys!$C$5, NEMS_residential!$DH$7:$DH$9972, Keys!$C$17, NEMS_residential!$G$7:$G$9972, Keys!$C$4) -> 1505456898 | ... AD29: =SUMIFS(NEMS_residential!AP7:AP9972, NEMS_residential!$A$7:$A$9972, Keys!$C$5, NEMS_residential!$DH$7:$DH$9972, Keys!$C$17, NEMS_residential!$G$7:$G$9972, Keys!$C$4) -> 1922947997
A30: 7 | B30: 7 West South Central | C30: cooling and ventilation | D30: =SUMIFS(NEMS_residential!P7:P9972, NEMS_residential!$A$7:$A$9972, Keys!$C$6, NEMS_residential!$DH$7:$DH$9972, Keys!$C$17, NEMS_residential!$G$7:$G$9972, Keys!$C$4) -> 2979842363 | E30: =SUMIFS(NEMS_residential!Q7:Q9972, NEMS_residential!$A$7:$A$9972, Keys!$C$6, NEMS_residential!$DH$7:$DH$9972, Keys!$C$17, NEMS_residential!$G$7:$G$9972, Keys!$C$4) -> 2935064879 | F30: =SUMIFS(NEMS_residential!R7:R9972, NEMS_residential!$A$7:$A$9972, Keys!$C$6, NEMS_residential!$DH$7:$DH$9972, Keys!$C$17, NEMS_residential!$G$7:$G$9972, Keys!$C$4) -> 2865950153 | G30: =SUMIFS(NEMS_residential!S7:S9972, NEMS_residential!$A$7:$A$9972, Keys!$C$6, NEMS_residential!$DH$7:$DH$9972, Keys!$C$17, NEMS_residential!$G$7:$G$9972, Keys!$C$4) -> 2809402259 | H30: =SUMIFS(NEMS_residential!T7:T9972, NEMS_residential!$A$7:$A$9972, Keys!$C$6, NEMS_residential!$DH$7:$DH$9972, Keys!$C$17, NEMS_residential!$G$7:$G$9972, Keys!$C$4) -> 2761074566 | I30: =SUMIFS(NEMS_residential!U7:U9972, NEMS_residential!$A$7:$A$9972, Keys!$C$6, NEMS_residential!$DH$7:$DH$9972, Keys!$C$17, NEMS_residential!$G$7:$G$9972, Keys!$C$4) -> 2729321231 | J30: =SUMIFS(NEMS_residential!V7:V9972, NEMS_residential!$A$7:$A$9972, Keys!$C$6, NEMS_residential!$DH$7:$DH$9972, Keys!$C$17, NEMS_residential!$G$7:$G$9972, Keys!$C$4) -> 2678285222 | K30: =SUMIFS(NEMS_residential!W7:W9972, NEMS_residential!$A$7:$A$9972, Keys!$C$6, NEMS_residential!$DH$7:$DH$9972, Keys!$C$17, NEMS_residential!$G$7:$G$9972, Keys!$C$4) -> 2622248334 | ... AD30: =SUMIFS(NEMS_residential!AP7:AP9972, NEMS_residential!$A$7:$A$9972, Keys!$C$6, NEMS_residential!$DH$7:$DH$9972, Keys!$C$17, NEMS_residential!$G$7:$G$9972, Keys!$C$4) -> 3227670509
A31: 7 | B31: 7 West South Central | C31: lighting | D31: =SUMIFS(NEMS_residential!P7:P9972, NEMS_residential!$A$7:$A$9972, Keys!$C$7, NEMS_residential!$DH$7:$DH$9972, Keys!$C$17, NEMS_residential!$G$7:$G$9972, Keys!$C$4) -> 299517390 | E31: =SUMIFS(NEMS_residential!Q7:Q9972, NEMS_residential!$A$7:$A$9972, Keys!$C$7, NEMS_residential!$DH$7:$DH$9972, Keys!$C$17, NEMS_residential!$G$7:$G$9972, Keys!$C$4) -> 258202393 | F31: =SUMIFS(NEMS_residential!R7:R9972, NEMS_residential!$A$7:$A$9972, Keys!$C$7, NEMS_residential!$DH$7:$DH$9972, Keys!$C$17, NEMS_residential!$G$7:$G$9972, Keys!$C$4) -> 245478969 | G31: =SUMIFS(NEMS_residential!S7:S9972, NEMS_residential!$A$7:$A$9972, Keys!$C$7, NEMS_residential!$DH$7:$DH$9972, Keys!$C$17, NEMS_residential!$G$7:$G$9972, Keys!$C$4) -> 232124480 | H31: =SUMIFS(NEMS_residential!T7:T9972, NEMS_residential!$A$7:$A$9972, Keys!$C$7, NEMS_residential!$DH$7:$DH$9972, Keys!$C$17, NEMS_residential!$G$7:$G$9972, Keys!$C$4) -> 222200090 | I31: =SUMIFS(NEMS_residential!U7:U9972, NEMS_residential!$A$7:$A$9972, Keys!$C$7, NEMS_residential!$DH$7:$DH$9972, Keys!$C$17, NEMS_residential!$G$7:$G$9972, Keys!$C$4) -> 225449727 | J31: =SUMIFS(NEMS_residential!V7:V9972, NEMS_residential!$A$7:$A$9972, Keys!$C$7, NEMS_residential!$DH$7:$DH$9972, Keys!$C$17, NEMS_residential!$G$7:$G$9972, Keys!$C$4) -> 169141370 | K31: =SUMIFS(NEMS_residential!W7:W9972, NEMS_residential!$A$7:$A$9972, Keys!$C$7, NEMS_residential!$DH$7:$DH$9972, Keys!$C$17, NEMS_residential!$G$7:$G$9972, Keys!$C$4) -> 172693883 | ... AD31: =SUMIFS(NEMS_residential!AP7:AP9972, NEMS_residential!$A$7:$A$9972, Keys!$C$7, NEMS_residential!$DH$7:$DH$9972, Keys!$C$17, NEMS_residential!$G$7:$G$9972, Keys!$C$4) -> 224834644
A32: 7 | B32: 7 West South Central | C32: appliances | D32: =SUMIFS(NEMS_residential!P7:P9972, NEMS_residential!$A$7:$A$9972, Keys!$C$8, NEMS_residential!$DH$7:$DH$9972, Keys!$C$17, NEMS_residential!$G$7:$G$9972, Keys!$C$4) -> 5122047524 | E32: =SUMIFS(NEMS_residential!Q7:Q9972, NEMS_residential!$A$7:$A$9972, Keys!$C$8, NEMS_residential!$DH$7:$DH$9972, Keys!$C$17, NEMS_residential!$G$7:$G$9972, Keys!$C$4) -> 5256157715 | F32: =SUMIFS(NEMS_residential!R7:R9972, NEMS_residential!$A$7:$A$9972, Keys!$C$8, NEMS_residential!$DH$7:$DH$9972, Keys!$C$17, NEMS_residential!$G$7:$G$9972, Keys!$C$4) -> 5416724614 | G32: =SUMIFS(NEMS_residential!S7:S9972, NEMS_residential!$A$7:$A$9972, Keys!$C$8, NEMS_residential!$DH$7:$DH$9972, Keys!$C$17, NEMS_residential!$G$7:$G$9972, Keys!$C$4) -> 5604403238 | H32: =SUMIFS(NEMS_residential!T7:T9972, NEMS_residential!$A$7:$A$9972, Keys!$C$8, NEMS_residential!$DH$7:$DH$9972, Keys!$C$17, NEMS_residential!$G$7:$G$9972, Keys!$C$4) -> 5632927118 | I32: =SUMIFS(NEMS_residential!U7:U9972, NEMS_residential!$A$7:$A$9972, Keys!$C$8, NEMS_residential!$DH$7:$DH$9972, Keys!$C$17, NEMS_residential!$G$7:$G$9972, Keys!$C$4) -> 5730938341 | J32: =SUMIFS(NEMS_residential!V7:V9972, NEMS_residential!$A$7:$A$9972, Keys!$C$8, NEMS_residential!$DH$7:$DH$9972, Keys!$C$17, NEMS_residential!$G$7:$G$9972, Keys!$C$4) -> 5846818574 | K32: =SUMIFS(NEMS_residential!W7:W9972, NEMS_residential!$A$7:$A$9972, Keys!$C$8, NEMS_residential!$DH$7:$DH$9972, Keys!$C$17, NEMS_residential!$G$7:$G$9972, Keys!$C$4) -> 6041491812 | ... AD32: =SUMIFS(NEMS_residential!AP7:AP9972, NEMS_residential!$A$7:$A$9972, Keys!$C$8, NEMS_residential!$DH$7:$DH$9972, Keys!$C$17, NEMS_residential!$G$7:$G$9972, Keys!$C$4) -> 7008987159
A33: 8 | B33: 8 Mountain | C33: heating | D33: =SUMIFS(NEMS_residential!P7:P9972, NEMS_residential!$A$7:$A$9972, Keys!$C$5, NEMS_residential!$DH$7:$DH$9972, Keys!$C$18, NEMS_residential!$G$7:$G$9972, Keys!$C$4) -> 1071454237 | E33: =SUMIFS(NEMS_residential!Q7:Q9972, NEMS_residential!$A$7:$A$9972, Keys!$C$5, NEMS_residential!$DH$7:$DH$9972, Keys!$C$18, NEMS_residential!$G$7:$G$9972, Keys!$C$4) -> 1083595959 | F33: =SUMIFS(NEMS_residential!R7:R9972, NEMS_residential!$A$7:$A$9972, Keys!$C$5, NEMS_residential!$DH$7:$DH$9972, Keys!$C$18, NEMS_residential!$G$7:$G$9972, Keys!$C$4) -> 1092732900 | G33: =SUMIFS(NEMS_residential!S7:S9972, NEMS_residential!$A$7:$A$9972, Keys!$C$5, NEMS_residential!$DH$7:$DH$9972, Keys!$C$18, NEMS_residential!$G$7:$G$9972, Keys!$C$4) -> 1075012651 | H33: =SUMIFS(NEMS_residential!T7:T9972, NEMS_residential!$A$7:$A$9972, Keys!$C$5, NEMS_residential!$DH$7:$DH$9972, Keys!$C$18, NEMS_residential!$G$7:$G$9972, Keys!$C$4) -> 1062022587 | I33: =SUMIFS(NEMS_residential!U7:U9972, NEMS_residential!$A$7:$A$9972, Keys!$C$5, NEMS_residential!$DH$7:$DH$9972, Keys!$C$18, NEMS_residential!$G$7:$G$9972, Keys!$C$4) -> 1047137923 | J33: =SUMIFS(NEMS_residential!V7:V9972, NEMS_residential!$A$7:$A$9972, Keys!$C$5, NEMS_residential!$DH$7:$DH$9972, Keys!$C$18, NEMS_residential!$G$7:$G$9972, Keys!$C$4) -> 1034618209 | K33: =SUMIFS(NEMS_residential!W7:W9972, NEMS_residential!$A$7:$A$9972, Keys!$C$5, NEMS_residential!$DH$7:$DH$9972, Keys!$C$18, NEMS_residential!$G$7:$G$9972, Keys!$C$4) -> 1032290944 | ... AD33: =SUMIFS(NEMS_residential!AP7:AP9972, NEMS_residential!$A$7:$A$9972, Keys!$C$5, NEMS_residential!$DH$7:$DH$9972, Keys!$C$18, NEMS_residential!$G$7:$G$9972, Keys!$C$4) -> 1201935189
A34: 8 | B34: 8 Mountain | C34: cooling and ventilation | D34: =SUMIFS(NEMS_residential!P7:P9972, NEMS_residential!$A$7:$A$9972, Keys!$C$6, NEMS_residential!$DH$7:$DH$9972, Keys!$C$18, NEMS_residential!$G$7:$G$9972, Keys!$C$4) -> 1674628709 | E34: =SUMIFS(NEMS_residential!Q7:Q9972, NEMS_residential!$A$7:$A$9972, Keys!$C$6, NEMS_residential!$DH$7:$DH$9972, Keys!$C$18, NEMS_residential!$G$7:$G$9972, Keys!$C$4) -> 1665809462 | F34: =SUMIFS(NEMS_residential!R7:R9972, NEMS_residential!$A$7:$A$9972, Keys!$C$6, NEMS_residential!$DH$7:$DH$9972, Keys!$C$18, NEMS_residential!$G$7:$G$9972, Keys!$C$4) -> 1648385839 | G34: =SUMIFS(NEMS_residential!S7:S9972, NEMS_residential!$A$7:$A$9972, Keys!$C$6, NEMS_residential!$DH$7:$DH$9972, Keys!$C$18, NEMS_residential!$G$7:$G$9972, Keys!$C$4) -> 1641252623 | H34: =SUMIFS(NEMS_residential!T7:T9972, NEMS_residential!$A$7:$A$9972, Keys!$C$6, NEMS_residential!$DH$7:$DH$9972, Keys!$C$18, NEMS_residential!$G$7:$G$9972, Keys!$C$4) -> 1641695543 | I34: =SUMIFS(NEMS_residential!U7:U9972, NEMS_residential!$A$7:$A$9972, Keys!$C$6, NEMS_residential!$DH$7:$DH$9972, Keys!$C$18, NEMS_residential!$G$7:$G$9972, Keys!$C$4) -> 1655196281 | J34: =SUMIFS(NEMS_residential!V7:V9972, NEMS_residential!$A$7:$A$9972, Keys!$C$6, NEMS_residential!$DH$7:$DH$9972, Keys!$C$18, NEMS_residential!$G$7:$G$9972, Keys!$C$4) -> 1664228890 | K34: =SUMIFS(NEMS_residential!W7:W9972, NEMS_residential!$A$7:$A$9972, Keys!$C$6, NEMS_residential!$DH$7:$DH$9972, Keys!$C$18, NEMS_residential!$G$7:$G$9972, Keys!$C$4) -> 1678602027 | ... AD34: =SUMIFS(NEMS_residential!AP7:AP9972, NEMS_residential!$A$7:$A$9972, Keys!$C$6, NEMS_residential!$DH$7:$DH$9972, Keys!$C$18, NEMS_residential!$G$7:$G$9972, Keys!$C$4) -> 2580270576
